Workbook

Sheet README
A1: MarginLab Pricing Lab — Operating Manual
A3: What this workbook does
A4: Takes your café menu, your costs, and (optionally) your sales history, and recommends a price for each item that improves profit while respecting psychological pricing rules, role-based caps, and reversibility constraints.
A6: How to use it (the short version)
A7: Step 1 — SETTINGS: pick currency, rounding step, ending preference, and guardrails. Step 2 — OWNER_INPUTS: enter your menu (name, category, role, cost, current price, monthly units). Step 3 — (optional) COMPETITOR_BENCHMARK: enter prices from 2-3 nearby cafés for items where market context matters. Step 4 — (optional) SALES_DATA: paste at least 60 daily price+quantity rows per item where you have real history. The model will estimate elasticity from your data. Step 5 — OWNER_RESULTS: read the headline lift, per-item recommendations, sensitivity check, and any data-quality warnings. Step 6 — QA_CHECKS: review any FLAG or FAIL items before sharing the file with a client.
A9: What gets calculated
A10: For each item: the profit-maximizing price under economic theory (Lerner), shrunk toward current price by a confidence factor, clamped to role and global guardrails, threshold-pulled below psychological round numbers, optionally snapped to charm endings (USD only), and rounded to the configured step. The workbook also computes the menu-engineering quadrant for each item, runs a three-scenario sensitivity analysis on elasticity, and (optionally) compares recommendations against local competitor prices.
A12: What "confidence" means here
A13: If you have given the model real daily sales data with genuine price variation, it estimates the price sensitivity of each item statistically and uses the high-confidence path. If you have not (most cafés have not), the model uses category-level priors and the low-confidence path, which produces smaller, more cautious recommendations and labels them "Pilot first."
A15: Sheets you (the owner) need to touch
A16: SETTINGS, OWNER_INPUTS, OWNER_RESULTS, and optionally COMPETITOR_BENCHMARK. Everything else is internal machinery — do not edit unless you know exactly what you are doing.
A18: Sheets the consultant operates
... A30: Quick navigation
A31: =HYPERLINK("#'SETTINGS'!A1","SETTINGS") -> SETTINGS | B31: Currency, rounding, guardrails, demo toggle
A32: =HYPERLINK("#'OWNER_INPUTS'!A1","OWNER_INPUTS") -> OWNER_INPUTS | B32: Your menu — name, category, role, cost, price, monthly units
A33: =HYPERLINK("#'COMPETITOR_BENCHMARK'!A1","COMPETITOR_BENCHMARK") -> COMPETITOR_BENCHMARK | B33: (Optional) local competitor prices and market position
A34: =HYPERLINK("#'OWNER_RESULTS'!A1","OWNER_RESULTS") -> OWNER_RESULTS | B34: The headline: lift, per-item recommendations, sensitivity
A35: =HYPERLINK("#'CATEGORY_PRIORS'!A1","CATEGORY_PRIORS") -> CATEGORY_PRIORS | B35: Default elasticities by category (used when no sales data)
A36: =HYPERLINK("#'PSYCHOLOGY_RULES'!A1","PSYCHOLOGY_RULES") -> PSYCHOLOGY_RULES | B36: Role caps and price-threshold pullbacks
A37: =HYPERLINK("#'MENU_ENGINEERING'!A1","MENU_ENGINEERING") -> MENU_ENGINEERING | B37: Star / Plowhorse / Puzzle / Dog classification
A38: =HYPERLINK("#'SALES_DATA'!A1","SALES_DATA") -> SALES_DATA | B38: (Optional) daily sales for elasticity estimation
A39: =HYPERLINK("#'CALIBRATION'!A1","CALIBRATION") -> CALIBRATION | B39: Per-item elasticity estimates with confidence intervals
A40: =HYPERLINK("#'OPTIMIZER'!A1","OPTIMIZER") -> OPTIMIZER | B40: Full Lerner → shrinkage → caps → rounding pipeline
A41: =HYPERLINK("#'SENSITIVITY'!A1","SENSITIVITY") -> SENSITIVITY | B41: Conservative / Baseline / Optimistic profit lift scenarios
A42: =HYPERLINK("#'QA_CHECKS'!A1","QA_CHECKS") -> QA_CHECKS | B42: Data-quality and model-sanity checks

Sheet SETTINGS
A1: Global Settings
A3: Currency & Rounding
A4: Currency | B4: USD | C4: Choose USD or IDR. Drives rounding and threshold rules.
A5: Round to nearest | B5: 0.1 | C5: For small-denomination currencies (USD/EUR/GBP/AUD/CAD): 0.01, 0.05, 0.10, 0.50, 1.00. For large-denomination currencies (IDR/JPY/VND): 500, 1000, 5000.
A6: Price ending preference | B6: .00 | C6: Examples: ".00", ".50", ".90", ".95", ".99". Used only when round_to ≤ 0.50 (i.e., small-denomination currencies like USD/EUR/GBP). Auto-disabled for high-denomination currencies like IDR/JPY. ".00" = no charm. Direction-preserving: charm never reverses the analytical recommendation.
A8: Global Guardrails
A9: Max raise per item | B9: 0.1 | C9: +10% by default. The single largest price increase the model will ever recommend.
A10: Max cut per item | B10: -0.05 | C10: -5% by default. The single largest price decrease the model will ever recommend.
A11: Confidence shrinkage (HIGH) | B11: 1 | C11: How much of the Lerner-optimal move to take when confidence is HIGH. 1.0 = take it all.
A12: Confidence shrinkage (MEDIUM) | B12: 0.5 | C12: How much of the Lerner-optimal move to take when confidence is MEDIUM.
A13: Confidence shrinkage (LOW) | B13: 0.25 | C13: How much of the Lerner-optimal move to take when confidence is LOW (prior only).
A15: Demo / Production Toggle
A16: Use sample SALES_DATA | B16: No | C16: "Yes" = run the model against the built-in synthetic demo. "No" = client production mode (uses category priors unless the client gives you real data).

Sheet OWNER_INPUTS
A1: Your Menu — Edit Here
A3: Fill in your real menu below. Up to 30 items. The recommendations on OWNER_RESULTS update automatically.
A5: # | B5: Item Name | C5: Category | D5: Role | E5: Cost per unit | F5: Current Price | G5: Units sold last month | H5: Notes (optional)
A6: 1 | B6: Flat White | C6: Coffee | D6: Traffic Driver | E6: 1 | F6: 4.2 | G6: 1500 | H6: Entry price — protect.
A7: 2 | B7: Matcha Latte | C7: Specialty Drink | D7: Profit Driver | E7: 1.4 | F7: 4.8 | G7: 1200 | H7: Higher margin specialty.
A8: 3 | B8: Eggs Benedict | C8: Sandwich/Food | D8: Signature | E8: 4.2 | F8: 9.8 | G8: 900 | H8: Brunch hero item.
A9: 4 | B9: Avocado Toast | C9: Sandwich/Food | D9: Core | E9: 4.5 | F9: 10.5 | G9: 1050
A10: 5 | B10: Pancakes | C10: Pastry | D10: Premium Anchor | E10: 3.5 | F10: 8.8 | G10: 750
A11: 6 | B11: Cheesecake | C11: Dessert | D11: Profit Driver | E11: 2.1 | F11: 5.8 | G11: 450 | H11: Pair with coffee.
A12: 7
A13: 8
A14: 9
A15: 10
A16: 11
A17: 12
A18: 13
A19: 14
A20: 15
A21: 16
A22: 17
A23: 18
... A35: 30
A37: How to use this tab:
A38: 1. | B38: Replace the 6 demo rows with your real menu. Use the dropdowns for Category and Role.
A39: 2. | B39: "Cost per unit" = what you pay in ingredients/labor to make ONE serving. Net of taxes.
A40: 3. | B40: "Units sold last month" = approximate monthly volume per item. ±20% is fine.
A41: 4. | B41: "Role" tells the model how aggressively to move each item. Use Traffic Driver for entry items the customer expects to be sharp. Use Profit Driver / Premium Anchor / Signature for items that can carry margin. Use Core for everyday items in between.
A42: 5. | B42: Open the OWNER_RESULTS tab to see what to do.

Sheet COMPETITOR_BENCHMARK
A1: Competitor Benchmark — Local Market Pricing Context
A3: Optional. Enter prices from 2–3 nearby cafés for items where market context matters (visible traffic drivers, signature items). The market average, min, and max are computed automatically. A flag fires in the rightmost column if the recommended price falls outside the local market range by more than the tolerance set below.
A5: Tolerance above market max | B5: 0.2 | C5: Default 20%. Recommendations more than this above market max are flagged "Above market."
A6: Tolerance below market min | B6: 0.2 | C6: Default 20%. Recommendations more than this below market min are flagged "Below market."
A8: # | B8: Item | C8: Current price | D8: Competitor 1 | E8: Competitor 2 | F8: Competitor 3 | G8: Market avg | H8: Market min | I8: Market max | J8: Rec price | K8: Position | L8: Flag
A9: 1 | B9: =IF(OWNER_INPUTS!B6="","",OWNER_INPUTS!B6) -> Flat White | C9: =IF($B9="","",OWNER_INPUTS!F6) -> 4.2 | G9: =IF($B9="","",IFERROR(AVERAGE($D9:$F9),"")) | H9: =IF($B9="","",IFERROR(IF(COUNT($D9:$F9)>0,MIN($D9:$F9),""),"")) | I9: =IF($B9="","",IFERROR(IF(COUNT($D9:$F9)>0,MAX($D9:$F9),""),"")) | J9: =IF($B9="","",OPTIMIZER!T6) -> 4.3 | K9: =IF($B9="","",IF(OR($G9="",NOT(ISNUMBER($G9))),"No comp data",IF($J9>$I9*(1+$B$5),"Above market",IF($J9<$H9*(1-$B$6),"Below market","Within market")))) -> No comp data | L9: =IF($B9="","",IF($K9="Above market","⚠ Above local market by >"&TEXT($B$5,"0%"),IF($K9="Below market","⚠ Below local market by >"&TEXT($B$6,"0%"),"")))
A10: 2 | B10: =IF(OWNER_INPUTS!B7="","",OWNER_INPUTS!B7) -> Matcha Latte | C10: =IF($B10="","",OWNER_INPUTS!F7) -> 4.8 | G10: =IF($B10="","",IFERROR(AVERAGE($D10:$F10),"")) | H10: =IF($B10="","",IFERROR(IF(COUNT($D10:$F10)>0,MIN($D10:$F10),""),"")) | I10: =IF($B10="","",IFERROR(IF(COUNT($D10:$F10)>0,MAX($D10:$F10),""),"")) | J10: =IF($B10="","",OPTIMIZER!T7) -> 4.9 | K10: =IF($B10="","",IF(OR($G10="",NOT(ISNUMBER($G10))),"No comp data",IF($J10>$I10*(1+$B$5),"Above market",IF($J10<$H10*(1-$B$6),"Below market","Within market")))) -> No comp data | L10: =IF($B10="","",IF($K10="Above market","⚠ Above local market by >"&TEXT($B$5,"0%"),IF($K10="Below market","⚠ Below local market by >"&TEXT($B$6,"0%"),"")))
A11: 3 | B11: =IF(OWNER_INPUTS!B8="","",OWNER_INPUTS!B8) -> Eggs Benedict | C11: =IF($B11="","",OWNER_INPUTS!F8) -> 9.8 | G11: =IF($B11="","",IFERROR(AVERAGE($D11:$F11),"")) | H11: =IF($B11="","",IFERROR(IF(COUNT($D11:$F11)>0,MIN($D11:$F11),""),"")) | I11: =IF($B11="","",IFERROR(IF(COUNT($D11:$F11)>0,MAX($D11:$F11),""),"")) | J11: =IF($B11="","",OPTIMIZER!T8) -> 9.9 | K11: =IF($B11="","",IF(OR($G11="",NOT(ISNUMBER($G11))),"No comp data",IF($J11>$I11*(1+$B$5),"Above market",IF($J11<$H11*(1-$B$6),"Below market","Within market")))) -> No comp data | L11: =IF($B11="","",IF($K11="Above market","⚠ Above local market by >"&TEXT($B$5,"0%"),IF($K11="Below market","⚠ Below local market by >"&TEXT($B$6,"0%"),"")))
A12: 4 | B12: =IF(OWNER_INPUTS!B9="","",OWNER_INPUTS!B9) -> Avocado Toast | C12: =IF($B12="","",OWNER_INPUTS!F9) -> 10.5 | G12: =IF($B12="","",IFERROR(AVERAGE($D12:$F12),"")) | H12: =IF($B12="","",IFERROR(IF(COUNT($D12:$F12)>0,MIN($D12:$F12),""),"")) | I12: =IF($B12="","",IFERROR(IF(COUNT($D12:$F12)>0,MAX($D12:$F12),""),"")) | J12: =IF($B12="","",OPTIMIZER!T9) -> 10.7 | K12: =IF($B12="","",IF(OR($G12="",NOT(ISNUMBER($G12))),"No comp data",IF($J12>$I12*(1+$B$5),"Above market",IF($J12<$H12*(1-$B$6),"Below market","Within market")))) -> No comp data | L12: =IF($B12="","",IF($K12="Above market","⚠ Above local market by >"&TEXT($B$5,"0%"),IF($K12="Below market","⚠ Below local market by >"&TEXT($B$6,"0%"),"")))
A13: 5 | B13: =IF(OWNER_INPUTS!B10="","",OWNER_INPUTS!B10) -> Pancakes | C13: =IF($B13="","",OWNER_INPUTS!F10) -> 8.8 | G13: =IF($B13="","",IFERROR(AVERAGE($D13:$F13),"")) | H13: =IF($B13="","",IFERROR(IF(COUNT($D13:$F13)>0,MIN($D13:$F13),""),"")) | I13: =IF($B13="","",IFERROR(IF(COUNT($D13:$F13)>0,MAX($D13:$F13),""),"")) | J13: =IF($B13="","",OPTIMIZER!T10) -> 9.2 | K13: =IF($B13="","",IF(OR($G13="",NOT(ISNUMBER($G13))),"No comp data",IF($J13>$I13*(1+$B$5),"Above market",IF($J13<$H13*(1-$B$6),"Below market","Within market")))) -> No comp data | L13: =IF($B13="","",IF($K13="Above market","⚠ Above local market by >"&TEXT($B$5,"0%"),IF($K13="Below market","⚠ Below local market by >"&TEXT($B$6,"0%"),"")))
A14: 6 | B14: =IF(OWNER_INPUTS!B11="","",OWNER_INPUTS!B11) -> Cheesecake | C14: =IF($B14="","",OWNER_INPUTS!F11) -> 5.8 | G14: =IF($B14="","",IFERROR(AVERAGE($D14:$F14),"")) | H14: =IF($B14="","",IFERROR(IF(COUNT($D14:$F14)>0,MIN($D14:$F14),""),"")) | I14: =IF($B14="","",IFERROR(IF(COUNT($D14:$F14)>0,MAX($D14:$F14),""),"")) | J14: =IF($B14="","",OPTIMIZER!T11) -> 6.1 | K14: =IF($B14="","",IF(OR($G14="",NOT(ISNUMBER($G14))),"No comp data",IF($J14>$I14*(1+$B$5),"Above market",IF($J14<$H14*(1-$B$6),"Below market","Within market")))) -> No comp data | L14: =IF($B14="","",IF($K14="Above market","⚠ Above local market by >"&TEXT($B$5,"0%"),IF($K14="Below market","⚠ Below local market by >"&TEXT($B$6,"0%"),"")))
A15: 7 | B15: =IF(OWNER_INPUTS!B12="","",OWNER_INPUTS!B12) | C15: =IF($B15="","",OWNER_INPUTS!F12) | G15: =IF($B15="","",IFERROR(AVERAGE($D15:$F15),"")) | H15: =IF($B15="","",IFERROR(IF(COUNT($D15:$F15)>0,MIN($D15:$F15),""),"")) | I15: =IF($B15="","",IFERROR(IF(COUNT($D15:$F15)>0,MAX($D15:$F15),""),"")) | J15: =IF($B15="","",OPTIMIZER!T12) | K15: =IF($B15="","",IF(OR($G15="",NOT(ISNUMBER($G15))),"No comp data",IF($J15>$I15*(1+$B$5),"Above market",IF($J15<$H15*(1-$B$6),"Below market","Within market")))) | L15: =IF($B15="","",IF($K15="Above market","⚠ Above local market by >"&TEXT($B$5,"0%"),IF($K15="Below market","⚠ Below local market by >"&TEXT($B$6,"0%"),"")))
A16: 8 | B16: =IF(OWNER_INPUTS!B13="","",OWNER_INPUTS!B13) | C16: =IF($B16="","",OWNER_INPUTS!F13) | G16: =IF($B16="","",IFERROR(AVERAGE($D16:$F16),"")) | H16: =IF($B16="","",IFERROR(IF(COUNT($D16:$F16)>0,MIN($D16:$F16),""),"")) | I16: =IF($B16="","",IFERROR(IF(COUNT($D16:$F16)>0,MAX($D16:$F16),""),"")) | J16: =IF($B16="","",OPTIMIZER!T13) | K16: =IF($B16="","",IF(OR($G16="",NOT(ISNUMBER($G16))),"No comp data",IF($J16>$I16*(1+$B$5),"Above market",IF($J16<$H16*(1-$B$6),"Below market","Within market")))) | L16: =IF($B16="","",IF($K16="Above market","⚠ Above local market by >"&TEXT($B$5,"0%"),IF($K16="Below market","⚠ Below local market by >"&TEXT($B$6,"0%"),"")))
A17: 9 | B17: =IF(OWNER_INPUTS!B14="","",OWNER_INPUTS!B14) | C17: =IF($B17="","",OWNER_INPUTS!F14) | G17: =IF($B17="","",IFERROR(AVERAGE($D17:$F17),"")) | H17: =IF($B17="","",IFERROR(IF(COUNT($D17:$F17)>0,MIN($D17:$F17),""),"")) | I17: =IF($B17="","",IFERROR(IF(COUNT($D17:$F17)>0,MAX($D17:$F17),""),"")) | J17: =IF($B17="","",OPTIMIZER!T14) | K17: =IF($B17="","",IF(OR($G17="",NOT(ISNUMBER($G17))),"No comp data",IF($J17>$I17*(1+$B$5),"Above market",IF($J17<$H17*(1-$B$6),"Below market","Within market")))) | L17: =IF($B17="","",IF($K17="Above market","⚠ Above local market by >"&TEXT($B$5,"0%"),IF($K17="Below market","⚠ Below local market by >"&TEXT($B$6,"0%"),"")))
A18: 10 | B18: =IF(OWNER_INPUTS!B15="","",OWNER_INPUTS!B15) | C18: =IF($B18="","",OWNER_INPUTS!F15) | G18: =IF($B18="","",IFERROR(AVERAGE($D18:$F18),"")) | H18: =IF($B18="","",IFERROR(IF(COUNT($D18:$F18)>0,MIN($D18:$F18),""),"")) | I18: =IF($B18="","",IFERROR(IF(COUNT($D18:$F18)>0,MAX($D18:$F18),""),"")) | J18: =IF($B18="","",OPTIMIZER!T15) | K18: =IF($B18="","",IF(OR($G18="",NOT(ISNUMBER($G18))),"No comp data",IF($J18>$I18*(1+$B$5),"Above market",IF($J18<$H18*(1-$B$6),"Below market","Within market")))) | L18: =IF($B18="","",IF($K18="Above market","⚠ Above local market by >"&TEXT($B$5,"0%"),IF($K18="Below market","⚠ Below local market by >"&TEXT($B$6,"0%"),"")))
A19: 11 | B19: =IF(OWNER_INPUTS!B16="","",OWNER_INPUTS!B16) | C19: =IF($B19="","",OWNER_INPUTS!F16) | G19: =IF($B19="","",IFERROR(AVERAGE($D19:$F19),"")) | H19: =IF($B19="","",IFERROR(IF(COUNT($D19:$F19)>0,MIN($D19:$F19),""),"")) | I19: =IF($B19="","",IFERROR(IF(COUNT($D19:$F19)>0,MAX($D19:$F19),""),"")) | J19: =IF($B19="","",OPTIMIZER!T16) | K19: =IF($B19="","",IF(OR($G19="",NOT(ISNUMBER($G19))),"No comp data",IF($J19>$I19*(1+$B$5),"Above market",IF($J19<$H19*(1-$B$6),"Below market","Within market")))) | L19: =IF($B19="","",IF($K19="Above market","⚠ Above local market by >"&TEXT($B$5,"0%"),IF($K19="Below market","⚠ Below local market by >"&TEXT($B$6,"0%"),"")))
A20: 12 | B20: =IF(OWNER_INPUTS!B17="","",OWNER_INPUTS!B17) | C20: =IF($B20="","",OWNER_INPUTS!F17) | G20: =IF($B20="","",IFERROR(AVERAGE($D20:$F20),"")) | H20: =IF($B20="","",IFERROR(IF(COUNT($D20:$F20)>0,MIN($D20:$F20),""),"")) | I20: =IF($B20="","",IFERROR(IF(COUNT($D20:$F20)>0,MAX($D20:$F20),""),"")) | J20: =IF($B20="","",OPTIMIZER!T17) | K20: =IF($B20="","",IF(OR($G20="",NOT(ISNUMBER($G20))),"No comp data",IF($J20>$I20*(1+$B$5),"Above market",IF($J20<$H20*(1-$B$6),"Below market","Within market")))) | L20: =IF($B20="","",IF($K20="Above market","⚠ Above local market by >"&TEXT($B$5,"0%"),IF($K20="Below market","⚠ Below local market by >"&TEXT($B$6,"0%"),"")))
... A38: 30 | B38: =IF(OWNER_INPUTS!B35="","",OWNER_INPUTS!B35) | C38: =IF($B38="","",OWNER_INPUTS!F35) | G38: =IF($B38="","",IFERROR(AVERAGE($D38:$F38),"")) | H38: =IF($B38="","",IFERROR(IF(COUNT($D38:$F38)>0,MIN($D38:$F38),""),"")) | I38: =IF($B38="","",IFERROR(IF(COUNT($D38:$F38)>0,MAX($D38:$F38),""),"")) | J38: =IF($B38="","",OPTIMIZER!T35) | K38: =IF($B38="","",IF(OR($G38="",NOT(ISNUMBER($G38))),"No comp data",IF($J38>$I38*(1+$B$5),"Above market",IF($J38<$H38*(1-$B$6),"Below market","Within market")))) | L38: =IF($B38="","",IF($K38="Above market","⚠ Above local market by >"&TEXT($B$5,"0%"),IF($K38="Below market","⚠ Below local market by >"&TEXT($B$6,"0%"),"")))
A40: Summary
A41: Items with competitor data | B41: =SUMPRODUCT(($B9:$B38<>"")*(ISNUMBER($G9:$G38))) -> 0
A42: Items priced above local market | B42: =COUNTIF($K9:$K38,"Above market") -> 0
A43: Items priced below local market | B43: =COUNTIF($K9:$K38,"Below market") -> 0
A44: Items within local market range | B44: =COUNTIF($K9:$K38,"Within market") -> 0

Sheet OWNER_RESULTS
A1: Your Pricing Recommendation
A2: Based on your menu and goals. Refresh each month or after major recipe/cost changes.
A3: =IF(OR(QA_CHECKS!C14="FLAG",QA_CHECKS!C15="FLAG",QA_CHECKS!C16="FLAG",QA_CHECKS!C17="FLAG",QA_CHECKS!C24="FLAG",QA_CHECKS!C27="FAIL",QA_CHECKS!C28="FAIL",QA_CHECKS!C29="FAIL",QA_CHECKS!C30="FAIL",QA_CHECKS!C31="FAIL"),"⚠ DATA QUALITY WARNING — One or more Hard QA checks are failing. Review QA_CHECKS before showing this to a client. Headline numbers below may be misleading.","")
A4: ESTIMATED MONTHLY PROFIT LIFT | C4: AS % OF CURRENT PROFIT | E4: ITEMS WITH A CHANGE | G4: CONFIDENCE LEVEL
A5: =opt_total_lift -> 372.23205 | C5: =opt_lift_pct -> 0.014394124 | E5: =COUNTIF(OPTIMIZER!U6:U35,"<>0")-COUNTBLANK(OPTIMIZER!U6:U35)&" of "&COUNTA(OPTIMIZER!B6:B35) -> 6 of 30 | G5: =QA_CHECKS!C32 -> LOW
A7: =cfg_currency&" per month, vs current" -> USD per month, vs current | C7: =IF(opt_baseline=0,"—","based on current contribution margin") -> based on current contribution margin | E7: "Hold" = no change recommended this cycle | G7: ="Best item: "&IFERROR(INDEX(OPTIMIZER!B6:B35,MATCH(maxifs(OPTIMIZER!X6:X35,OPTIMIZER!J6:J35,"HIGH",OPTIMIZER!B6:B35,"<>"),OPTIMIZER!X6:X35,0)),IFERROR(INDEX(OPTIMIZER!B6:B35,MATCH(maxifs(OPTIMIZER!X6:X35,OPTIMIZER!J6:J35,"MEDIUM",OPTIMIZER!B6:B35,"<>"),OPTIMIZER!X6:X35,0)),IFERROR(INDEX(OPTIMIZER!B6:B35,MATCH(MAX(OPTIMIZER!X6:X35),OPTIMIZER!X6:X35,0)),"no items configured"))) -> Best item: Pancakes
A9: What to do, item by item
A10: Item | B10: Action | C10: From | D10: To | E10: Δ % | F10: Monthly Δ profit | G10: Confidence | H10: Phase | I10: Quadrant | J10: Market | K10: Narrative
A11: =IF(OPTIMIZER!B6="","",OPTIMIZER!B6) -> Flat White | B11: =IF(OPTIMIZER!B6="","",IF(ABS(OPTIMIZER!U6)<0.005,"Hold",IF(OPTIMIZER!U6>0,"Raise","Cut"))) -> Raise | C11: =IF(OPTIMIZER!B6="","",OPTIMIZER!F6) -> 4.2 | D11: =IF(OPTIMIZER!B6="","",OPTIMIZER!T6) -> 4.3 | E11: =IF(OPTIMIZER!B6="","",OPTIMIZER!U6) -> 0.023809524 | F11: =IF(OPTIMIZER!B6="","",OPTIMIZER!X6) -> 23.520374 | G11: =IF(OPTIMIZER!B6="","",OPTIMIZER!J6) -> LOW | H11: =IF(OPTIMIZER!B6="","",IF(ABS(OPTIMIZER!U6)<0.005,"Hold",IF(OPTIMIZER!J6="HIGH","Now","Pilot first"))) -> Pilot first | I11: =IF(OPTIMIZER!B6="","",MENU_ENGINEERING!K10) -> Star | J11: =IF(OPTIMIZER!B6="","",COMPETITOR_BENCHMARK!K9) -> No comp data | K11: =IF(OPTIMIZER!B6="","",IF(ABS(OPTIMIZER!U6)<0.005,"Hold. ",IF(OPTIMIZER!U6>0,IF(OPTIMIZER!U6<0.02,"Small raise. ",IF(OPTIMIZER!U6<0.05,"Modest raise. ","Notable raise. ")),IF(OPTIMIZER!U6>-0.02,"Small cut. ",IF(OPTIMIZER!U6>-0.05,"Modest cut. ","Notable cut. "))))&IF(OPTIMIZER!D6="Traffic Driver","Traffic Driver — protect entry price. ",IF(AND(OR(OPTIMIZER!D6="Signature",OPTIMIZER!D6="Premium Anchor"),MENU_ENGINEERING!K10="Dog"),OPTIMIZER!D6&" role in Dog quadrant — protect intentionally. ",IF(MENU_ENGINEERING!K10="Star","Star — protect leadership. ",IF(MENU_ENGINEERING!K10="Plowhorse","Plowhorse — capture margin. ",IF(MENU_ENGINEERING!K10="Puzzle","Puzzle — promote or reposition. ",IF(MENU_ENGINEERING!K10="Dog","Dog — consider removal. ",""))))))&IF(OPTIMIZER!J6="HIGH","Ship now.",IF(OPTIMIZER!J6="MEDIUM","Test first.","Pilot small — using prior."))) -> Modest raise. Traffic Driver — protect entry price. Pilot small — using prior.
A12: =IF(OPTIMIZER!B7="","",OPTIMIZER!B7) -> Matcha Latte | B12: =IF(OPTIMIZER!B7="","",IF(ABS(OPTIMIZER!U7)<0.005,"Hold",IF(OPTIMIZER!U7>0,"Raise","Cut"))) -> Raise | C12: =IF(OPTIMIZER!B7="","",OPTIMIZER!F7) -> 4.8 | D12: =IF(OPTIMIZER!B7="","",OPTIMIZER!T7) -> 4.9 | E12: =IF(OPTIMIZER!B7="","",OPTIMIZER!U7) -> 0.020833333 | F12: =IF(OPTIMIZER!B7="","",OPTIMIZER!X7) -> 8.914175 | G12: =IF(OPTIMIZER!B7="","",OPTIMIZER!J7) -> LOW | H12: =IF(OPTIMIZER!B7="","",IF(ABS(OPTIMIZER!U7)<0.005,"Hold",IF(OPTIMIZER!J7="HIGH","Now","Pilot first"))) -> Pilot first | I12: =IF(OPTIMIZER!B7="","",MENU_ENGINEERING!K11) -> Star | J12: =IF(OPTIMIZER!B7="","",COMPETITOR_BENCHMARK!K10) -> No comp data | K12: =IF(OPTIMIZER!B7="","",IF(ABS(OPTIMIZER!U7)<0.005,"Hold. ",IF(OPTIMIZER!U7>0,IF(OPTIMIZER!U7<0.02,"Small raise. ",IF(OPTIMIZER!U7<0.05,"Modest raise. ","Notable raise. ")),IF(OPTIMIZER!U7>-0.02,"Small cut. ",IF(OPTIMIZER!U7>-0.05,"Modest cut. ","Notable cut. "))))&IF(OPTIMIZER!D7="Traffic Driver","Traffic Driver — protect entry price. ",IF(AND(OR(OPTIMIZER!D7="Signature",OPTIMIZER!D7="Premium Anchor"),MENU_ENGINEERING!K11="Dog"),OPTIMIZER!D7&" role in Dog quadrant — protect intentionally. ",IF(MENU_ENGINEERING!K11="Star","Star — protect leadership. ",IF(MENU_ENGINEERING!K11="Plowhorse","Plowhorse — capture margin. ",IF(MENU_ENGINEERING!K11="Puzzle","Puzzle — promote or reposition. ",IF(MENU_ENGINEERING!K11="Dog","Dog — consider removal. ",""))))))&IF(OPTIMIZER!J7="HIGH","Ship now.",IF(OPTIMIZER!J7="MEDIUM","Test first.","Pilot small — using prior."))) -> Modest raise. Star — protect leadership. Pilot small — using prior.
A13: =IF(OPTIMIZER!B8="","",OPTIMIZER!B8) -> Eggs Benedict | B13: =IF(OPTIMIZER!B8="","",IF(ABS(OPTIMIZER!U8)<0.005,"Hold",IF(OPTIMIZER!U8>0,"Raise","Cut"))) -> Raise | C13: =IF(OPTIMIZER!B8="","",OPTIMIZER!F8) -> 9.8 | D13: =IF(OPTIMIZER!B8="","",OPTIMIZER!T8) -> 9.9 | E13: =IF(OPTIMIZER!B8="","",OPTIMIZER!U8) -> 0.010204082 | F13: =IF(OPTIMIZER!B8="","",OPTIMIZER!X8) -> 48.503411 | G13: =IF(OPTIMIZER!B8="","",OPTIMIZER!J8) -> LOW | H13: =IF(OPTIMIZER!B8="","",IF(ABS(OPTIMIZER!U8)<0.005,"Hold",IF(OPTIMIZER!J8="HIGH","Now","Pilot first"))) -> Pilot first | I13: =IF(OPTIMIZER!B8="","",MENU_ENGINEERING!K12) -> Dog | J13: =IF(OPTIMIZER!B8="","",COMPETITOR_BENCHMARK!K11) -> No comp data | K13: =IF(OPTIMIZER!B8="","",IF(ABS(OPTIMIZER!U8)<0.005,"Hold. ",IF(OPTIMIZER!U8>0,IF(OPTIMIZER!U8<0.02,"Small raise. ",IF(OPTIMIZER!U8<0.05,"Modest raise. ","Notable raise. ")),IF(OPTIMIZER!U8>-0.02,"Small cut. ",IF(OPTIMIZER!U8>-0.05,"Modest cut. ","Notable cut. "))))&IF(OPTIMIZER!D8="Traffic Driver","Traffic Driver — protect entry price. ",IF(AND(OR(OPTIMIZER!D8="Signature",OPTIMIZER!D8="Premium Anchor"),MENU_ENGINEERING!K12="Dog"),OPTIMIZER!D8&" role in Dog quadrant — protect intentionally. ",IF(MENU_ENGINEERING!K12="Star","Star — protect leadership. ",IF(MENU_ENGINEERING!K12="Plowhorse","Plowhorse — capture margin. ",IF(MENU_ENGINEERING!K12="Puzzle","Puzzle — promote or reposition. ",IF(MENU_ENGINEERING!K12="Dog","Dog — consider removal. ",""))))))&IF(OPTIMIZER!J8="HIGH","Ship now.",IF(OPTIMIZER!J8="MEDIUM","Test first.","Pilot small — using prior."))) -> Small raise. Signature role in Dog quadrant — protect intentionally. Pilot small — using prior.
A14: =IF(OPTIMIZER!B9="","",OPTIMIZER!B9) -> Avocado Toast | B14: =IF(OPTIMIZER!B9="","",IF(ABS(OPTIMIZER!U9)<0.005,"Hold",IF(OPTIMIZER!U9>0,"Raise","Cut"))) -> Raise | C14: =IF(OPTIMIZER!B9="","",OPTIMIZER!F9) -> 10.5 | D14: =IF(OPTIMIZER!B9="","",OPTIMIZER!T9) -> 10.7 | E14: =IF(OPTIMIZER!B9="","",OPTIMIZER!U9) -> 0.019047619 | F14: =IF(OPTIMIZER!B9="","",OPTIMIZER!X9) -> 112.47088 | G14: =IF(OPTIMIZER!B9="","",OPTIMIZER!J9) -> LOW | H14: =IF(OPTIMIZER!B9="","",IF(ABS(OPTIMIZER!U9)<0.005,"Hold",IF(OPTIMIZER!J9="HIGH","Now","Pilot first"))) -> Pilot first | I14: =IF(OPTIMIZER!B9="","",MENU_ENGINEERING!K13) -> Plowhorse | J14: =IF(OPTIMIZER!B9="","",COMPETITOR_BENCHMARK!K12) -> No comp data | K14: =IF(OPTIMIZER!B9="","",IF(ABS(OPTIMIZER!U9)<0.005,"Hold. ",IF(OPTIMIZER!U9>0,IF(OPTIMIZER!U9<0.02,"Small raise. ",IF(OPTIMIZER!U9<0.05,"Modest raise. ","Notable raise. ")),IF(OPTIMIZER!U9>-0.02,"Small cut. ",IF(OPTIMIZER!U9>-0.05,"Modest cut. ","Notable cut. "))))&IF(OPTIMIZER!D9="Traffic Driver","Traffic Driver — protect entry price. ",IF(AND(OR(OPTIMIZER!D9="Signature",OPTIMIZER!D9="Premium Anchor"),MENU_ENGINEERING!K13="Dog"),OPTIMIZER!D9&" role in Dog quadrant — protect intentionally. ",IF(MENU_ENGINEERING!K13="Star","Star — protect leadership. ",IF(MENU_ENGINEERING!K13="Plowhorse","Plowhorse — capture margin. ",IF(MENU_ENGINEERING!K13="Puzzle","Puzzle — promote or reposition. ",IF(MENU_ENGINEERING!K13="Dog","Dog — consider removal. ",""))))))&IF(OPTIMIZER!J9="HIGH","Ship now.",IF(OPTIMIZER!J9="MEDIUM","Test first.","Pilot small — using prior."))) -> Small raise. Plowhorse — capture margin. Pilot small — using prior.
A15: =IF(OPTIMIZER!B10="","",OPTIMIZER!B10) -> Pancakes | B15: =IF(OPTIMIZER!B10="","",IF(ABS(OPTIMIZER!U10)<0.005,"Hold",IF(OPTIMIZER!U10>0,"Raise","Cut"))) -> Raise | C15: =IF(OPTIMIZER!B10="","",OPTIMIZER!F10) -> 8.8 | D15: =IF(OPTIMIZER!B10="","",OPTIMIZER!T10) -> 9.2 | E15: =IF(OPTIMIZER!B10="","",OPTIMIZER!U10) -> 0.045454545 | F15: =IF(OPTIMIZER!B10="","",OPTIMIZER!X10) -> 132.3478 | G15: =IF(OPTIMIZER!B10="","",OPTIMIZER!J10) -> LOW | H15: =IF(OPTIMIZER!B10="","",IF(ABS(OPTIMIZER!U10)<0.005,"Hold",IF(OPTIMIZER!J10="HIGH","Now","Pilot first"))) -> Pilot first | I15: =IF(OPTIMIZER!B10="","",MENU_ENGINEERING!K14) -> Dog | J15: =IF(OPTIMIZER!B10="","",COMPETITOR_BENCHMARK!K13) -> No comp data | K15: =IF(OPTIMIZER!B10="","",IF(ABS(OPTIMIZER!U10)<0.005,"Hold. ",IF(OPTIMIZER!U10>0,IF(OPTIMIZER!U10<0.02,"Small raise. ",IF(OPTIMIZER!U10<0.05,"Modest raise. ","Notable raise. ")),IF(OPTIMIZER!U10>-0.02,"Small cut. ",IF(OPTIMIZER!U10>-0.05,"Modest cut. ","Notable cut. "))))&IF(OPTIMIZER!D10="Traffic Driver","Traffic Driver — protect entry price. ",IF(AND(OR(OPTIMIZER!D10="Signature",OPTIMIZER!D10="Premium Anchor"),MENU_ENGINEERING!K14="Dog"),OPTIMIZER!D10&" role in Dog quadrant — protect intentionally. ",IF(MENU_ENGINEERING!K14="Star","Star — protect leadership. ",IF(MENU_ENGINEERING!K14="Plowhorse","Plowhorse — capture margin. ",IF(MENU_ENGINEERING!K14="Puzzle","Puzzle — promote or reposition. ",IF(MENU_ENGINEERING!K14="Dog","Dog — consider removal. ",""))))))&IF(OPTIMIZER!J10="HIGH","Ship now.",IF(OPTIMIZER!J10="MEDIUM","Test first.","Pilot small — using prior."))) -> Modest raise. Premium Anchor role in Dog quadrant — protect intentionally. Pilot small — using prior.
A16: =IF(OPTIMIZER!B11="","",OPTIMIZER!B11) -> Cheesecake | B16: =IF(OPTIMIZER!B11="","",IF(ABS(OPTIMIZER!U11)<0.005,"Hold",IF(OPTIMIZER!U11>0,"Raise","Cut"))) -> Raise | C16: =IF(OPTIMIZER!B11="","",OPTIMIZER!F11) -> 5.8 | D16: =IF(OPTIMIZER!B11="","",OPTIMIZER!T11) -> 6.1 | E16: =IF(OPTIMIZER!B11="","",OPTIMIZER!U11) -> 0.051724138 | F16: =IF(OPTIMIZER!B11="","",OPTIMIZER!X11) -> 46.47541 | G16: =IF(OPTIMIZER!B11="","",OPTIMIZER!J11) -> LOW | H16: =IF(OPTIMIZER!B11="","",IF(ABS(OPTIMIZER!U11)<0.005,"Hold",IF(OPTIMIZER!J11="HIGH","Now","Pilot first"))) -> Pilot first | I16: =IF(OPTIMIZER!B11="","",MENU_ENGINEERING!K15) -> Puzzle | J16: =IF(OPTIMIZER!B11="","",COMPETITOR_BENCHMARK!K14) -> No comp data | K16: =IF(OPTIMIZER!B11="","",IF(ABS(OPTIMIZER!U11)<0.005,"Hold. ",IF(OPTIMIZER!U11>0,IF(OPTIMIZER!U11<0.02,"Small raise. ",IF(OPTIMIZER!U11<0.05,"Modest raise. ","Notable raise. ")),IF(OPTIMIZER!U11>-0.02,"Small cut. ",IF(OPTIMIZER!U11>-0.05,"Modest cut. ","Notable cut. "))))&IF(OPTIMIZER!D11="Traffic Driver","Traffic Driver — protect entry price. ",IF(AND(OR(OPTIMIZER!D11="Signature",OPTIMIZER!D11="Premium Anchor"),MENU_ENGINEERING!K15="Dog"),OPTIMIZER!D11&" role in Dog quadrant — protect intentionally. ",IF(MENU_ENGINEERING!K15="Star","Star — protect leadership. ",IF(MENU_ENGINEERING!K15="Plowhorse","Plowhorse — capture margin. ",IF(MENU_ENGINEERING!K15="Puzzle","Puzzle — promote or reposition. ",IF(MENU_ENGINEERING!K15="Dog","Dog — consider removal. ",""))))))&IF(OPTIMIZER!J11="HIGH","Ship now.",IF(OPTIMIZER!J11="MEDIUM","Test first.","Pilot small — using prior."))) -> Notable raise. Puzzle — promote or reposition. Pilot small — using prior.
A17: =IF(OPTIMIZER!B12="","",OPTIMIZER!B12) | B17: =IF(OPTIMIZER!B12="","",IF(ABS(OPTIMIZER!U12)<0.005,"Hold",IF(OPTIMIZER!U12>0,"Raise","Cut"))) | C17: =IF(OPTIMIZER!B12="","",OPTIMIZER!F12) | D17: =IF(OPTIMIZER!B12="","",OPTIMIZER!T12) | E17: =IF(OPTIMIZER!B12="","",OPTIMIZER!U12) | F17: =IF(OPTIMIZER!B12="","",OPTIMIZER!X12) | G17: =IF(OPTIMIZER!B12="","",OPTIMIZER!J12) | H17: =IF(OPTIMIZER!B12="","",IF(ABS(OPTIMIZER!U12)<0.005,"Hold",IF(OPTIMIZER!J12="HIGH","Now","Pilot first"))) | I17: =IF(OPTIMIZER!B12="","",MENU_ENGINEERING!K16) | J17: =IF(OPTIMIZER!B12="","",COMPETITOR_BENCHMARK!K15) | K17: =IF(OPTIMIZER!B12="","",IF(ABS(OPTIMIZER!U12)<0.005,"Hold. ",IF(OPTIMIZER!U12>0,IF(OPTIMIZER!U12<0.02,"Small raise. ",IF(OPTIMIZER!U12<0.05,"Modest raise. ","Notable raise. ")),IF(OPTIMIZER!U12>-0.02,"Small cut. ",IF(OPTIMIZER!U12>-0.05,"Modest cut. ","Notable cut. "))))&IF(OPTIMIZER!D12="Traffic Driver","Traffic Driver — protect entry price. ",IF(AND(OR(OPTIMIZER!D12="Signature",OPTIMIZER!D12="Premium Anchor"),MENU_ENGINEERING!K16="Dog"),OPTIMIZER!D12&" role in Dog quadrant — protect intentionally. ",IF(MENU_ENGINEERING!K16="Star","Star — protect leadership. ",IF(MENU_ENGINEERING!K16="Plowhorse","Plowhorse — capture margin. ",IF(MENU_ENGINEERING!K16="Puzzle","Puzzle — promote or reposition. ",IF(MENU_ENGINEERING!K16="Dog","Dog — consider removal. ",""))))))&IF(OPTIMIZER!J12="HIGH","Ship now.",IF(OPTIMIZER!J12="MEDIUM","Test first.","Pilot small — using prior.")))
A18: =IF(OPTIMIZER!B13="","",OPTIMIZER!B13) | B18: =IF(OPTIMIZER!B13="","",IF(ABS(OPTIMIZER!U13)<0.005,"Hold",IF(OPTIMIZER!U13>0,"Raise","Cut"))) | C18: =IF(OPTIMIZER!B13="","",OPTIMIZER!F13) | D18: =IF(OPTIMIZER!B13="","",OPTIMIZER!T13) | E18: =IF(OPTIMIZER!B13="","",OPTIMIZER!U13) | F18: =IF(OPTIMIZER!B13="","",OPTIMIZER!X13) | G18: =IF(OPTIMIZER!B13="","",OPTIMIZER!J13) | H18: =IF(OPTIMIZER!B13="","",IF(ABS(OPTIMIZER!U13)<0.005,"Hold",IF(OPTIMIZER!J13="HIGH","Now","Pilot first"))) | I18: =IF(OPTIMIZER!B13="","",MENU_ENGINEERING!K17) | J18: =IF(OPTIMIZER!B13="","",COMPETITOR_BENCHMARK!K16) | K18: =IF(OPTIMIZER!B13="","",IF(ABS(OPTIMIZER!U13)<0.005,"Hold. ",IF(OPTIMIZER!U13>0,IF(OPTIMIZER!U13<0.02,"Small raise. ",IF(OPTIMIZER!U13<0.05,"Modest raise. ","Notable raise. ")),IF(OPTIMIZER!U13>-0.02,"Small cut. ",IF(OPTIMIZER!U13>-0.05,"Modest cut. ","Notable cut. "))))&IF(OPTIMIZER!D13="Traffic Driver","Traffic Driver — protect entry price. ",IF(AND(OR(OPTIMIZER!D13="Signature",OPTIMIZER!D13="Premium Anchor"),MENU_ENGINEERING!K17="Dog"),OPTIMIZER!D13&" role in Dog quadrant — protect intentionally. ",IF(MENU_ENGINEERING!K17="Star","Star — protect leadership. ",IF(MENU_ENGINEERING!K17="Plowhorse","Plowhorse — capture margin. ",IF(MENU_ENGINEERING!K17="Puzzle","Puzzle — promote or reposition. ",IF(MENU_ENGINEERING!K17="Dog","Dog — consider removal. ",""))))))&IF(OPTIMIZER!J13="HIGH","Ship now.",IF(OPTIMIZER!J13="MEDIUM","Test first.","Pilot small — using prior.")))
A19: =IF(OPTIMIZER!B14="","",OPTIMIZER!B14) | B19: =IF(OPTIMIZER!B14="","",IF(ABS(OPTIMIZER!U14)<0.005,"Hold",IF(OPTIMIZER!U14>0,"Raise","Cut"))) | C19: =IF(OPTIMIZER!B14="","",OPTIMIZER!F14) | D19: =IF(OPTIMIZER!B14="","",OPTIMIZER!T14) | E19: =IF(OPTIMIZER!B14="","",OPTIMIZER!U14) | F19: =IF(OPTIMIZER!B14="","",OPTIMIZER!X14) | G19: =IF(OPTIMIZER!B14="","",OPTIMIZER!J14) | H19: =IF(OPTIMIZER!B14="","",IF(ABS(OPTIMIZER!U14)<0.005,"Hold",IF(OPTIMIZER!J14="HIGH","Now","Pilot first"))) | I19: =IF(OPTIMIZER!B14="","",MENU_ENGINEERING!K18) | J19: =IF(OPTIMIZER!B14="","",COMPETITOR_BENCHMARK!K17) | K19: =IF(OPTIMIZER!B14="","",IF(ABS(OPTIMIZER!U14)<0.005,"Hold. ",IF(OPTIMIZER!U14>0,IF(OPTIMIZER!U14<0.02,"Small raise. ",IF(OPTIMIZER!U14<0.05,"Modest raise. ","Notable raise. ")),IF(OPTIMIZER!U14>-0.02,"Small cut. ",IF(OPTIMIZER!U14>-0.05,"Modest cut. ","Notable cut. "))))&IF(OPTIMIZER!D14="Traffic Driver","Traffic Driver — protect entry price. ",IF(AND(OR(OPTIMIZER!D14="Signature",OPTIMIZER!D14="Premium Anchor"),MENU_ENGINEERING!K18="Dog"),OPTIMIZER!D14&" role in Dog quadrant — protect intentionally. ",IF(MENU_ENGINEERING!K18="Star","Star — protect leadership. ",IF(MENU_ENGINEERING!K18="Plowhorse","Plowhorse — capture margin. ",IF(MENU_ENGINEERING!K18="Puzzle","Puzzle — promote or reposition. ",IF(MENU_ENGINEERING!K18="Dog","Dog — consider removal. ",""))))))&IF(OPTIMIZER!J14="HIGH","Ship now.",IF(OPTIMIZER!J14="MEDIUM","Test first.","Pilot small — using prior.")))
A20: =IF(OPTIMIZER!B15="","",OPTIMIZER!B15) | B20: =IF(OPTIMIZER!B15="","",IF(ABS(OPTIMIZER!U15)<0.005,"Hold",IF(OPTIMIZER!U15>0,"Raise","Cut"))) | C20: =IF(OPTIMIZER!B15="","",OPTIMIZER!F15) | D20: =IF(OPTIMIZER!B15="","",OPTIMIZER!T15) | E20: =IF(OPTIMIZER!B15="","",OPTIMIZER!U15) | F20: =IF(OPTIMIZER!B15="","",OPTIMIZER!X15) | G20: =IF(OPTIMIZER!B15="","",OPTIMIZER!J15) | H20: =IF(OPTIMIZER!B15="","",IF(ABS(OPTIMIZER!U15)<0.005,"Hold",IF(OPTIMIZER!J15="HIGH","Now","Pilot first"))) | I20: =IF(OPTIMIZER!B15="","",MENU_ENGINEERING!K19) | J20: =IF(OPTIMIZER!B15="","",COMPETITOR_BENCHMARK!K18) | K20: =IF(OPTIMIZER!B15="","",IF(ABS(OPTIMIZER!U15)<0.005,"Hold. ",IF(OPTIMIZER!U15>0,IF(OPTIMIZER!U15<0.02,"Small raise. ",IF(OPTIMIZER!U15<0.05,"Modest raise. ","Notable raise. ")),IF(OPTIMIZER!U15>-0.02,"Small cut. ",IF(OPTIMIZER!U15>-0.05,"Modest cut. ","Notable cut. "))))&IF(OPTIMIZER!D15="Traffic Driver","Traffic Driver — protect entry price. ",IF(AND(OR(OPTIMIZER!D15="Signature",OPTIMIZER!D15="Premium Anchor"),MENU_ENGINEERING!K19="Dog"),OPTIMIZER!D15&" role in Dog quadrant — protect intentionally. ",IF(MENU_ENGINEERING!K19="Star","Star — protect leadership. ",IF(MENU_ENGINEERING!K19="Plowhorse","Plowhorse — capture margin. ",IF(MENU_ENGINEERING!K19="Puzzle","Puzzle — promote or reposition. ",IF(MENU_ENGINEERING!K19="Dog","Dog — consider removal. ",""))))))&IF(OPTIMIZER!J15="HIGH","Ship now.",IF(OPTIMIZER!J15="MEDIUM","Test first.","Pilot small — using prior.")))
A21: =IF(OPTIMIZER!B16="","",OPTIMIZER!B16) | B21: =IF(OPTIMIZER!B16="","",IF(ABS(OPTIMIZER!U16)<0.005,"Hold",IF(OPTIMIZER!U16>0,"Raise","Cut"))) | C21: =IF(OPTIMIZER!B16="","",OPTIMIZER!F16) | D21: =IF(OPTIMIZER!B16="","",OPTIMIZER!T16) | E21: =IF(OPTIMIZER!B16="","",OPTIMIZER!U16) | F21: =IF(OPTIMIZER!B16="","",OPTIMIZER!X16) | G21: =IF(OPTIMIZER!B16="","",OPTIMIZER!J16) | H21: =IF(OPTIMIZER!B16="","",IF(ABS(OPTIMIZER!U16)<0.005,"Hold",IF(OPTIMIZER!J16="HIGH","Now","Pilot first"))) | I21: =IF(OPTIMIZER!B16="","",MENU_ENGINEERING!K20) | J21: =IF(OPTIMIZER!B16="","",COMPETITOR_BENCHMARK!K19) | K21: =IF(OPTIMIZER!B16="","",IF(ABS(OPTIMIZER!U16)<0.005,"Hold. ",IF(OPTIMIZER!U16>0,IF(OPTIMIZER!U16<0.02,"Small raise. ",IF(OPTIMIZER!U16<0.05,"Modest raise. ","Notable raise. ")),IF(OPTIMIZER!U16>-0.02,"Small cut. ",IF(OPTIMIZER!U16>-0.05,"Modest cut. ","Notable cut. "))))&IF(OPTIMIZER!D16="Traffic Driver","Traffic Driver — protect entry price. ",IF(AND(OR(OPTIMIZER!D16="Signature",OPTIMIZER!D16="Premium Anchor"),MENU_ENGINEERING!K20="Dog"),OPTIMIZER!D16&" role in Dog quadrant — protect intentionally. ",IF(MENU_ENGINEERING!K20="Star","Star — protect leadership. ",IF(MENU_ENGINEERING!K20="Plowhorse","Plowhorse — capture margin. ",IF(MENU_ENGINEERING!K20="Puzzle","Puzzle — promote or reposition. ",IF(MENU_ENGINEERING!K20="Dog","Dog — consider removal. ",""))))))&IF(OPTIMIZER!J16="HIGH","Ship now.",IF(OPTIMIZER!J16="MEDIUM","Test first.","Pilot small — using prior.")))
A22: =IF(OPTIMIZER!B17="","",OPTIMIZER!B17) | B22: =IF(OPTIMIZER!B17="","",IF(ABS(OPTIMIZER!U17)<0.005,"Hold",IF(OPTIMIZER!U17>0,"Raise","Cut"))) | C22: =IF(OPTIMIZER!B17="","",OPTIMIZER!F17) | D22: =IF(OPTIMIZER!B17="","",OPTIMIZER!T17) | E22: =IF(OPTIMIZER!B17="","",OPTIMIZER!U17) | F22: =IF(OPTIMIZER!B17="","",OPTIMIZER!X17) | G22: =IF(OPTIMIZER!B17="","",OPTIMIZER!J17) | H22: =IF(OPTIMIZER!B17="","",IF(ABS(OPTIMIZER!U17)<0.005,"Hold",IF(OPTIMIZER!J17="HIGH","Now","Pilot first"))) | I22: =IF(OPTIMIZER!B17="","",MENU_ENGINEERING!K21) | J22: =IF(OPTIMIZER!B17="","",COMPETITOR_BENCHMARK!K20) | K22: =IF(OPTIMIZER!B17="","",IF(ABS(OPTIMIZER!U17)<0.005,"Hold. ",IF(OPTIMIZER!U17>0,IF(OPTIMIZER!U17<0.02,"Small raise. ",IF(OPTIMIZER!U17<0.05,"Modest raise. ","Notable raise. ")),IF(OPTIMIZER!U17>-0.02,"Small cut. ",IF(OPTIMIZER!U17>-0.05,"Modest cut. ","Notable cut. "))))&IF(OPTIMIZER!D17="Traffic Driver","Traffic Driver — protect entry price. ",IF(AND(OR(OPTIMIZER!D17="Signature",OPTIMIZER!D17="Premium Anchor"),MENU_ENGINEERING!K21="Dog"),OPTIMIZER!D17&" role in Dog quadrant — protect intentionally. ",IF(MENU_ENGINEERING!K21="Star","Star — protect leadership. ",IF(MENU_ENGINEERING!K21="Plowhorse","Plowhorse — capture margin. ",IF(MENU_ENGINEERING!K21="Puzzle","Puzzle — promote or reposition. ",IF(MENU_ENGINEERING!K21="Dog","Dog — consider removal. ",""))))))&IF(OPTIMIZER!J17="HIGH","Ship now.",IF(OPTIMIZER!J17="MEDIUM","Test first.","Pilot small — using prior.")))
... A40: =IF(OPTIMIZER!B35="","",OPTIMIZER!B35) | B40: =IF(OPTIMIZER!B35="","",IF(ABS(OPTIMIZER!U35)<0.005,"Hold",IF(OPTIMIZER!U35>0,"Raise","Cut"))) | C40: =IF(OPTIMIZER!B35="","",OPTIMIZER!F35) | D40: =IF(OPTIMIZER!B35="","",OPTIMIZER!T35) | E40: =IF(OPTIMIZER!B35="","",OPTIMIZER!U35) | F40: =IF(OPTIMIZER!B35="","",OPTIMIZER!X35) | G40: =IF(OPTIMIZER!B35="","",OPTIMIZER!J35) | H40: =IF(OPTIMIZER!B35="","",IF(ABS(OPTIMIZER!U35)<0.005,"Hold",IF(OPTIMIZER!J35="HIGH","Now","Pilot first"))) | I40: =IF(OPTIMIZER!B35="","",MENU_ENGINEERING!K39) | J40: =IF(OPTIMIZER!B35="","",COMPETITOR_BENCHMARK!K38) | K40: =IF(OPTIMIZER!B35="","",IF(ABS(OPTIMIZER!U35)<0.005,"Hold. ",IF(OPTIMIZER!U35>0,IF(OPTIMIZER!U35<0.02,"Small raise. ",IF(OPTIMIZER!U35<0.05,"Modest raise. ","Notable raise. ")),IF(OPTIMIZER!U35>-0.02,"Small cut. ",IF(OPTIMIZER!U35>-0.05,"Modest cut. ","Notable cut. "))))&IF(OPTIMIZER!D35="Traffic Driver","Traffic Driver — protect entry price. ",IF(AND(OR(OPTIMIZER!D35="Signature",OPTIMIZER!D35="Premium Anchor"),MENU_ENGINEERING!K39="Dog"),OPTIMIZER!D35&" role in Dog quadrant — protect intentionally. ",IF(MENU_ENGINEERING!K39="Star","Star — protect leadership. ",IF(MENU_ENGINEERING!K39="Plowhorse","Plowhorse — capture margin. ",IF(MENU_ENGINEERING!K39="Puzzle","Puzzle — promote or reposition. ",IF(MENU_ENGINEERING!K39="Dog","Dog — consider removal. ",""))))))&IF(OPTIMIZER!J35="HIGH","Ship now.",IF(OPTIMIZER!J35="MEDIUM","Test first.","Pilot small — using prior.")))
A41: TOTAL MONTHLY Δ PROFIT | F41: =opt_total_lift -> 372.23205
A44: What this recommendation is based on
A45: Customer price sensitivity | B45: Estimated from your sales data if available (HIGH/MEDIUM confidence); otherwise category-level priors are used (LOW confidence — recommendations are smaller and labelled "Pilot first").
A46: Your guardrails | B46: ="No item moves more than "&TEXT(cfg_max_raise,"+0%")&" or less than "&TEXT(cfg_max_cut,"0%")&" — set on SETTINGS. Role-based caps are tighter for traffic-driver items." -> No item moves more than +10% or less than -5% — set on SETTINGS. Role-based caps are tighter for traffic-driver items.
A47: Your cost numbers | B47: Update OWNER_INPUTS!E column when costs change; recommendations refresh automatically.
A48: Psychology | B48: Prices are pulled below major thresholds (5.00, 10.00, etc. in USD; 5000, 10000 etc. in IDR) when they would otherwise just barely cross.
A50: Want to dig deeper?
A51: =HYPERLINK("#'OPTIMIZER'!A1","OPTIMIZER") -> OPTIMIZER | B51: See the full pipeline — Lerner math, shrinkage, role caps, guardrails, thresholds, rounding.
A52: =HYPERLINK("#'CALIBRATION'!A1","CALIBRATION") -> CALIBRATION | B52: See per-item elasticity estimates with 95% confidence intervals.
A53: =HYPERLINK("#'PSYCHOLOGY_RULES'!A1","PSYCHOLOGY_RULES") -> PSYCHOLOGY_RULES | B53: See the role caps and threshold tables that the model uses.
A54: =HYPERLINK("#'CATEGORY_PRIORS'!A1","CATEGORY_PRIORS") -> CATEGORY_PRIORS | B54: Edit the default category elasticities used when data is missing.
A55: =HYPERLINK("#'MENU_ENGINEERING'!A1","MENU_ENGINEERING") -> MENU_ENGINEERING | B55: See how each item is classified as Star, Plowhorse, Puzzle, or Dog.
A56: =HYPERLINK("#'SENSITIVITY'!A1","SENSITIVITY") -> SENSITIVITY | B56: See the conservative / baseline / optimistic profit lift under different elasticity assumptions.
A57: =HYPERLINK("#'COMPETITOR_BENCHMARK'!A1","COMPETITOR_BENCHMARK") -> COMPETITOR_BENCHMARK | B57: Enter local competitor prices (optional) to see if any recommendation breaches the local market range.
A60: Sensitivity Check
A61: Conservative (e×1.2) | B61: =SENSITIVITY!H40 -> 247.96726 | C61: Profit lift if customers are MORE price-sensitive than assumed.
A62: Baseline (e×1.0) | B62: =SENSITIVITY!I40 -> 372.23205 | C62: Profit lift at the baseline elasticity used by the optimizer.
A63: Optimistic (e×0.8) | B63: =SENSITIVITY!J40 -> 497.25255 | C63: Profit lift if customers are LESS price-sensitive than assumed.
A64: Robust? | B64: =IF(AND(SENSITIVITY!H40>=0,SENSITIVITY!I40>=0,SENSITIVITY!J40>=0),"Yes — positive across all scenarios","No — at least one scenario negative") -> Yes — positive across all scenarios

Sheet CATEGORY_PRIORS
A1: Category Elasticity Priors (used when no client data is available)
A3: Each row is a default own-price elasticity assumption used when the model has no client-specific data. Negative numbers — more negative means customers react more strongly to price changes. These are starting assumptions only. Replace with estimates from CALIBRATION as real data comes in.
A5: Category | B5: Elasticity (prior) | C5: Source | D5: Sensitivity tier | E5: Notes
A6: Coffee | B6: -1.1 | C6: Manual Tab 4 | D6: Moderate | E6: Daily routine; competitive market.
A7: Specialty Drink | B7: -1.3 | C7: Manual Tab 4 | D7: Sensitive | E7: Substitutes within drink menu.
A8: Tea | B8: -1 | C8: Manual Tab 4 | D8: Moderate | E8: Comparable to coffee but lower volume.
A9: Pastry | B9: -0.9 | C9: Manual Tab 4 | D9: Inelastic | E9: Often impulse-bought as add-on.
A10: Dessert | B10: -1 | C10: Manual Tab 4 | D10: Moderate | E10: Special occasion items.
A11: Sandwich/Food | B11: -0.8 | C11: Manual Tab 4 | D11: Inelastic | E11: Brunch and food less substitutable.
A12: Bundle | B12: -0.95 | C12: Estimated | D12: Moderate | E12: Treat as basket; cross effects apply.
A13: Complement | B13: -0.7 | C13: Estimated | D13: Inelastic | E13: Sides, add-ons; basket effect dominates.
A14: Other | B14: -1.1 | C14: Default | D14: Moderate | E14: Fallback when category is unspecified.

Sheet PSYCHOLOGY_RULES
A1: Psychology Rules — Role caps and threshold management
A3: These rules constrain raw model output to keep recommendations psychologically credible. Role caps limit how much any single item can move, by its strategic role on the menu. Test increments are the small moves used when confidence is LOW — when the model is working off priors, not real data.
A5: Role caps
A6: Role | B6: Max raise (role cap) | C6: Max cut (role floor) | D6: Test increment (LOW conf.) | E6: Description | F6: Default action when no data
A7: Traffic Driver | B7: 0.03 | C7: -0.05 | D7: 0 | E7: Sharp entry price that signals fairness. Protect. | F7: Hold
A8: Core | B8: 0.06 | C8: -0.05 | D8: 0.02 | E8: High-volume standard menu item. Moderate moves OK. | F8: Small test raise
A9: Profit Driver | B9: 0.1 | C9: -0.05 | D9: 0.05 | E9: High-margin item that can carry most of the gain. | F9: Modest test raise
A10: Premium Anchor | B10: 0.1 | C10: -0.05 | D10: 0.05 | E10: Expensive reference point; protect premium feel. | F10: Modest test raise
A11: Signature | B11: 0.1 | C11: -0.05 | D11: 0.05 | E11: Brand-defining item; can carry premium pricing. | F11: Modest test raise
A12: Complement | B12: 0.07 | C12: -0.05 | D12: 0.03 | E12: Side/add-on; basket effect dominates. | F12: Small test raise
A13: Other | B13: 0.05 | C13: -0.05 | D13: 0.02 | E13: Unspecified role — conservative default. | F13: Small test raise
A16: Psychological thresholds
A17: If the rounded recommended price would land within "Buffer" above one of these thresholds, the model pulls the price down to threshold - 0.05 (USD) or threshold - 500 (IDR) instead. These represent perceptual jumps customers notice.
A19: USD thresholds | B19: Buffer (USD) | D19: IDR thresholds | E19: Buffer (IDR)
A20: 1 | B20: 0.2 | D20: 5000 | E20: 500
A21: 2 | B21: 0.2 | D21: 10000 | E21: 500
A22: 5 | B22: 0.2 | D22: 15000 | E22: 500
A23: 10 | B23: 0.3 | D23: 25000 | E23: 1000
A24: 15 | B24: 0.3 | D24: 50000 | E24: 1500
A25: 20 | B25: 0.4 | D25: 75000 | E25: 2000
A26: 50 | B26: 0.5 | D26: 100000 | E26: 3000
A27: 100 | B27: 1 | D27: 150000 | E27: 4000

Sheet MENU_ENGINEERING
A1: Menu Engineering — Star / Plowhorse / Puzzle / Dog
A3: Classifies each item by popularity (monthly units) and margin %, using menu medians as thresholds. Items above median on both axes are Stars; below on both are Dogs. The quadrant guides the recommended action.
A5: Median monthly units | B5: =IFERROR(MEDIAN($E$10:$E$39),0) -> 975 | C5: Items at or above this volume → "high popularity"
A6: Median margin % | B6: =IFERROR(MEDIAN($H$10:$H$39),0) -> 0.62010188 | C6: Items at or above this margin → "high margin"
A9: # | B9: Item | C9: Category | D9: Role | E9: Monthly units | F9: Unit margin | G9: Monthly profit | H9: Margin % | I9: Popularity tier | J9: Margin tier | K9: Quadrant | L9: Action | M9: Narrative
A10: 1 | B10: =IF(OWNER_INPUTS!B6="","",OWNER_INPUTS!B6) -> Flat White | C10: =IF($B10="","",OWNER_INPUTS!C6) -> Coffee | D10: =IF($B10="","",OWNER_INPUTS!D6) -> Traffic Driver | E10: =IF($B10="","",OWNER_INPUTS!G6) -> 1500 | F10: =IF($B10="","",OWNER_INPUTS!F6-OWNER_INPUTS!E6) -> 3.2 | G10: =IF($B10="","",$E10*$F10) -> 4800 | H10: =IF($B10="","",IF(OWNER_INPUTS!F6>0,$F10/OWNER_INPUTS!F6,0)) -> 0.76190476 | I10: =IF($B10="","",IF($E10>=$B$5,"High","Low")) -> High | J10: =IF($B10="","",IF($H10>=$B$6,"High","Low")) -> High | K10: =IF($B10="","",IF(AND($I10="High",$J10="High"),"Star",IF(AND($I10="High",$J10="Low"),"Plowhorse",IF(AND($I10="Low",$J10="High"),"Puzzle","Dog")))) -> Star | L10: =IF($B10="","",IF($K10="Star","Hold / protect leadership",IF($K10="Plowhorse","Modest raise to capture margin",IF($K10="Puzzle","Reposition / promote / test premium","Consider removal or simplification")))) -> Hold / protect leadership | M10: =IF($B10="","",$K10&" ("&$I10&" volume, "&$J10&" margin). "&$L10&".") -> Star (High volume, High margin). Hold / protect leadership.
A11: 2 | B11: =IF(OWNER_INPUTS!B7="","",OWNER_INPUTS!B7) -> Matcha Latte | C11: =IF($B11="","",OWNER_INPUTS!C7) -> Specialty Drink | D11: =IF($B11="","",OWNER_INPUTS!D7) -> Profit Driver | E11: =IF($B11="","",OWNER_INPUTS!G7) -> 1200 | F11: =IF($B11="","",OWNER_INPUTS!F7-OWNER_INPUTS!E7) -> 3.4 | G11: =IF($B11="","",$E11*$F11) -> 4080 | H11: =IF($B11="","",IF(OWNER_INPUTS!F7>0,$F11/OWNER_INPUTS!F7,0)) -> 0.70833333 | I11: =IF($B11="","",IF($E11>=$B$5,"High","Low")) -> High | J11: =IF($B11="","",IF($H11>=$B$6,"High","Low")) -> High | K11: =IF($B11="","",IF(AND($I11="High",$J11="High"),"Star",IF(AND($I11="High",$J11="Low"),"Plowhorse",IF(AND($I11="Low",$J11="High"),"Puzzle","Dog")))) -> Star | L11: =IF($B11="","",IF($K11="Star","Hold / protect leadership",IF($K11="Plowhorse","Modest raise to capture margin",IF($K11="Puzzle","Reposition / promote / test premium","Consider removal or simplification")))) -> Hold / protect leadership | M11: =IF($B11="","",$K11&" ("&$I11&" volume, "&$J11&" margin). "&$L11&".") -> Star (High volume, High margin). Hold / protect leadership.
A12: 3 | B12: =IF(OWNER_INPUTS!B8="","",OWNER_INPUTS!B8) -> Eggs Benedict | C12: =IF($B12="","",OWNER_INPUTS!C8) -> Sandwich/Food | D12: =IF($B12="","",OWNER_INPUTS!D8) -> Signature | E12: =IF($B12="","",OWNER_INPUTS!G8) -> 900 | F12: =IF($B12="","",OWNER_INPUTS!F8-OWNER_INPUTS!E8) -> 5.6 | G12: =IF($B12="","",$E12*$F12) -> 5040 | H12: =IF($B12="","",IF(OWNER_INPUTS!F8>0,$F12/OWNER_INPUTS!F8,0)) -> 0.57142857 | I12: =IF($B12="","",IF($E12>=$B$5,"High","Low")) -> Low | J12: =IF($B12="","",IF($H12>=$B$6,"High","Low")) -> Low | K12: =IF($B12="","",IF(AND($I12="High",$J12="High"),"Star",IF(AND($I12="High",$J12="Low"),"Plowhorse",IF(AND($I12="Low",$J12="High"),"Puzzle","Dog")))) -> Dog | L12: =IF($B12="","",IF($K12="Star","Hold / protect leadership",IF($K12="Plowhorse","Modest raise to capture margin",IF($K12="Puzzle","Reposition / promote / test premium","Consider removal or simplification")))) -> Consider removal or simplification | M12: =IF($B12="","",$K12&" ("&$I12&" volume, "&$J12&" margin). "&$L12&".") -> Dog (Low volume, Low margin). Consider removal or simplification.
A13: 4 | B13: =IF(OWNER_INPUTS!B9="","",OWNER_INPUTS!B9) -> Avocado Toast | C13: =IF($B13="","",OWNER_INPUTS!C9) -> Sandwich/Food | D13: =IF($B13="","",OWNER_INPUTS!D9) -> Core | E13: =IF($B13="","",OWNER_INPUTS!G9) -> 1050 | F13: =IF($B13="","",OWNER_INPUTS!F9-OWNER_INPUTS!E9) -> 6 | G13: =IF($B13="","",$E13*$F13) -> 6300 | H13: =IF($B13="","",IF(OWNER_INPUTS!F9>0,$F13/OWNER_INPUTS!F9,0)) -> 0.57142857 | I13: =IF($B13="","",IF($E13>=$B$5,"High","Low")) -> High | J13: =IF($B13="","",IF($H13>=$B$6,"High","Low")) -> Low | K13: =IF($B13="","",IF(AND($I13="High",$J13="High"),"Star",IF(AND($I13="High",$J13="Low"),"Plowhorse",IF(AND($I13="Low",$J13="High"),"Puzzle","Dog")))) -> Plowhorse | L13: =IF($B13="","",IF($K13="Star","Hold / protect leadership",IF($K13="Plowhorse","Modest raise to capture margin",IF($K13="Puzzle","Reposition / promote / test premium","Consider removal or simplification")))) -> Modest raise to capture margin | M13: =IF($B13="","",$K13&" ("&$I13&" volume, "&$J13&" margin). "&$L13&".") -> Plowhorse (High volume, Low margin). Modest raise to capture margin.
A14: 5 | B14: =IF(OWNER_INPUTS!B10="","",OWNER_INPUTS!B10) -> Pancakes | C14: =IF($B14="","",OWNER_INPUTS!C10) -> Pastry | D14: =IF($B14="","",OWNER_INPUTS!D10) -> Premium Anchor | E14: =IF($B14="","",OWNER_INPUTS!G10) -> 750 | F14: =IF($B14="","",OWNER_INPUTS!F10-OWNER_INPUTS!E10) -> 5.3 | G14: =IF($B14="","",$E14*$F14) -> 3975 | H14: =IF($B14="","",IF(OWNER_INPUTS!F10>0,$F14/OWNER_INPUTS!F10,0)) -> 0.60227273 | I14: =IF($B14="","",IF($E14>=$B$5,"High","Low")) -> Low | J14: =IF($B14="","",IF($H14>=$B$6,"High","Low")) -> Low | K14: =IF($B14="","",IF(AND($I14="High",$J14="High"),"Star",IF(AND($I14="High",$J14="Low"),"Plowhorse",IF(AND($I14="Low",$J14="High"),"Puzzle","Dog")))) -> Dog | L14: =IF($B14="","",IF($K14="Star","Hold / protect leadership",IF($K14="Plowhorse","Modest raise to capture margin",IF($K14="Puzzle","Reposition / promote / test premium","Consider removal or simplification")))) -> Consider removal or simplification | M14: =IF($B14="","",$K14&" ("&$I14&" volume, "&$J14&" margin). "&$L14&".") -> Dog (Low volume, Low margin). Consider removal or simplification.
A15: 6 | B15: =IF(OWNER_INPUTS!B11="","",OWNER_INPUTS!B11) -> Cheesecake | C15: =IF($B15="","",OWNER_INPUTS!C11) -> Dessert | D15: =IF($B15="","",OWNER_INPUTS!D11) -> Profit Driver | E15: =IF($B15="","",OWNER_INPUTS!G11) -> 450 | F15: =IF($B15="","",OWNER_INPUTS!F11-OWNER_INPUTS!E11) -> 3.7 | G15: =IF($B15="","",$E15*$F15) -> 1665 | H15: =IF($B15="","",IF(OWNER_INPUTS!F11>0,$F15/OWNER_INPUTS!F11,0)) -> 0.63793103 | I15: =IF($B15="","",IF($E15>=$B$5,"High","Low")) -> Low | J15: =IF($B15="","",IF($H15>=$B$6,"High","Low")) -> High | K15: =IF($B15="","",IF(AND($I15="High",$J15="High"),"Star",IF(AND($I15="High",$J15="Low"),"Plowhorse",IF(AND($I15="Low",$J15="High"),"Puzzle","Dog")))) -> Puzzle | L15: =IF($B15="","",IF($K15="Star","Hold / protect leadership",IF($K15="Plowhorse","Modest raise to capture margin",IF($K15="Puzzle","Reposition / promote / test premium","Consider removal or simplification")))) -> Reposition / promote / test premium | M15: =IF($B15="","",$K15&" ("&$I15&" volume, "&$J15&" margin). "&$L15&".") -> Puzzle (Low volume, High margin). Reposition / promote / test premium.
A16: 7 | B16: =IF(OWNER_INPUTS!B12="","",OWNER_INPUTS!B12) | C16: =IF($B16="","",OWNER_INPUTS!C12) | D16: =IF($B16="","",OWNER_INPUTS!D12) | E16: =IF($B16="","",OWNER_INPUTS!G12) | F16: =IF($B16="","",OWNER_INPUTS!F12-OWNER_INPUTS!E12) | G16: =IF($B16="","",$E16*$F16) | H16: =IF($B16="","",IF(OWNER_INPUTS!F12>0,$F16/OWNER_INPUTS!F12,0)) | I16: =IF($B16="","",IF($E16>=$B$5,"High","Low")) | J16: =IF($B16="","",IF($H16>=$B$6,"High","Low")) | K16: =IF($B16="","",IF(AND($I16="High",$J16="High"),"Star",IF(AND($I16="High",$J16="Low"),"Plowhorse",IF(AND($I16="Low",$J16="High"),"Puzzle","Dog")))) | L16: =IF($B16="","",IF($K16="Star","Hold / protect leadership",IF($K16="Plowhorse","Modest raise to capture margin",IF($K16="Puzzle","Reposition / promote / test premium","Consider removal or simplification")))) | M16: =IF($B16="","",$K16&" ("&$I16&" volume, "&$J16&" margin). "&$L16&".")
A17: 8 | B17: =IF(OWNER_INPUTS!B13="","",OWNER_INPUTS!B13) | C17: =IF($B17="","",OWNER_INPUTS!C13) | D17: =IF($B17="","",OWNER_INPUTS!D13) | E17: =IF($B17="","",OWNER_INPUTS!G13) | F17: =IF($B17="","",OWNER_INPUTS!F13-OWNER_INPUTS!E13) | G17: =IF($B17="","",$E17*$F17) | H17: =IF($B17="","",IF(OWNER_INPUTS!F13>0,$F17/OWNER_INPUTS!F13,0)) | I17: =IF($B17="","",IF($E17>=$B$5,"High","Low")) | J17: =IF($B17="","",IF($H17>=$B$6,"High","Low")) | K17: =IF($B17="","",IF(AND($I17="High",$J17="High"),"Star",IF(AND($I17="High",$J17="Low"),"Plowhorse",IF(AND($I17="Low",$J17="High"),"Puzzle","Dog")))) | L17: =IF($B17="","",IF($K17="Star","Hold / protect leadership",IF($K17="Plowhorse","Modest raise to capture margin",IF($K17="Puzzle","Reposition / promote / test premium","Consider removal or simplification")))) | M17: =IF($B17="","",$K17&" ("&$I17&" volume, "&$J17&" margin). "&$L17&".")
A18: 9 | B18: =IF(OWNER_INPUTS!B14="","",OWNER_INPUTS!B14) | C18: =IF($B18="","",OWNER_INPUTS!C14) | D18: =IF($B18="","",OWNER_INPUTS!D14) | E18: =IF($B18="","",OWNER_INPUTS!G14) | F18: =IF($B18="","",OWNER_INPUTS!F14-OWNER_INPUTS!E14) | G18: =IF($B18="","",$E18*$F18) | H18: =IF($B18="","",IF(OWNER_INPUTS!F14>0,$F18/OWNER_INPUTS!F14,0)) | I18: =IF($B18="","",IF($E18>=$B$5,"High","Low")) | J18: =IF($B18="","",IF($H18>=$B$6,"High","Low")) | K18: =IF($B18="","",IF(AND($I18="High",$J18="High"),"Star",IF(AND($I18="High",$J18="Low"),"Plowhorse",IF(AND($I18="Low",$J18="High"),"Puzzle","Dog")))) | L18: =IF($B18="","",IF($K18="Star","Hold / protect leadership",IF($K18="Plowhorse","Modest raise to capture margin",IF($K18="Puzzle","Reposition / promote / test premium","Consider removal or simplification")))) | M18: =IF($B18="","",$K18&" ("&$I18&" volume, "&$J18&" margin). "&$L18&".")
A19: 10 | B19: =IF(OWNER_INPUTS!B15="","",OWNER_INPUTS!B15) | C19: =IF($B19="","",OWNER_INPUTS!C15) | D19: =IF($B19="","",OWNER_INPUTS!D15) | E19: =IF($B19="","",OWNER_INPUTS!G15) | F19: =IF($B19="","",OWNER_INPUTS!F15-OWNER_INPUTS!E15) | G19: =IF($B19="","",$E19*$F19) | H19: =IF($B19="","",IF(OWNER_INPUTS!F15>0,$F19/OWNER_INPUTS!F15,0)) | I19: =IF($B19="","",IF($E19>=$B$5,"High","Low")) | J19: =IF($B19="","",IF($H19>=$B$6,"High","Low")) | K19: =IF($B19="","",IF(AND($I19="High",$J19="High"),"Star",IF(AND($I19="High",$J19="Low"),"Plowhorse",IF(AND($I19="Low",$J19="High"),"Puzzle","Dog")))) | L19: =IF($B19="","",IF($K19="Star","Hold / protect leadership",IF($K19="Plowhorse","Modest raise to capture margin",IF($K19="Puzzle","Reposition / promote / test premium","Consider removal or simplification")))) | M19: =IF($B19="","",$K19&" ("&$I19&" volume, "&$J19&" margin). "&$L19&".")
A20: 11 | B20: =IF(OWNER_INPUTS!B16="","",OWNER_INPUTS!B16) | C20: =IF($B20="","",OWNER_INPUTS!C16) | D20: =IF($B20="","",OWNER_INPUTS!D16) | E20: =IF($B20="","",OWNER_INPUTS!G16) | F20: =IF($B20="","",OWNER_INPUTS!F16-OWNER_INPUTS!E16) | G20: =IF($B20="","",$E20*$F20) | H20: =IF($B20="","",IF(OWNER_INPUTS!F16>0,$F20/OWNER_INPUTS!F16,0)) | I20: =IF($B20="","",IF($E20>=$B$5,"High","Low")) | J20: =IF($B20="","",IF($H20>=$B$6,"High","Low")) | K20: =IF($B20="","",IF(AND($I20="High",$J20="High"),"Star",IF(AND($I20="High",$J20="Low"),"Plowhorse",IF(AND($I20="Low",$J20="High"),"Puzzle","Dog")))) | L20: =IF($B20="","",IF($K20="Star","Hold / protect leadership",IF($K20="Plowhorse","Modest raise to capture margin",IF($K20="Puzzle","Reposition / promote / test premium","Consider removal or simplification")))) | M20: =IF($B20="","",$K20&" ("&$I20&" volume, "&$J20&" margin). "&$L20&".")
A21: 12 | B21: =IF(OWNER_INPUTS!B17="","",OWNER_INPUTS!B17) | C21: =IF($B21="","",OWNER_INPUTS!C17) | D21: =IF($B21="","",OWNER_INPUTS!D17) | E21: =IF($B21="","",OWNER_INPUTS!G17) | F21: =IF($B21="","",OWNER_INPUTS!F17-OWNER_INPUTS!E17) | G21: =IF($B21="","",$E21*$F21) | H21: =IF($B21="","",IF(OWNER_INPUTS!F17>0,$F21/OWNER_INPUTS!F17,0)) | I21: =IF($B21="","",IF($E21>=$B$5,"High","Low")) | J21: =IF($B21="","",IF($H21>=$B$6,"High","Low")) | K21: =IF($B21="","",IF(AND($I21="High",$J21="High"),"Star",IF(AND($I21="High",$J21="Low"),"Plowhorse",IF(AND($I21="Low",$J21="High"),"Puzzle","Dog")))) | L21: =IF($B21="","",IF($K21="Star","Hold / protect leadership",IF($K21="Plowhorse","Modest raise to capture margin",IF($K21="Puzzle","Reposition / promote / test premium","Consider removal or simplification")))) | M21: =IF($B21="","",$K21&" ("&$I21&" volume, "&$J21&" margin). "&$L21&".")
... A39: 30 | B39: =IF(OWNER_INPUTS!B35="","",OWNER_INPUTS!B35) | C39: =IF($B39="","",OWNER_INPUTS!C35) | D39: =IF($B39="","",OWNER_INPUTS!D35) | E39: =IF($B39="","",OWNER_INPUTS!G35) | F39: =IF($B39="","",OWNER_INPUTS!F35-OWNER_INPUTS!E35) | G39: =IF($B39="","",$E39*$F39) | H39: =IF($B39="","",IF(OWNER_INPUTS!F35>0,$F39/OWNER_INPUTS!F35,0)) | I39: =IF($B39="","",IF($E39>=$B$5,"High","Low")) | J39: =IF($B39="","",IF($H39>=$B$6,"High","Low")) | K39: =IF($B39="","",IF(AND($I39="High",$J39="High"),"Star",IF(AND($I39="High",$J39="Low"),"Plowhorse",IF(AND($I39="Low",$J39="High"),"Puzzle","Dog")))) | L39: =IF($B39="","",IF($K39="Star","Hold / protect leadership",IF($K39="Plowhorse","Modest raise to capture margin",IF($K39="Puzzle","Reposition / promote / test premium","Consider removal or simplification")))) | M39: =IF($B39="","",$K39&" ("&$I39&" volume, "&$J39&" margin). "&$L39&".")
D40: Star count | E40: =COUNTIF($K$10:$K$39,"Star") -> 2
D41: Plowhorse count | E41: =COUNTIF($K$10:$K$39,"Plowhorse") -> 1
D42: Puzzle count | E42: =COUNTIF($K$10:$K$39,"Puzzle") -> 1
D43: Dog count | E43: =COUNTIF($K$10:$K$39,"Dog") -> 2
D44: Total items | E44: =SUMPRODUCT(--(LEN($B$10:$B$39)>0)) -> 6
D45: Menu balance | E45: =IF($E$40+$E$41+$E$42+$E$43=0,"No items configured",IF(($E$43/($E$40+$E$41+$E$42+$E$43))>0.3,"DOG-HEAVY — consider menu simplification",IF(($E$40+$E$41)/($E$40+$E$41+$E$42+$E$43)>=0.6,"BALANCED — popular items dominate","PUZZLE-HEAVY — many low-volume items, opportunity for promotion"))) -> DOG-HEAVY — consider menu simplification

Sheet SALES_DATA
A1: Daily Sales Data — for calibrating item-level price sensitivity
A3: This tab is OPTIONAL. Most cafés will not have it filled in. If you do have daily sales history with genuine price variation (POS export, A/B price tests, natural price changes), paste it here. Rows 6-545 are pre-formatted with formulas — that gives you 540 transaction rows (enough for 6 months of daily data across 3 items, or 18 months for 1 item). The CALIBRATION tab will estimate each item's real elasticity from it. If empty, the model falls back to category-level priors from CATEGORY_PRIORS.
A5: Day | B5: DOW | C5: ItemID | D5: Item | E5: IsSample | F5: PriceTested | G5: BasePrice | H5: QtySold | I5: Revenue | J5: COGS_unit | K5: Profit | L5: LnPrice | M5: LnQty
A6: 1 | B6: 1 | C6: ITM01 | D6: Flat White | E6: Y | F6: 4.62 | G6: 4.2 | H6: 53 | I6: =IFERROR(F6*H6,"") -> 244.86 | J6: 1 | K6: =IFERROR((F6-J6)*H6,"") -> 191.86 | L6: =IFERROR(IF(F6>0,LN(F6),""),"") -> 1.5303947 | M6: =IFERROR(IF(H6>0,LN(H6),""),"") -> 3.9702919
A7: 2 | B7: 2 | C7: ITM01 | D7: Flat White | E7: Y | F7: 3.99 | G7: 4.2 | H7: 63 | I7: =IFERROR(F7*H7,"") -> 251.37 | J7: 1 | K7: =IFERROR((F7-J7)*H7,"") -> 188.37 | L7: =IFERROR(IF(F7>0,LN(F7),""),"") -> 1.3837912 | M7: =IFERROR(IF(H7>0,LN(H7),""),"") -> 4.1431347
A8: 3 | B8: 3 | C8: ITM01 | D8: Flat White | E8: Y | F8: 3.99 | G8: 4.2 | H8: 56 | I8: =IFERROR(F8*H8,"") -> 223.44 | J8: 1 | K8: =IFERROR((F8-J8)*H8,"") -> 167.44 | L8: =IFERROR(IF(F8>0,LN(F8),""),"") -> 1.3837912 | M8: =IFERROR(IF(H8>0,LN(H8),""),"") -> 4.0253517
A9: 4 | B9: 4 | C9: ITM01 | D9: Flat White | E9: Y | F9: 4.62 | G9: 4.2 | H9: 47 | I9: =IFERROR(F9*H9,"") -> 217.14 | J9: 1 | K9: =IFERROR((F9-J9)*H9,"") -> 170.14 | L9: =IFERROR(IF(F9>0,LN(F9),""),"") -> 1.5303947 | M9: =IFERROR(IF(H9>0,LN(H9),""),"") -> 3.8501476
A10: 5 | B10: 5 | C10: ITM01 | D10: Flat White | E10: Y | F10: 4.41 | G10: 4.2 | H10: 54 | I10: =IFERROR(F10*H10,"") -> 238.14 | J10: 1 | K10: =IFERROR((F10-J10)*H10,"") -> 184.14 | L10: =IFERROR(IF(F10>0,LN(F10),""),"") -> 1.4838747 | M10: =IFERROR(IF(H10>0,LN(H10),""),"") -> 3.988984
A11: 6 | B11: 6 | C11: ITM01 | D11: Flat White | E11: Y | F11: 3.78 | G11: 4.2 | H11: 62 | I11: =IFERROR(F11*H11,"") -> 234.36 | J11: 1 | K11: =IFERROR((F11-J11)*H11,"") -> 172.36 | L11: =IFERROR(IF(F11>0,LN(F11),""),"") -> 1.329724 | M11: =IFERROR(IF(H11>0,LN(H11),""),"") -> 4.1271344
A12: 7 | B12: 7 | C12: ITM01 | D12: Flat White | E12: Y | F12: 3.78 | G12: 4.2 | H12: 59 | I12: =IFERROR(F12*H12,"") -> 223.02 | J12: 1 | K12: =IFERROR((F12-J12)*H12,"") -> 164.02 | L12: =IFERROR(IF(F12>0,LN(F12),""),"") -> 1.329724 | M12: =IFERROR(IF(H12>0,LN(H12),""),"") -> 4.0775374
A13: 8 | B13: 1 | C13: ITM01 | D13: Flat White | E13: Y | F13: 3.78 | G13: 4.2 | H13: 68 | I13: =IFERROR(F13*H13,"") -> 257.04 | J13: 1 | K13: =IFERROR((F13-J13)*H13,"") -> 189.04 | L13: =IFERROR(IF(F13>0,LN(F13),""),"") -> 1.329724 | M13: =IFERROR(IF(H13>0,LN(H13),""),"") -> 4.2195077
A14: 9 | B14: 2 | C14: ITM01 | D14: Flat White | E14: Y | F14: 4.41 | G14: 4.2 | H14: 50 | I14: =IFERROR(F14*H14,"") -> 220.5 | J14: 1 | K14: =IFERROR((F14-J14)*H14,"") -> 170.5 | L14: =IFERROR(IF(F14>0,LN(F14),""),"") -> 1.4838747 | M14: =IFERROR(IF(H14>0,LN(H14),""),"") -> 3.912023
A15: 10 | B15: 3 | C15: ITM01 | D15: Flat White | E15: Y | F15: 4.41 | G15: 4.2 | H15: 58 | I15: =IFERROR(F15*H15,"") -> 255.78 | J15: 1 | K15: =IFERROR((F15-J15)*H15,"") -> 197.78 | L15: =IFERROR(IF(F15>0,LN(F15),""),"") -> 1.4838747 | M15: =IFERROR(IF(H15>0,LN(H15),""),"") -> 4.060443
A16: 11 | B16: 4 | C16: ITM01 | D16: Flat White | E16: Y | F16: 4.2 | G16: 4.2 | H16: 52 | I16: =IFERROR(F16*H16,"") -> 218.4 | J16: 1 | K16: =IFERROR((F16-J16)*H16,"") -> 166.4 | L16: =IFERROR(IF(F16>0,LN(F16),""),"") -> 1.4350845 | M16: =IFERROR(IF(H16>0,LN(H16),""),"") -> 3.9512437
A17: 12 | B17: 5 | C17: ITM01 | D17: Flat White | E17: Y | F17: 3.78 | G17: 4.2 | H17: 70 | I17: =IFERROR(F17*H17,"") -> 264.6 | J17: 1 | K17: =IFERROR((F17-J17)*H17,"") -> 194.6 | L17: =IFERROR(IF(F17>0,LN(F17),""),"") -> 1.329724 | M17: =IFERROR(IF(H17>0,LN(H17),""),"") -> 4.2484952
... A545: 90 | B545: 6 | C545: ITM06 | D545: Cheesecake | E545: Y | F545: 5.8 | G545: 5.8 | H545: 15 | I545: =IFERROR(F545*H545,"") -> 87 | J545: 2.1 | K545: =IFERROR((F545-J545)*H545,"") -> 55.5 | L545: =IFERROR(IF(F545>0,LN(F545),""),"") -> 1.7578579 | M545: =IFERROR(IF(H545>0,LN(H545),""),"") -> 2.7080502

Sheet CALIBRATION
A1: Demand Calibration — Elasticities Estimated from SALES_DATA
A3: For each item in OWNER_INPUTS, the model regresses ln(QtySold) on ln(PriceTested) over all matching rows in SALES_DATA. The slope of that regression IS the own-price elasticity. The 95% CI shows how confident the estimate is. Rows flagged IsSample="Y" are included only when SETTINGS!Use sample = "Yes".
A5: # | B5: Item (from OWNER_INPUTS) | C5: N obs | D5: Avg Price | E5: Avg Qty/day | F5: Elasticity (ê) | G5: Std Error | H5: 95% CI low | I5: 95% CI high | J5: Confidence tier | K5: Notes | L5: Estimate (numeric) | N5: Helper: mean lnP | O5: Helper: mean lnQ | P5: Helper: SSxx | Q5: Helper: SSxy | R5: Helper: SSres
A6: 1 | B6: =IF(OWNER_INPUTS!B6="","",OWNER_INPUTS!B6) -> Flat White | C6: =IFERROR(IF($B6="","",SUMPRODUCT((sd_item=$B6)*((sd_sample="N") + (sd_sample="Y")*(cfg_use_sample="Yes"))*(sd_qty>0))),"") -> 0 | D6: =IFERROR(IF(OR($B6="",$C6=0,$C6=""),"",SUMPRODUCT((sd_item=$B6)*((sd_sample="N") + (sd_sample="Y")*(cfg_use_sample="Yes"))*SALES_DATA!$F$6:$F$545)/$C6),"") | E6: =IFERROR(IF(OR($B6="",$C6=0,$C6=""),"",SUMPRODUCT((sd_item=$B6)*((sd_sample="N") + (sd_sample="Y")*(cfg_use_sample="Yes"))*sd_qty)/$C6),"") | F6: =IFERROR(IF(OR($B6="",$C6<10,NOT(ISNUMBER($P6)),$P6=0),"",$Q6/$P6),"") | G6: =IFERROR(IF(OR(NOT(ISNUMBER($F6)),$C6<3,$P6=0,NOT(ISNUMBER($R6))),"",SQRT($R6/($C6-2)/$P6)),"") | H6: =IFERROR(IF(OR(NOT(ISNUMBER($F6)),NOT(ISNUMBER($G6))),"",$F6-1.96*$G6),"") | I6: =IFERROR(IF(OR(NOT(ISNUMBER($F6)),NOT(ISNUMBER($G6))),"",$F6+1.96*$G6),"") | J6: =IF(OR($B6="",NOT(ISNUMBER($F6))),"—",IF($C6<30,"LOW",IF($I6<=-1,"HIGH","MEDIUM"))) -> — | K6: =IF($B6="","",IF(NOT(ISNUMBER($F6)),"No matching rows in SALES_DATA — using category prior",IF($C6<30,"Low sample (<30 obs) — CI is wide",IF($I6>-1,"CI crosses -1 — direction uncertain","OK")))) -> No matching rows in SALES_DATA — using category prior | L6: =IF(ISNUMBER($F6),$F6,"") | N6: =IFERROR(IF($B6="","",SUMPRODUCT((sd_item=$B6)*((sd_sample="N") + (sd_sample="Y")*(cfg_use_sample="Yes"))*sd_lnp)/SUMPRODUCT((sd_item=$B6)*((sd_sample="N") + (sd_sample="Y")*(cfg_use_sample="Yes")))),"") | O6: =IFERROR(IF($B6="","",SUMPRODUCT((sd_item=$B6)*((sd_sample="N") + (sd_sample="Y")*(cfg_use_sample="Yes"))*sd_lnq)/SUMPRODUCT((sd_item=$B6)*((sd_sample="N") + (sd_sample="Y")*(cfg_use_sample="Yes")))),"") | P6: =IFERROR(IF(OR($B6="",$N6=""),"",SUMPRODUCT((sd_item=$B6)*((sd_sample="N") + (sd_sample="Y")*(cfg_use_sample="Yes"))*(sd_lnp-$N6)^2)),"") | Q6: =IFERROR(IF(OR($B6="",$N6=""),"",SUMPRODUCT((sd_item=$B6)*((sd_sample="N") + (sd_sample="Y")*(cfg_use_sample="Yes"))*(sd_lnp-$N6)*(sd_lnq-$O6))),"") | R6: =IFERROR(IF(OR($B6="",$F6="",$F6=0,NOT(ISNUMBER($F6))),"",SUMPRODUCT((sd_item=$B6)*((sd_sample="N") + (sd_sample="Y")*(cfg_use_sample="Yes"))*(sd_lnq-$O6-$F6*(sd_lnp-$N6))^2)),"")
A7: 2 | B7: =IF(OWNER_INPUTS!B7="","",OWNER_INPUTS!B7) -> Matcha Latte | C7: =IFERROR(IF($B7="","",SUMPRODUCT((sd_item=$B7)*((sd_sample="N") + (sd_sample="Y")*(cfg_use_sample="Yes"))*(sd_qty>0))),"") -> 0 | D7: =IFERROR(IF(OR($B7="",$C7=0,$C7=""),"",SUMPRODUCT((sd_item=$B7)*((sd_sample="N") + (sd_sample="Y")*(cfg_use_sample="Yes"))*SALES_DATA!$F$6:$F$545)/$C7),"") | E7: =IFERROR(IF(OR($B7="",$C7=0,$C7=""),"",SUMPRODUCT((sd_item=$B7)*((sd_sample="N") + (sd_sample="Y")*(cfg_use_sample="Yes"))*sd_qty)/$C7),"") | F7: =IFERROR(IF(OR($B7="",$C7<10,NOT(ISNUMBER($P7)),$P7=0),"",$Q7/$P7),"") | G7: =IFERROR(IF(OR(NOT(ISNUMBER($F7)),$C7<3,$P7=0,NOT(ISNUMBER($R7))),"",SQRT($R7/($C7-2)/$P7)),"") | H7: =IFERROR(IF(OR(NOT(ISNUMBER($F7)),NOT(ISNUMBER($G7))),"",$F7-1.96*$G7),"") | I7: =IFERROR(IF(OR(NOT(ISNUMBER($F7)),NOT(ISNUMBER($G7))),"",$F7+1.96*$G7),"") | J7: =IF(OR($B7="",NOT(ISNUMBER($F7))),"—",IF($C7<30,"LOW",IF($I7<=-1,"HIGH","MEDIUM"))) -> — | K7: =IF($B7="","",IF(NOT(ISNUMBER($F7)),"No matching rows in SALES_DATA — using category prior",IF($C7<30,"Low sample (<30 obs) — CI is wide",IF($I7>-1,"CI crosses -1 — direction uncertain","OK")))) -> No matching rows in SALES_DATA — using category prior | L7: =IF(ISNUMBER($F7),$F7,"") | N7: =IFERROR(IF($B7="","",SUMPRODUCT((sd_item=$B7)*((sd_sample="N") + (sd_sample="Y")*(cfg_use_sample="Yes"))*sd_lnp)/SUMPRODUCT((sd_item=$B7)*((sd_sample="N") + (sd_sample="Y")*(cfg_use_sample="Yes")))),"") | O7: =IFERROR(IF($B7="","",SUMPRODUCT((sd_item=$B7)*((sd_sample="N") + (sd_sample="Y")*(cfg_use_sample="Yes"))*sd_lnq)/SUMPRODUCT((sd_item=$B7)*((sd_sample="N") + (sd_sample="Y")*(cfg_use_sample="Yes")))),"") | P7: =IFERROR(IF(OR($B7="",$N7=""),"",SUMPRODUCT((sd_item=$B7)*((sd_sample="N") + (sd_sample="Y")*(cfg_use_sample="Yes"))*(sd_lnp-$N7)^2)),"") | Q7: =IFERROR(IF(OR($B7="",$N7=""),"",SUMPRODUCT((sd_item=$B7)*((sd_sample="N") + (sd_sample="Y")*(cfg_use_sample="Yes"))*(sd_lnp-$N7)*(sd_lnq-$O7))),"") | R7: =IFERROR(IF(OR($B7="",$F7="",$F7=0,NOT(ISNUMBER($F7))),"",SUMPRODUCT((sd_item=$B7)*((sd_sample="N") + (sd_sample="Y")*(cfg_use_sample="Yes"))*(sd_lnq-$O7-$F7*(sd_lnp-$N7))^2)),"")
A8: 3 | B8: =IF(OWNER_INPUTS!B8="","",OWNER_INPUTS!B8) -> Eggs Benedict | C8: =IFERROR(IF($B8="","",SUMPRODUCT((sd_item=$B8)*((sd_sample="N") + (sd_sample="Y")*(cfg_use_sample="Yes"))*(sd_qty>0))),"") -> 0 | D8: =IFERROR(IF(OR($B8="",$C8=0,$C8=""),"",SUMPRODUCT((sd_item=$B8)*((sd_sample="N") + (sd_sample="Y")*(cfg_use_sample="Yes"))*SALES_DATA!$F$6:$F$545)/$C8),"") | E8: =IFERROR(IF(OR($B8="",$C8=0,$C8=""),"",SUMPRODUCT((sd_item=$B8)*((sd_sample="N") + (sd_sample="Y")*(cfg_use_sample="Yes"))*sd_qty)/$C8),"") | F8: =IFERROR(IF(OR($B8="",$C8<10,NOT(ISNUMBER($P8)),$P8=0),"",$Q8/$P8),"") | G8: =IFERROR(IF(OR(NOT(ISNUMBER($F8)),$C8<3,$P8=0,NOT(ISNUMBER($R8))),"",SQRT($R8/($C8-2)/$P8)),"") | H8: =IFERROR(IF(OR(NOT(ISNUMBER($F8)),NOT(ISNUMBER($G8))),"",$F8-1.96*$G8),"") | I8: =IFERROR(IF(OR(NOT(ISNUMBER($F8)),NOT(ISNUMBER($G8))),"",$F8+1.96*$G8),"") | J8: =IF(OR($B8="",NOT(ISNUMBER($F8))),"—",IF($C8<30,"LOW",IF($I8<=-1,"HIGH","MEDIUM"))) -> — | K8: =IF($B8="","",IF(NOT(ISNUMBER($F8)),"No matching rows in SALES_DATA — using category prior",IF($C8<30,"Low sample (<30 obs) — CI is wide",IF($I8>-1,"CI crosses -1 — direction uncertain","OK")))) -> No matching rows in SALES_DATA — using category prior | L8: =IF(ISNUMBER($F8),$F8,"") | N8: =IFERROR(IF($B8="","",SUMPRODUCT((sd_item=$B8)*((sd_sample="N") + (sd_sample="Y")*(cfg_use_sample="Yes"))*sd_lnp)/SUMPRODUCT((sd_item=$B8)*((sd_sample="N") + (sd_sample="Y")*(cfg_use_sample="Yes")))),"") | O8: =IFERROR(IF($B8="","",SUMPRODUCT((sd_item=$B8)*((sd_sample="N") + (sd_sample="Y")*(cfg_use_sample="Yes"))*sd_lnq)/SUMPRODUCT((sd_item=$B8)*((sd_sample="N") + (sd_sample="Y")*(cfg_use_sample="Yes")))),"") | P8: =IFERROR(IF(OR($B8="",$N8=""),"",SUMPRODUCT((sd_item=$B8)*((sd_sample="N") + (sd_sample="Y")*(cfg_use_sample="Yes"))*(sd_lnp-$N8)^2)),"") | Q8: =IFERROR(IF(OR($B8="",$N8=""),"",SUMPRODUCT((sd_item=$B8)*((sd_sample="N") + (sd_sample="Y")*(cfg_use_sample="Yes"))*(sd_lnp-$N8)*(sd_lnq-$O8))),"") | R8: =IFERROR(IF(OR($B8="",$F8="",$F8=0,NOT(ISNUMBER($F8))),"",SUMPRODUCT((sd_item=$B8)*((sd_sample="N") + (sd_sample="Y")*(cfg_use_sample="Yes"))*(sd_lnq-$O8-$F8*(sd_lnp-$N8))^2)),"")
A9: 4 | B9: =IF(OWNER_INPUTS!B9="","",OWNER_INPUTS!B9) -> Avocado Toast | C9: =IFERROR(IF($B9="","",SUMPRODUCT((sd_item=$B9)*((sd_sample="N") + (sd_sample="Y")*(cfg_use_sample="Yes"))*(sd_qty>0))),"") -> 0 | D9: =IFERROR(IF(OR($B9="",$C9=0,$C9=""),"",SUMPRODUCT((sd_item=$B9)*((sd_sample="N") + (sd_sample="Y")*(cfg_use_sample="Yes"))*SALES_DATA!$F$6:$F$545)/$C9),"") | E9: =IFERROR(IF(OR($B9="",$C9=0,$C9=""),"",SUMPRODUCT((sd_item=$B9)*((sd_sample="N") + (sd_sample="Y")*(cfg_use_sample="Yes"))*sd_qty)/$C9),"") | F9: =IFERROR(IF(OR($B9="",$C9<10,NOT(ISNUMBER($P9)),$P9=0),"",$Q9/$P9),"") | G9: =IFERROR(IF(OR(NOT(ISNUMBER($F9)),$C9<3,$P9=0,NOT(ISNUMBER($R9))),"",SQRT($R9/($C9-2)/$P9)),"") | H9: =IFERROR(IF(OR(NOT(ISNUMBER($F9)),NOT(ISNUMBER($G9))),"",$F9-1.96*$G9),"") | I9: =IFERROR(IF(OR(NOT(ISNUMBER($F9)),NOT(ISNUMBER($G9))),"",$F9+1.96*$G9),"") | J9: =IF(OR($B9="",NOT(ISNUMBER($F9))),"—",IF($C9<30,"LOW",IF($I9<=-1,"HIGH","MEDIUM"))) -> — | K9: =IF($B9="","",IF(NOT(ISNUMBER($F9)),"No matching rows in SALES_DATA — using category prior",IF($C9<30,"Low sample (<30 obs) — CI is wide",IF($I9>-1,"CI crosses -1 — direction uncertain","OK")))) -> No matching rows in SALES_DATA — using category prior | L9: =IF(ISNUMBER($F9),$F9,"") | N9: =IFERROR(IF($B9="","",SUMPRODUCT((sd_item=$B9)*((sd_sample="N") + (sd_sample="Y")*(cfg_use_sample="Yes"))*sd_lnp)/SUMPRODUCT((sd_item=$B9)*((sd_sample="N") + (sd_sample="Y")*(cfg_use_sample="Yes")))),"") | O9: =IFERROR(IF($B9="","",SUMPRODUCT((sd_item=$B9)*((sd_sample="N") + (sd_sample="Y")*(cfg_use_sample="Yes"))*sd_lnq)/SUMPRODUCT((sd_item=$B9)*((sd_sample="N") + (sd_sample="Y")*(cfg_use_sample="Yes")))),"") | P9: =IFERROR(IF(OR($B9="",$N9=""),"",SUMPRODUCT((sd_item=$B9)*((sd_sample="N") + (sd_sample="Y")*(cfg_use_sample="Yes"))*(sd_lnp-$N9)^2)),"") | Q9: =IFERROR(IF(OR($B9="",$N9=""),"",SUMPRODUCT((sd_item=$B9)*((sd_sample="N") + (sd_sample="Y")*(cfg_use_sample="Yes"))*(sd_lnp-$N9)*(sd_lnq-$O9))),"") | R9: =IFERROR(IF(OR($B9="",$F9="",$F9=0,NOT(ISNUMBER($F9))),"",SUMPRODUCT((sd_item=$B9)*((sd_sample="N") + (sd_sample="Y")*(cfg_use_sample="Yes"))*(sd_lnq-$O9-$F9*(sd_lnp-$N9))^2)),"")
A10: 5 | B10: =IF(OWNER_INPUTS!B10="","",OWNER_INPUTS!B10) -> Pancakes | C10: =IFERROR(IF($B10="","",SUMPRODUCT((sd_item=$B10)*((sd_sample="N") + (sd_sample="Y")*(cfg_use_sample="Yes"))*(sd_qty>0))),"") -> 0 | D10: =IFERROR(IF(OR($B10="",$C10=0,$C10=""),"",SUMPRODUCT((sd_item=$B10)*((sd_sample="N") + (sd_sample="Y")*(cfg_use_sample="Yes"))*SALES_DATA!$F$6:$F$545)/$C10),"") | E10: =IFERROR(IF(OR($B10="",$C10=0,$C10=""),"",SUMPRODUCT((sd_item=$B10)*((sd_sample="N") + (sd_sample="Y")*(cfg_use_sample="Yes"))*sd_qty)/$C10),"") | F10: =IFERROR(IF(OR($B10="",$C10<10,NOT(ISNUMBER($P10)),$P10=0),"",$Q10/$P10),"") | G10: =IFERROR(IF(OR(NOT(ISNUMBER($F10)),$C10<3,$P10=0,NOT(ISNUMBER($R10))),"",SQRT($R10/($C10-2)/$P10)),"") | H10: =IFERROR(IF(OR(NOT(ISNUMBER($F10)),NOT(ISNUMBER($G10))),"",$F10-1.96*$G10),"") | I10: =IFERROR(IF(OR(NOT(ISNUMBER($F10)),NOT(ISNUMBER($G10))),"",$F10+1.96*$G10),"") | J10: =IF(OR($B10="",NOT(ISNUMBER($F10))),"—",IF($C10<30,"LOW",IF($I10<=-1,"HIGH","MEDIUM"))) -> — | K10: =IF($B10="","",IF(NOT(ISNUMBER($F10)),"No matching rows in SALES_DATA — using category prior",IF($C10<30,"Low sample (<30 obs) — CI is wide",IF($I10>-1,"CI crosses -1 — direction uncertain","OK")))) -> No matching rows in SALES_DATA — using category prior | L10: =IF(ISNUMBER($F10),$F10,"") | N10: =IFERROR(IF($B10="","",SUMPRODUCT((sd_item=$B10)*((sd_sample="N") + (sd_sample="Y")*(cfg_use_sample="Yes"))*sd_lnp)/SUMPRODUCT((sd_item=$B10)*((sd_sample="N") + (sd_sample="Y")*(cfg_use_sample="Yes")))),"") | O10: =IFERROR(IF($B10="","",SUMPRODUCT((sd_item=$B10)*((sd_sample="N") + (sd_sample="Y")*(cfg_use_sample="Yes"))*sd_lnq)/SUMPRODUCT((sd_item=$B10)*((sd_sample="N") + (sd_sample="Y")*(cfg_use_sample="Yes")))),"") | P10: =IFERROR(IF(OR($B10="",$N10=""),"",SUMPRODUCT((sd_item=$B10)*((sd_sample="N") + (sd_sample="Y")*(cfg_use_sample="Yes"))*(sd_lnp-$N10)^2)),"") | Q10: =IFERROR(IF(OR($B10="",$N10=""),"",SUMPRODUCT((sd_item=$B10)*((sd_sample="N") + (sd_sample="Y")*(cfg_use_sample="Yes"))*(sd_lnp-$N10)*(sd_lnq-$O10))),"") | R10: =IFERROR(IF(OR($B10="",$F10="",$F10=0,NOT(ISNUMBER($F10))),"",SUMPRODUCT((sd_item=$B10)*((sd_sample="N") + (sd_sample="Y")*(cfg_use_sample="Yes"))*(sd_lnq-$O10-$F10*(sd_lnp-$N10))^2)),"")
A11: 6 | B11: =IF(OWNER_INPUTS!B11="","",OWNER_INPUTS!B11) -> Cheesecake | C11: =IFERROR(IF($B11="","",SUMPRODUCT((sd_item=$B11)*((sd_sample="N") + (sd_sample="Y")*(cfg_use_sample="Yes"))*(sd_qty>0))),"") -> 0 | D11: =IFERROR(IF(OR($B11="",$C11=0,$C11=""),"",SUMPRODUCT((sd_item=$B11)*((sd_sample="N") + (sd_sample="Y")*(cfg_use_sample="Yes"))*SALES_DATA!$F$6:$F$545)/$C11),"") | E11: =IFERROR(IF(OR($B11="",$C11=0,$C11=""),"",SUMPRODUCT((sd_item=$B11)*((sd_sample="N") + (sd_sample="Y")*(cfg_use_sample="Yes"))*sd_qty)/$C11),"") | F11: =IFERROR(IF(OR($B11="",$C11<10,NOT(ISNUMBER($P11)),$P11=0),"",$Q11/$P11),"") | G11: =IFERROR(IF(OR(NOT(ISNUMBER($F11)),$C11<3,$P11=0,NOT(ISNUMBER($R11))),"",SQRT($R11/($C11-2)/$P11)),"") | H11: =IFERROR(IF(OR(NOT(ISNUMBER($F11)),NOT(ISNUMBER($G11))),"",$F11-1.96*$G11),"") | I11: =IFERROR(IF(OR(NOT(ISNUMBER($F11)),NOT(ISNUMBER($G11))),"",$F11+1.96*$G11),"") | J11: =IF(OR($B11="",NOT(ISNUMBER($F11))),"—",IF($C11<30,"LOW",IF($I11<=-1,"HIGH","MEDIUM"))) -> — | K11: =IF($B11="","",IF(NOT(ISNUMBER($F11)),"No matching rows in SALES_DATA — using category prior",IF($C11<30,"Low sample (<30 obs) — CI is wide",IF($I11>-1,"CI crosses -1 — direction uncertain","OK")))) -> No matching rows in SALES_DATA — using category prior | L11: =IF(ISNUMBER($F11),$F11,"") | N11: =IFERROR(IF($B11="","",SUMPRODUCT((sd_item=$B11)*((sd_sample="N") + (sd_sample="Y")*(cfg_use_sample="Yes"))*sd_lnp)/SUMPRODUCT((sd_item=$B11)*((sd_sample="N") + (sd_sample="Y")*(cfg_use_sample="Yes")))),"") | O11: =IFERROR(IF($B11="","",SUMPRODUCT((sd_item=$B11)*((sd_sample="N") + (sd_sample="Y")*(cfg_use_sample="Yes"))*sd_lnq)/SUMPRODUCT((sd_item=$B11)*((sd_sample="N") + (sd_sample="Y")*(cfg_use_sample="Yes")))),"") | P11: =IFERROR(IF(OR($B11="",$N11=""),"",SUMPRODUCT((sd_item=$B11)*((sd_sample="N") + (sd_sample="Y")*(cfg_use_sample="Yes"))*(sd_lnp-$N11)^2)),"") | Q11: =IFERROR(IF(OR($B11="",$N11=""),"",SUMPRODUCT((sd_item=$B11)*((sd_sample="N") + (sd_sample="Y")*(cfg_use_sample="Yes"))*(sd_lnp-$N11)*(sd_lnq-$O11))),"") | R11: =IFERROR(IF(OR($B11="",$F11="",$F11=0,NOT(ISNUMBER($F11))),"",SUMPRODUCT((sd_item=$B11)*((sd_sample="N") + (sd_sample="Y")*(cfg_use_sample="Yes"))*(sd_lnq-$O11-$F11*(sd_lnp-$N11))^2)),"")
A12: 7 | B12: =IF(OWNER_INPUTS!B12="","",OWNER_INPUTS!B12) | C12: =IFERROR(IF($B12="","",SUMPRODUCT((sd_item=$B12)*((sd_sample="N") + (sd_sample="Y")*(cfg_use_sample="Yes"))*(sd_qty>0))),"") | D12: =IFERROR(IF(OR($B12="",$C12=0,$C12=""),"",SUMPRODUCT((sd_item=$B12)*((sd_sample="N") + (sd_sample="Y")*(cfg_use_sample="Yes"))*SALES_DATA!$F$6:$F$545)/$C12),"") | E12: =IFERROR(IF(OR($B12="",$C12=0,$C12=""),"",SUMPRODUCT((sd_item=$B12)*((sd_sample="N") + (sd_sample="Y")*(cfg_use_sample="Yes"))*sd_qty)/$C12),"") | F12: =IFERROR(IF(OR($B12="",$C12<10,NOT(ISNUMBER($P12)),$P12=0),"",$Q12/$P12),"") | G12: =IFERROR(IF(OR(NOT(ISNUMBER($F12)),$C12<3,$P12=0,NOT(ISNUMBER($R12))),"",SQRT($R12/($C12-2)/$P12)),"") | H12: =IFERROR(IF(OR(NOT(ISNUMBER($F12)),NOT(ISNUMBER($G12))),"",$F12-1.96*$G12),"") | I12: =IFERROR(IF(OR(NOT(ISNUMBER($F12)),NOT(ISNUMBER($G12))),"",$F12+1.96*$G12),"") | J12: =IF(OR($B12="",NOT(ISNUMBER($F12))),"—",IF($C12<30,"LOW",IF($I12<=-1,"HIGH","MEDIUM"))) -> — | K12: =IF($B12="","",IF(NOT(ISNUMBER($F12)),"No matching rows in SALES_DATA — using category prior",IF($C12<30,"Low sample (<30 obs) — CI is wide",IF($I12>-1,"CI crosses -1 — direction uncertain","OK")))) | L12: =IF(ISNUMBER($F12),$F12,"") | N12: =IFERROR(IF($B12="","",SUMPRODUCT((sd_item=$B12)*((sd_sample="N") + (sd_sample="Y")*(cfg_use_sample="Yes"))*sd_lnp)/SUMPRODUCT((sd_item=$B12)*((sd_sample="N") + (sd_sample="Y")*(cfg_use_sample="Yes")))),"") | O12: =IFERROR(IF($B12="","",SUMPRODUCT((sd_item=$B12)*((sd_sample="N") + (sd_sample="Y")*(cfg_use_sample="Yes"))*sd_lnq)/SUMPRODUCT((sd_item=$B12)*((sd_sample="N") + (sd_sample="Y")*(cfg_use_sample="Yes")))),"") | P12: =IFERROR(IF(OR($B12="",$N12=""),"",SUMPRODUCT((sd_item=$B12)*((sd_sample="N") + (sd_sample="Y")*(cfg_use_sample="Yes"))*(sd_lnp-$N12)^2)),"") | Q12: =IFERROR(IF(OR($B12="",$N12=""),"",SUMPRODUCT((sd_item=$B12)*((sd_sample="N") + (sd_sample="Y")*(cfg_use_sample="Yes"))*(sd_lnp-$N12)*(sd_lnq-$O12))),"") | R12: =IFERROR(IF(OR($B12="",$F12="",$F12=0,NOT(ISNUMBER($F12))),"",SUMPRODUCT((sd_item=$B12)*((sd_sample="N") + (sd_sample="Y")*(cfg_use_sample="Yes"))*(sd_lnq-$O12-$F12*(sd_lnp-$N12))^2)),"")
A13: 8 | B13: =IF(OWNER_INPUTS!B13="","",OWNER_INPUTS!B13) | C13: =IFERROR(IF($B13="","",SUMPRODUCT((sd_item=$B13)*((sd_sample="N") + (sd_sample="Y")*(cfg_use_sample="Yes"))*(sd_qty>0))),"") | D13: =IFERROR(IF(OR($B13="",$C13=0,$C13=""),"",SUMPRODUCT((sd_item=$B13)*((sd_sample="N") + (sd_sample="Y")*(cfg_use_sample="Yes"))*SALES_DATA!$F$6:$F$545)/$C13),"") | E13: =IFERROR(IF(OR($B13="",$C13=0,$C13=""),"",SUMPRODUCT((sd_item=$B13)*((sd_sample="N") + (sd_sample="Y")*(cfg_use_sample="Yes"))*sd_qty)/$C13),"") | F13: =IFERROR(IF(OR($B13="",$C13<10,NOT(ISNUMBER($P13)),$P13=0),"",$Q13/$P13),"") | G13: =IFERROR(IF(OR(NOT(ISNUMBER($F13)),$C13<3,$P13=0,NOT(ISNUMBER($R13))),"",SQRT($R13/($C13-2)/$P13)),"") | H13: =IFERROR(IF(OR(NOT(ISNUMBER($F13)),NOT(ISNUMBER($G13))),"",$F13-1.96*$G13),"") | I13: =IFERROR(IF(OR(NOT(ISNUMBER($F13)),NOT(ISNUMBER($G13))),"",$F13+1.96*$G13),"") | J13: =IF(OR($B13="",NOT(ISNUMBER($F13))),"—",IF($C13<30,"LOW",IF($I13<=-1,"HIGH","MEDIUM"))) -> — | K13: =IF($B13="","",IF(NOT(ISNUMBER($F13)),"No matching rows in SALES_DATA — using category prior",IF($C13<30,"Low sample (<30 obs) — CI is wide",IF($I13>-1,"CI crosses -1 — direction uncertain","OK")))) | L13: =IF(ISNUMBER($F13),$F13,"") | N13: =IFERROR(IF($B13="","",SUMPRODUCT((sd_item=$B13)*((sd_sample="N") + (sd_sample="Y")*(cfg_use_sample="Yes"))*sd_lnp)/SUMPRODUCT((sd_item=$B13)*((sd_sample="N") + (sd_sample="Y")*(cfg_use_sample="Yes")))),"") | O13: =IFERROR(IF($B13="","",SUMPRODUCT((sd_item=$B13)*((sd_sample="N") + (sd_sample="Y")*(cfg_use_sample="Yes"))*sd_lnq)/SUMPRODUCT((sd_item=$B13)*((sd_sample="N") + (sd_sample="Y")*(cfg_use_sample="Yes")))),"") | P13: =IFERROR(IF(OR($B13="",$N13=""),"",SUMPRODUCT((sd_item=$B13)*((sd_sample="N") + (sd_sample="Y")*(cfg_use_sample="Yes"))*(sd_lnp-$N13)^2)),"") | Q13: =IFERROR(IF(OR($B13="",$N13=""),"",SUMPRODUCT((sd_item=$B13)*((sd_sample="N") + (sd_sample="Y")*(cfg_use_sample="Yes"))*(sd_lnp-$N13)*(sd_lnq-$O13))),"") | R13: =IFERROR(IF(OR($B13="",$F13="",$F13=0,NOT(ISNUMBER($F13))),"",SUMPRODUCT((sd_item=$B13)*((sd_sample="N") + (sd_sample="Y")*(cfg_use_sample="Yes"))*(sd_lnq-$O13-$F13*(sd_lnp-$N13))^2)),"")
A14: 9 | B14: =IF(OWNER_INPUTS!B14="","",OWNER_INPUTS!B14) | C14: =IFERROR(IF($B14="","",SUMPRODUCT((sd_item=$B14)*((sd_sample="N") + (sd_sample="Y")*(cfg_use_sample="Yes"))*(sd_qty>0))),"") | D14: =IFERROR(IF(OR($B14="",$C14=0,$C14=""),"",SUMPRODUCT((sd_item=$B14)*((sd_sample="N") + (sd_sample="Y")*(cfg_use_sample="Yes"))*SALES_DATA!$F$6:$F$545)/$C14),"") | E14: =IFERROR(IF(OR($B14="",$C14=0,$C14=""),"",SUMPRODUCT((sd_item=$B14)*((sd_sample="N") + (sd_sample="Y")*(cfg_use_sample="Yes"))*sd_qty)/$C14),"") | F14: =IFERROR(IF(OR($B14="",$C14<10,NOT(ISNUMBER($P14)),$P14=0),"",$Q14/$P14),"") | G14: =IFERROR(IF(OR(NOT(ISNUMBER($F14)),$C14<3,$P14=0,NOT(ISNUMBER($R14))),"",SQRT($R14/($C14-2)/$P14)),"") | H14: =IFERROR(IF(OR(NOT(ISNUMBER($F14)),NOT(ISNUMBER($G14))),"",$F14-1.96*$G14),"") | I14: =IFERROR(IF(OR(NOT(ISNUMBER($F14)),NOT(ISNUMBER($G14))),"",$F14+1.96*$G14),"") | J14: =IF(OR($B14="",NOT(ISNUMBER($F14))),"—",IF($C14<30,"LOW",IF($I14<=-1,"HIGH","MEDIUM"))) -> — | K14: =IF($B14="","",IF(NOT(ISNUMBER($F14)),"No matching rows in SALES_DATA — using category prior",IF($C14<30,"Low sample (<30 obs) — CI is wide",IF($I14>-1,"CI crosses -1 — direction uncertain","OK")))) | L14: =IF(ISNUMBER($F14),$F14,"") | N14: =IFERROR(IF($B14="","",SUMPRODUCT((sd_item=$B14)*((sd_sample="N") + (sd_sample="Y")*(cfg_use_sample="Yes"))*sd_lnp)/SUMPRODUCT((sd_item=$B14)*((sd_sample="N") + (sd_sample="Y")*(cfg_use_sample="Yes")))),"") | O14: =IFERROR(IF($B14="","",SUMPRODUCT((sd_item=$B14)*((sd_sample="N") + (sd_sample="Y")*(cfg_use_sample="Yes"))*sd_lnq)/SUMPRODUCT((sd_item=$B14)*((sd_sample="N") + (sd_sample="Y")*(cfg_use_sample="Yes")))),"") | P14: =IFERROR(IF(OR($B14="",$N14=""),"",SUMPRODUCT((sd_item=$B14)*((sd_sample="N") + (sd_sample="Y")*(cfg_use_sample="Yes"))*(sd_lnp-$N14)^2)),"") | Q14: =IFERROR(IF(OR($B14="",$N14=""),"",SUMPRODUCT((sd_item=$B14)*((sd_sample="N") + (sd_sample="Y")*(cfg_use_sample="Yes"))*(sd_lnp-$N14)*(sd_lnq-$O14))),"") | R14: =IFERROR(IF(OR($B14="",$F14="",$F14=0,NOT(ISNUMBER($F14))),"",SUMPRODUCT((sd_item=$B14)*((sd_sample="N") + (sd_sample="Y")*(cfg_use_sample="Yes"))*(sd_lnq-$O14-$F14*(sd_lnp-$N14))^2)),"")
A15: 10 | B15: =IF(OWNER_INPUTS!B15="","",OWNER_INPUTS!B15) | C15: =IFERROR(IF($B15="","",SUMPRODUCT((sd_item=$B15)*((sd_sample="N") + (sd_sample="Y")*(cfg_use_sample="Yes"))*(sd_qty>0))),"") | D15: =IFERROR(IF(OR($B15="",$C15=0,$C15=""),"",SUMPRODUCT((sd_item=$B15)*((sd_sample="N") + (sd_sample="Y")*(cfg_use_sample="Yes"))*SALES_DATA!$F$6:$F$545)/$C15),"") | E15: =IFERROR(IF(OR($B15="",$C15=0,$C15=""),"",SUMPRODUCT((sd_item=$B15)*((sd_sample="N") + (sd_sample="Y")*(cfg_use_sample="Yes"))*sd_qty)/$C15),"") | F15: =IFERROR(IF(OR($B15="",$C15<10,NOT(ISNUMBER($P15)),$P15=0),"",$Q15/$P15),"") | G15: =IFERROR(IF(OR(NOT(ISNUMBER($F15)),$C15<3,$P15=0,NOT(ISNUMBER($R15))),"",SQRT($R15/($C15-2)/$P15)),"") | H15: =IFERROR(IF(OR(NOT(ISNUMBER($F15)),NOT(ISNUMBER($G15))),"",$F15-1.96*$G15),"") | I15: =IFERROR(IF(OR(NOT(ISNUMBER($F15)),NOT(ISNUMBER($G15))),"",$F15+1.96*$G15),"") | J15: =IF(OR($B15="",NOT(ISNUMBER($F15))),"—",IF($C15<30,"LOW",IF($I15<=-1,"HIGH","MEDIUM"))) -> — | K15: =IF($B15="","",IF(NOT(ISNUMBER($F15)),"No matching rows in SALES_DATA — using category prior",IF($C15<30,"Low sample (<30 obs) — CI is wide",IF($I15>-1,"CI crosses -1 — direction uncertain","OK")))) | L15: =IF(ISNUMBER($F15),$F15,"") | N15: =IFERROR(IF($B15="","",SUMPRODUCT((sd_item=$B15)*((sd_sample="N") + (sd_sample="Y")*(cfg_use_sample="Yes"))*sd_lnp)/SUMPRODUCT((sd_item=$B15)*((sd_sample="N") + (sd_sample="Y")*(cfg_use_sample="Yes")))),"") | O15: =IFERROR(IF($B15="","",SUMPRODUCT((sd_item=$B15)*((sd_sample="N") + (sd_sample="Y")*(cfg_use_sample="Yes"))*sd_lnq)/SUMPRODUCT((sd_item=$B15)*((sd_sample="N") + (sd_sample="Y")*(cfg_use_sample="Yes")))),"") | P15: =IFERROR(IF(OR($B15="",$N15=""),"",SUMPRODUCT((sd_item=$B15)*((sd_sample="N") + (sd_sample="Y")*(cfg_use_sample="Yes"))*(sd_lnp-$N15)^2)),"") | Q15: =IFERROR(IF(OR($B15="",$N15=""),"",SUMPRODUCT((sd_item=$B15)*((sd_sample="N") + (sd_sample="Y")*(cfg_use_sample="Yes"))*(sd_lnp-$N15)*(sd_lnq-$O15))),"") | R15: =IFERROR(IF(OR($B15="",$F15="",$F15=0,NOT(ISNUMBER($F15))),"",SUMPRODUCT((sd_item=$B15)*((sd_sample="N") + (sd_sample="Y")*(cfg_use_sample="Yes"))*(sd_lnq-$O15-$F15*(sd_lnp-$N15))^2)),"")
A16: 11 | B16: =IF(OWNER_INPUTS!B16="","",OWNER_INPUTS!B16) | C16: =IFERROR(IF($B16="","",SUMPRODUCT((sd_item=$B16)*((sd_sample="N") + (sd_sample="Y")*(cfg_use_sample="Yes"))*(sd_qty>0))),"") | D16: =IFERROR(IF(OR($B16="",$C16=0,$C16=""),"",SUMPRODUCT((sd_item=$B16)*((sd_sample="N") + (sd_sample="Y")*(cfg_use_sample="Yes"))*SALES_DATA!$F$6:$F$545)/$C16),"") | E16: =IFERROR(IF(OR($B16="",$C16=0,$C16=""),"",SUMPRODUCT((sd_item=$B16)*((sd_sample="N") + (sd_sample="Y")*(cfg_use_sample="Yes"))*sd_qty)/$C16),"") | F16: =IFERROR(IF(OR($B16="",$C16<10,NOT(ISNUMBER($P16)),$P16=0),"",$Q16/$P16),"") | G16: =IFERROR(IF(OR(NOT(ISNUMBER($F16)),$C16<3,$P16=0,NOT(ISNUMBER($R16))),"",SQRT($R16/($C16-2)/$P16)),"") | H16: =IFERROR(IF(OR(NOT(ISNUMBER($F16)),NOT(ISNUMBER($G16))),"",$F16-1.96*$G16),"") | I16: =IFERROR(IF(OR(NOT(ISNUMBER($F16)),NOT(ISNUMBER($G16))),"",$F16+1.96*$G16),"") | J16: =IF(OR($B16="",NOT(ISNUMBER($F16))),"—",IF($C16<30,"LOW",IF($I16<=-1,"HIGH","MEDIUM"))) -> — | K16: =IF($B16="","",IF(NOT(ISNUMBER($F16)),"No matching rows in SALES_DATA — using category prior",IF($C16<30,"Low sample (<30 obs) — CI is wide",IF($I16>-1,"CI crosses -1 — direction uncertain","OK")))) | L16: =IF(ISNUMBER($F16),$F16,"") | N16: =IFERROR(IF($B16="","",SUMPRODUCT((sd_item=$B16)*((sd_sample="N") + (sd_sample="Y")*(cfg_use_sample="Yes"))*sd_lnp)/SUMPRODUCT((sd_item=$B16)*((sd_sample="N") + (sd_sample="Y")*(cfg_use_sample="Yes")))),"") | O16: =IFERROR(IF($B16="","",SUMPRODUCT((sd_item=$B16)*((sd_sample="N") + (sd_sample="Y")*(cfg_use_sample="Yes"))*sd_lnq)/SUMPRODUCT((sd_item=$B16)*((sd_sample="N") + (sd_sample="Y")*(cfg_use_sample="Yes")))),"") | P16: =IFERROR(IF(OR($B16="",$N16=""),"",SUMPRODUCT((sd_item=$B16)*((sd_sample="N") + (sd_sample="Y")*(cfg_use_sample="Yes"))*(sd_lnp-$N16)^2)),"") | Q16: =IFERROR(IF(OR($B16="",$N16=""),"",SUMPRODUCT((sd_item=$B16)*((sd_sample="N") + (sd_sample="Y")*(cfg_use_sample="Yes"))*(sd_lnp-$N16)*(sd_lnq-$O16))),"") | R16: =IFERROR(IF(OR($B16="",$F16="",$F16=0,NOT(ISNUMBER($F16))),"",SUMPRODUCT((sd_item=$B16)*((sd_sample="N") + (sd_sample="Y")*(cfg_use_sample="Yes"))*(sd_lnq-$O16-$F16*(sd_lnp-$N16))^2)),"")
A17: 12 | B17: =IF(OWNER_INPUTS!B17="","",OWNER_INPUTS!B17) | C17: =IFERROR(IF($B17="","",SUMPRODUCT((sd_item=$B17)*((sd_sample="N") + (sd_sample="Y")*(cfg_use_sample="Yes"))*(sd_qty>0))),"") | D17: =IFERROR(IF(OR($B17="",$C17=0,$C17=""),"",SUMPRODUCT((sd_item=$B17)*((sd_sample="N") + (sd_sample="Y")*(cfg_use_sample="Yes"))*SALES_DATA!$F$6:$F$545)/$C17),"") | E17: =IFERROR(IF(OR($B17="",$C17=0,$C17=""),"",SUMPRODUCT((sd_item=$B17)*((sd_sample="N") + (sd_sample="Y")*(cfg_use_sample="Yes"))*sd_qty)/$C17),"") | F17: =IFERROR(IF(OR($B17="",$C17<10,NOT(ISNUMBER($P17)),$P17=0),"",$Q17/$P17),"") | G17: =IFERROR(IF(OR(NOT(ISNUMBER($F17)),$C17<3,$P17=0,NOT(ISNUMBER($R17))),"",SQRT($R17/($C17-2)/$P17)),"") | H17: =IFERROR(IF(OR(NOT(ISNUMBER($F17)),NOT(ISNUMBER($G17))),"",$F17-1.96*$G17),"") | I17: =IFERROR(IF(OR(NOT(ISNUMBER($F17)),NOT(ISNUMBER($G17))),"",$F17+1.96*$G17),"") | J17: =IF(OR($B17="",NOT(ISNUMBER($F17))),"—",IF($C17<30,"LOW",IF($I17<=-1,"HIGH","MEDIUM"))) -> — | K17: =IF($B17="","",IF(NOT(ISNUMBER($F17)),"No matching rows in SALES_DATA — using category prior",IF($C17<30,"Low sample (<30 obs) — CI is wide",IF($I17>-1,"CI crosses -1 — direction uncertain","OK")))) | L17: =IF(ISNUMBER($F17),$F17,"") | N17: =IFERROR(IF($B17="","",SUMPRODUCT((sd_item=$B17)*((sd_sample="N") + (sd_sample="Y")*(cfg_use_sample="Yes"))*sd_lnp)/SUMPRODUCT((sd_item=$B17)*((sd_sample="N") + (sd_sample="Y")*(cfg_use_sample="Yes")))),"") | O17: =IFERROR(IF($B17="","",SUMPRODUCT((sd_item=$B17)*((sd_sample="N") + (sd_sample="Y")*(cfg_use_sample="Yes"))*sd_lnq)/SUMPRODUCT((sd_item=$B17)*((sd_sample="N") + (sd_sample="Y")*(cfg_use_sample="Yes")))),"") | P17: =IFERROR(IF(OR($B17="",$N17=""),"",SUMPRODUCT((sd_item=$B17)*((sd_sample="N") + (sd_sample="Y")*(cfg_use_sample="Yes"))*(sd_lnp-$N17)^2)),"") | Q17: =IFERROR(IF(OR($B17="",$N17=""),"",SUMPRODUCT((sd_item=$B17)*((sd_sample="N") + (sd_sample="Y")*(cfg_use_sample="Yes"))*(sd_lnp-$N17)*(sd_lnq-$O17))),"") | R17: =IFERROR(IF(OR($B17="",$F17="",$F17=0,NOT(ISNUMBER($F17))),"",SUMPRODUCT((sd_item=$B17)*((sd_sample="N") + (sd_sample="Y")*(cfg_use_sample="Yes"))*(sd_lnq-$O17-$F17*(sd_lnp-$N17))^2)),"")
... A35: 30 | B35: =IF(OWNER_INPUTS!B35="","",OWNER_INPUTS!B35) | C35: =IFERROR(IF($B35="","",SUMPRODUCT((sd_item=$B35)*((sd_sample="N") + (sd_sample="Y")*(cfg_use_sample="Yes"))*(sd_qty>0))),"") | D35: =IFERROR(IF(OR($B35="",$C35=0,$C35=""),"",SUMPRODUCT((sd_item=$B35)*((sd_sample="N") + (sd_sample="Y")*(cfg_use_sample="Yes"))*SALES_DATA!$F$6:$F$545)/$C35),"") | E35: =IFERROR(IF(OR($B35="",$C35=0,$C35=""),"",SUMPRODUCT((sd_item=$B35)*((sd_sample="N") + (sd_sample="Y")*(cfg_use_sample="Yes"))*sd_qty)/$C35),"") | F35: =IFERROR(IF(OR($B35="",$C35<10,NOT(ISNUMBER($P35)),$P35=0),"",$Q35/$P35),"") | G35: =IFERROR(IF(OR(NOT(ISNUMBER($F35)),$C35<3,$P35=0,NOT(ISNUMBER($R35))),"",SQRT($R35/($C35-2)/$P35)),"") | H35: =IFERROR(IF(OR(NOT(ISNUMBER($F35)),NOT(ISNUMBER($G35))),"",$F35-1.96*$G35),"") | I35: =IFERROR(IF(OR(NOT(ISNUMBER($F35)),NOT(ISNUMBER($G35))),"",$F35+1.96*$G35),"") | J35: =IF(OR($B35="",NOT(ISNUMBER($F35))),"—",IF($C35<30,"LOW",IF($I35<=-1,"HIGH","MEDIUM"))) -> — | K35: =IF($B35="","",IF(NOT(ISNUMBER($F35)),"No matching rows in SALES_DATA — using category prior",IF($C35<30,"Low sample (<30 obs) — CI is wide",IF($I35>-1,"CI crosses -1 — direction uncertain","OK")))) | L35: =IF(ISNUMBER($F35),$F35,"") | N35: =IFERROR(IF($B35="","",SUMPRODUCT((sd_item=$B35)*((sd_sample="N") + (sd_sample="Y")*(cfg_use_sample="Yes"))*sd_lnp)/SUMPRODUCT((sd_item=$B35)*((sd_sample="N") + (sd_sample="Y")*(cfg_use_sample="Yes")))),"") | O35: =IFERROR(IF($B35="","",SUMPRODUCT((sd_item=$B35)*((sd_sample="N") + (sd_sample="Y")*(cfg_use_sample="Yes"))*sd_lnq)/SUMPRODUCT((sd_item=$B35)*((sd_sample="N") + (sd_sample="Y")*(cfg_use_sample="Yes")))),"") | P35: =IFERROR(IF(OR($B35="",$N35=""),"",SUMPRODUCT((sd_item=$B35)*((sd_sample="N") + (sd_sample="Y")*(cfg_use_sample="Yes"))*(sd_lnp-$N35)^2)),"") | Q35: =IFERROR(IF(OR($B35="",$N35=""),"",SUMPRODUCT((sd_item=$B35)*((sd_sample="N") + (sd_sample="Y")*(cfg_use_sample="Yes"))*(sd_lnp-$N35)*(sd_lnq-$O35))),"") | R35: =IFERROR(IF(OR($B35="",$F35="",$F35=0,NOT(ISNUMBER($F35))),"",SUMPRODUCT((sd_item=$B35)*((sd_sample="N") + (sd_sample="Y")*(cfg_use_sample="Yes"))*(sd_lnq-$O35-$F35*(sd_lnp-$N35))^2)),"")

Sheet OPTIMIZER
A1: Pricing Optimizer — Model + Psychology + Guardrails
A3: For each item: estimate elasticity (or fall back to prior), compute the profit-maximizing price under constant-elasticity demand, shrink toward current price by a confidence-dependent amount, cap by item role, cap by global guardrails, adjust for psychological thresholds, and round to the current currency. The Recommended Price (column W) is what should go on the menu.
A5: # | B5: Item | C5: Category | D5: Role | E5: Cost | F5: Current price | G5: Daily qty | H5: Elasticity (used) | I5: Source | J5: Confidence | K5: Lerner P* | L5: Shrinkage factor | M5: Shrunk target | N5: Role cap % | O5: Role floor % | P5: After role cap | Q5: After global guard | R5: After threshold | S5: Round step | T5: Recommended price | U5: Δ% | V5: Projected qty/day | W5: Δ daily profit | X5: Δ monthly profit | Y5: Charm up (helper) | Z5: Charm dn (helper) | AA5: Ending applied
A6: 1 | B6: =IF(OWNER_INPUTS!B6="","",OWNER_INPUTS!B6) -> Flat White | C6: =IF($B6="","",OWNER_INPUTS!C6) -> Coffee | D6: =IF($B6="","",OWNER_INPUTS!D6) -> Traffic Driver | E6: =IF($B6="","",OWNER_INPUTS!E6) -> 1 | F6: =IF($B6="","",OWNER_INPUTS!F6) -> 4.2 | G6: =IF($B6="","",OWNER_INPUTS!G6/30) -> 50 | H6: =IF($B6="","",IFERROR( IF(ISNUMBER(INDEX(cal_estimate,MATCH($B6,cal_items,0))), INDEX(cal_estimate,MATCH($B6,cal_items,0)), IFERROR(VLOOKUP($C6,tbl_priors,2,FALSE()), VLOOKUP("Other",tbl_priors,2,FALSE()))), IFERROR(VLOOKUP($C6,tbl_priors,2,FALSE()), VLOOKUP("Other",tbl_priors,2,FALSE())))) -> -1.1 | I6: =IF($B6="","",IF(IFERROR(ISNUMBER(INDEX(cal_estimate,MATCH($B6,cal_items,0))),FALSE()),"Estimated","Prior")) -> Prior | J6: =IF($B6="","",IF($I6="Estimated", IFERROR(INDEX(cal_conf,MATCH($B6,cal_items,0)),"LOW"),"LOW")) -> LOW | K6: =IF($B6="","",IF($H6<-1,$E6*$H6/($H6+1),"test")) -> 11 | L6: =IF($B6="","",IF($J6="HIGH",cfg_shr_high,IF($J6="MEDIUM",cfg_shr_med,cfg_shr_low))) -> 0.25 | M6: =IF($B6="","",IF($K6="test", $F6*(1+IFERROR(VLOOKUP($D6,tbl_roles,4,FALSE()), VLOOKUP("Other",tbl_roles,4,FALSE()))), $F6+$L6*($K6-$F6))) -> 5.9 | N6: =IF($B6="","",IFERROR(VLOOKUP($D6,tbl_roles,2,FALSE()),VLOOKUP("Other",tbl_roles,2,FALSE()))) -> 0.03 | O6: =IF($B6="","",IFERROR(VLOOKUP($D6,tbl_roles,3,FALSE()),VLOOKUP("Other",tbl_roles,3,FALSE()))) -> -0.05 | P6: =IF($B6="","",MIN($F6*(1+$N6),MAX($F6*(1+$O6),$M6))) -> 4.326 | Q6: =IF($B6="","",MIN($F6*(1+cfg_max_raise),MAX($F6*(1+cfg_max_cut),$P6))) -> 4.326 | R6: =IF($B6="","",IF(cfg_currency="IDR",IF($B6="","",IFERROR(IF(AND($Q6>INDEX(tbl_thr_idr,MATCH($Q6,INDEX(tbl_thr_idr,0,1),1),1),$Q6<=INDEX(tbl_thr_idr,MATCH($Q6,INDEX(tbl_thr_idr,0,1),1),1)+INDEX(tbl_thr_idr,MATCH($Q6,INDEX(tbl_thr_idr,0,1),1),2)),FLOOR(INDEX(tbl_thr_idr,MATCH($Q6,INDEX(tbl_thr_idr,0,1),1),1)-1,cfg_round_to),$Q6),$Q6)),IF($B6="","",IFERROR(IF(AND($Q6>INDEX(tbl_thr_usd,MATCH($Q6,INDEX(tbl_thr_usd,0,1),1),1),$Q6<=INDEX(tbl_thr_usd,MATCH($Q6,INDEX(tbl_thr_usd,0,1),1),1)+INDEX(tbl_thr_usd,MATCH($Q6,INDEX(tbl_thr_usd,0,1),1),2)),FLOOR(INDEX(tbl_thr_usd,MATCH($Q6,INDEX(tbl_thr_usd,0,1),1),1)-0.01,cfg_round_to),$Q6),$Q6)))) -> 4.326 | S6: =IF($B6="","",cfg_round_to) -> 0.1 | T6: =IF($B6="","",IF(N($AA6)=0,MIN(FLOOR($F6*(1+MIN($N6,cfg_max_raise)),$S6),MAX(CEILING($F6*(1+MAX($O6,cfg_max_cut)),$S6),MROUND($R6,$S6))),IF(SIGN(MIN(FLOOR($F6*(1+MIN($N6,cfg_max_raise)),$S6),MAX(CEILING($F6*(1+MAX($O6,cfg_max_cut)),$S6),MROUND($R6,$S6)))-$F6)>0,IF(AND(N($Y6)>=$F6,N($Y6)>=CEILING($F6*(1+MAX($O6,cfg_max_cut)),$S6),N($Y6)<=FLOOR($F6*(1+MIN($N6,cfg_max_raise)),$S6)),N($Y6),IF(AND(N($Z6)>$F6,N($Z6)>=CEILING($F6*(1+MAX($O6,cfg_max_cut)),$S6),N($Z6)<=FLOOR($F6*(1+MIN($N6,cfg_max_raise)),$S6)),N($Z6),MIN(FLOOR($F6*(1+MIN($N6,cfg_max_raise)),$S6),MAX(CEILING($F6*(1+MAX($O6,cfg_max_cut)),$S6),MROUND($R6,$S6))))),IF(SIGN(MIN(FLOOR($F6*(1+MIN($N6,cfg_max_raise)),$S6),MAX(CEILING($F6*(1+MAX($O6,cfg_max_cut)),$S6),MROUND($R6,$S6)))-$F6)<0,IF(AND(N($Z6)<=$F6,N($Z6)>=CEILING($F6*(1+MAX($O6,cfg_max_cut)),$S6),N($Z6)<=FLOOR($F6*(1+MIN($N6,cfg_max_raise)),$S6)),N($Z6),IF(AND(N($Y6)<$F6,N($Y6)>=CEILING($F6*(1+MAX($O6,cfg_max_cut)),$S6),N($Y6)<=FLOOR($F6*(1+MIN($N6,cfg_max_raise)),$S6)),N($Y6),MIN(FLOOR($F6*(1+MIN($N6,cfg_max_raise)),$S6),MAX(CEILING($F6*(1+MAX($O6,cfg_max_cut)),$S6),MROUND($R6,$S6))))),IF(ABS(N($Y6)-$F6)<=ABS(N($Z6)-$F6),IF(AND(N($Y6)>=CEILING($F6*(1+MAX($O6,cfg_max_cut)),$S6),N($Y6)<=FLOOR($F6*(1+MIN($N6,cfg_max_raise)),$S6)),N($Y6),MIN(FLOOR($F6*(1+MIN($N6,cfg_max_raise)),$S6),MAX(CEILING($F6*(1+MAX($O6,cfg_max_cut)),$S6),MROUND($R6,$S6)))),IF(AND(N($Z6)>=CEILING($F6*(1+MAX($O6,cfg_max_cut)),$S6),N($Z6)<=FLOOR($F6*(1+MIN($N6,cfg_max_raise)),$S6)),N($Z6),MIN(FLOOR($F6*(1+MIN($N6,cfg_max_raise)),$S6),MAX(CEILING($F6*(1+MAX($O6,cfg_max_cut)),$S6),MROUND($R6,$S6))))))))) -> 4.3 | U6: =IF($B6="","",IFERROR($T6/$F6-1,0)) -> 0.023809524 | V6: =IF($B6="","",$G6*($T6/$F6)^$H6) -> 48.722428 | W6: =IF($B6="","",($T6-$E6)*$V6-($F6-$E6)*$G6) -> 0.78401245 | X6: =IF($B6="","",$W6*30) -> 23.520374 | Y6: =IF($B6="","",IF(AND(cfg_round_to<=0.5,IFERROR(VALUE(cfg_ending),0)>0),CEILING($R6-VALUE(cfg_ending),1)+VALUE(cfg_ending),"")) | Z6: =IF($B6="","",IF(AND(cfg_round_to<=0.5,IFERROR(VALUE(cfg_ending),0)>0),FLOOR($R6-VALUE(cfg_ending),1)+VALUE(cfg_ending),"")) | AA6: =IF($B6="","",IF(AND(cfg_round_to<=0.5,IFERROR(VALUE(cfg_ending),0)>0),VALUE(cfg_ending),0)) -> 0
A7: 2 | B7: =IF(OWNER_INPUTS!B7="","",OWNER_INPUTS!B7) -> Matcha Latte | C7: =IF($B7="","",OWNER_INPUTS!C7) -> Specialty Drink | D7: =IF($B7="","",OWNER_INPUTS!D7) -> Profit Driver | E7: =IF($B7="","",OWNER_INPUTS!E7) -> 1.4 | F7: =IF($B7="","",OWNER_INPUTS!F7) -> 4.8 | G7: =IF($B7="","",OWNER_INPUTS!G7/30) -> 40 | H7: =IF($B7="","",IFERROR( IF(ISNUMBER(INDEX(cal_estimate,MATCH($B7,cal_items,0))), INDEX(cal_estimate,MATCH($B7,cal_items,0)), IFERROR(VLOOKUP($C7,tbl_priors,2,FALSE()), VLOOKUP("Other",tbl_priors,2,FALSE()))), IFERROR(VLOOKUP($C7,tbl_priors,2,FALSE()), VLOOKUP("Other",tbl_priors,2,FALSE())))) -> -1.3 | I7: =IF($B7="","",IF(IFERROR(ISNUMBER(INDEX(cal_estimate,MATCH($B7,cal_items,0))),FALSE()),"Estimated","Prior")) -> Prior | J7: =IF($B7="","",IF($I7="Estimated", IFERROR(INDEX(cal_conf,MATCH($B7,cal_items,0)),"LOW"),"LOW")) -> LOW | K7: =IF($B7="","",IF($H7<-1,$E7*$H7/($H7+1),"test")) -> 6.0666667 | L7: =IF($B7="","",IF($J7="HIGH",cfg_shr_high,IF($J7="MEDIUM",cfg_shr_med,cfg_shr_low))) -> 0.25 | M7: =IF($B7="","",IF($K7="test", $F7*(1+IFERROR(VLOOKUP($D7,tbl_roles,4,FALSE()), VLOOKUP("Other",tbl_roles,4,FALSE()))), $F7+$L7*($K7-$F7))) -> 5.1166667 | N7: =IF($B7="","",IFERROR(VLOOKUP($D7,tbl_roles,2,FALSE()),VLOOKUP("Other",tbl_roles,2,FALSE()))) -> 0.1 | O7: =IF($B7="","",IFERROR(VLOOKUP($D7,tbl_roles,3,FALSE()),VLOOKUP("Other",tbl_roles,3,FALSE()))) -> -0.05 | P7: =IF($B7="","",MIN($F7*(1+$N7),MAX($F7*(1+$O7),$M7))) -> 5.1166667 | Q7: =IF($B7="","",MIN($F7*(1+cfg_max_raise),MAX($F7*(1+cfg_max_cut),$P7))) -> 5.1166667 | R7: =IF($B7="","",IF(cfg_currency="IDR",IF($B7="","",IFERROR(IF(AND($Q7>INDEX(tbl_thr_idr,MATCH($Q7,INDEX(tbl_thr_idr,0,1),1),1),$Q7<=INDEX(tbl_thr_idr,MATCH($Q7,INDEX(tbl_thr_idr,0,1),1),1)+INDEX(tbl_thr_idr,MATCH($Q7,INDEX(tbl_thr_idr,0,1),1),2)),FLOOR(INDEX(tbl_thr_idr,MATCH($Q7,INDEX(tbl_thr_idr,0,1),1),1)-1,cfg_round_to),$Q7),$Q7)),IF($B7="","",IFERROR(IF(AND($Q7>INDEX(tbl_thr_usd,MATCH($Q7,INDEX(tbl_thr_usd,0,1),1),1),$Q7<=INDEX(tbl_thr_usd,MATCH($Q7,INDEX(tbl_thr_usd,0,1),1),1)+INDEX(tbl_thr_usd,MATCH($Q7,INDEX(tbl_thr_usd,0,1),1),2)),FLOOR(INDEX(tbl_thr_usd,MATCH($Q7,INDEX(tbl_thr_usd,0,1),1),1)-0.01,cfg_round_to),$Q7),$Q7)))) -> 4.9 | S7: =IF($B7="","",cfg_round_to) -> 0.1 | T7: =IF($B7="","",IF(N($AA7)=0,MIN(FLOOR($F7*(1+MIN($N7,cfg_max_raise)),$S7),MAX(CEILING($F7*(1+MAX($O7,cfg_max_cut)),$S7),MROUND($R7,$S7))),IF(SIGN(MIN(FLOOR($F7*(1+MIN($N7,cfg_max_raise)),$S7),MAX(CEILING($F7*(1+MAX($O7,cfg_max_cut)),$S7),MROUND($R7,$S7)))-$F7)>0,IF(AND(N($Y7)>=$F7,N($Y7)>=CEILING($F7*(1+MAX($O7,cfg_max_cut)),$S7),N($Y7)<=FLOOR($F7*(1+MIN($N7,cfg_max_raise)),$S7)),N($Y7),IF(AND(N($Z7)>$F7,N($Z7)>=CEILING($F7*(1+MAX($O7,cfg_max_cut)),$S7),N($Z7)<=FLOOR($F7*(1+MIN($N7,cfg_max_raise)),$S7)),N($Z7),MIN(FLOOR($F7*(1+MIN($N7,cfg_max_raise)),$S7),MAX(CEILING($F7*(1+MAX($O7,cfg_max_cut)),$S7),MROUND($R7,$S7))))),IF(SIGN(MIN(FLOOR($F7*(1+MIN($N7,cfg_max_raise)),$S7),MAX(CEILING($F7*(1+MAX($O7,cfg_max_cut)),$S7),MROUND($R7,$S7)))-$F7)<0,IF(AND(N($Z7)<=$F7,N($Z7)>=CEILING($F7*(1+MAX($O7,cfg_max_cut)),$S7),N($Z7)<=FLOOR($F7*(1+MIN($N7,cfg_max_raise)),$S7)),N($Z7),IF(AND(N($Y7)<$F7,N($Y7)>=CEILING($F7*(1+MAX($O7,cfg_max_cut)),$S7),N($Y7)<=FLOOR($F7*(1+MIN($N7,cfg_max_raise)),$S7)),N($Y7),MIN(FLOOR($F7*(1+MIN($N7,cfg_max_raise)),$S7),MAX(CEILING($F7*(1+MAX($O7,cfg_max_cut)),$S7),MROUND($R7,$S7))))),IF(ABS(N($Y7)-$F7)<=ABS(N($Z7)-$F7),IF(AND(N($Y7)>=CEILING($F7*(1+MAX($O7,cfg_max_cut)),$S7),N($Y7)<=FLOOR($F7*(1+MIN($N7,cfg_max_raise)),$S7)),N($Y7),MIN(FLOOR($F7*(1+MIN($N7,cfg_max_raise)),$S7),MAX(CEILING($F7*(1+MAX($O7,cfg_max_cut)),$S7),MROUND($R7,$S7)))),IF(AND(N($Z7)>=CEILING($F7*(1+MAX($O7,cfg_max_cut)),$S7),N($Z7)<=FLOOR($F7*(1+MIN($N7,cfg_max_raise)),$S7)),N($Z7),MIN(FLOOR($F7*(1+MIN($N7,cfg_max_raise)),$S7),MAX(CEILING($F7*(1+MAX($O7,cfg_max_cut)),$S7),MROUND($R7,$S7))))))))) -> 4.9 | U7: =IF($B7="","",IFERROR($T7/$F7-1,0)) -> 0.020833333 | V7: =IF($B7="","",$G7*($T7/$F7)^$H7) -> 38.94204 | W7: =IF($B7="","",($T7-$E7)*$V7-($F7-$E7)*$G7) -> 0.29713917 | X7: =IF($B7="","",$W7*30) -> 8.914175 | Y7: =IF($B7="","",IF(AND(cfg_round_to<=0.5,IFERROR(VALUE(cfg_ending),0)>0),CEILING($R7-VALUE(cfg_ending),1)+VALUE(cfg_ending),"")) | Z7: =IF($B7="","",IF(AND(cfg_round_to<=0.5,IFERROR(VALUE(cfg_ending),0)>0),FLOOR($R7-VALUE(cfg_ending),1)+VALUE(cfg_ending),"")) | AA7: =IF($B7="","",IF(AND(cfg_round_to<=0.5,IFERROR(VALUE(cfg_ending),0)>0),VALUE(cfg_ending),0)) -> 0
A8: 3 | B8: =IF(OWNER_INPUTS!B8="","",OWNER_INPUTS!B8) -> Eggs Benedict | C8: =IF($B8="","",OWNER_INPUTS!C8) -> Sandwich/Food | D8: =IF($B8="","",OWNER_INPUTS!D8) -> Signature | E8: =IF($B8="","",OWNER_INPUTS!E8) -> 4.2 | F8: =IF($B8="","",OWNER_INPUTS!F8) -> 9.8 | G8: =IF($B8="","",OWNER_INPUTS!G8/30) -> 30 | H8: =IF($B8="","",IFERROR( IF(ISNUMBER(INDEX(cal_estimate,MATCH($B8,cal_items,0))), INDEX(cal_estimate,MATCH($B8,cal_items,0)), IFERROR(VLOOKUP($C8,tbl_priors,2,FALSE()), VLOOKUP("Other",tbl_priors,2,FALSE()))), IFERROR(VLOOKUP($C8,tbl_priors,2,FALSE()), VLOOKUP("Other",tbl_priors,2,FALSE())))) -> -0.8 | I8: =IF($B8="","",IF(IFERROR(ISNUMBER(INDEX(cal_estimate,MATCH($B8,cal_items,0))),FALSE()),"Estimated","Prior")) -> Prior | J8: =IF($B8="","",IF($I8="Estimated", IFERROR(INDEX(cal_conf,MATCH($B8,cal_items,0)),"LOW"),"LOW")) -> LOW | K8: =IF($B8="","",IF($H8<-1,$E8*$H8/($H8+1),"test")) -> test | L8: =IF($B8="","",IF($J8="HIGH",cfg_shr_high,IF($J8="MEDIUM",cfg_shr_med,cfg_shr_low))) -> 0.25 | M8: =IF($B8="","",IF($K8="test", $F8*(1+IFERROR(VLOOKUP($D8,tbl_roles,4,FALSE()), VLOOKUP("Other",tbl_roles,4,FALSE()))), $F8+$L8*($K8-$F8))) -> 10.29 | N8: =IF($B8="","",IFERROR(VLOOKUP($D8,tbl_roles,2,FALSE()),VLOOKUP("Other",tbl_roles,2,FALSE()))) -> 0.1 | O8: =IF($B8="","",IFERROR(VLOOKUP($D8,tbl_roles,3,FALSE()),VLOOKUP("Other",tbl_roles,3,FALSE()))) -> -0.05 | P8: =IF($B8="","",MIN($F8*(1+$N8),MAX($F8*(1+$O8),$M8))) -> 10.29 | Q8: =IF($B8="","",MIN($F8*(1+cfg_max_raise),MAX($F8*(1+cfg_max_cut),$P8))) -> 10.29 | R8: =IF($B8="","",IF(cfg_currency="IDR",IF($B8="","",IFERROR(IF(AND($Q8>INDEX(tbl_thr_idr,MATCH($Q8,INDEX(tbl_thr_idr,0,1),1),1),$Q8<=INDEX(tbl_thr_idr,MATCH($Q8,INDEX(tbl_thr_idr,0,1),1),1)+INDEX(tbl_thr_idr,MATCH($Q8,INDEX(tbl_thr_idr,0,1),1),2)),FLOOR(INDEX(tbl_thr_idr,MATCH($Q8,INDEX(tbl_thr_idr,0,1),1),1)-1,cfg_round_to),$Q8),$Q8)),IF($B8="","",IFERROR(IF(AND($Q8>INDEX(tbl_thr_usd,MATCH($Q8,INDEX(tbl_thr_usd,0,1),1),1),$Q8<=INDEX(tbl_thr_usd,MATCH($Q8,INDEX(tbl_thr_usd,0,1),1),1)+INDEX(tbl_thr_usd,MATCH($Q8,INDEX(tbl_thr_usd,0,1),1),2)),FLOOR(INDEX(tbl_thr_usd,MATCH($Q8,INDEX(tbl_thr_usd,0,1),1),1)-0.01,cfg_round_to),$Q8),$Q8)))) -> 9.9 | S8: =IF($B8="","",cfg_round_to) -> 0.1 | T8: =IF($B8="","",IF(N($AA8)=0,MIN(FLOOR($F8*(1+MIN($N8,cfg_max_raise)),$S8),MAX(CEILING($F8*(1+MAX($O8,cfg_max_cut)),$S8),MROUND($R8,$S8))),IF(SIGN(MIN(FLOOR($F8*(1+MIN($N8,cfg_max_raise)),$S8),MAX(CEILING($F8*(1+MAX($O8,cfg_max_cut)),$S8),MROUND($R8,$S8)))-$F8)>0,IF(AND(N($Y8)>=$F8,N($Y8)>=CEILING($F8*(1+MAX($O8,cfg_max_cut)),$S8),N($Y8)<=FLOOR($F8*(1+MIN($N8,cfg_max_raise)),$S8)),N($Y8),IF(AND(N($Z8)>$F8,N($Z8)>=CEILING($F8*(1+MAX($O8,cfg_max_cut)),$S8),N($Z8)<=FLOOR($F8*(1+MIN($N8,cfg_max_raise)),$S8)),N($Z8),MIN(FLOOR($F8*(1+MIN($N8,cfg_max_raise)),$S8),MAX(CEILING($F8*(1+MAX($O8,cfg_max_cut)),$S8),MROUND($R8,$S8))))),IF(SIGN(MIN(FLOOR($F8*(1+MIN($N8,cfg_max_raise)),$S8),MAX(CEILING($F8*(1+MAX($O8,cfg_max_cut)),$S8),MROUND($R8,$S8)))-$F8)<0,IF(AND(N($Z8)<=$F8,N($Z8)>=CEILING($F8*(1+MAX($O8,cfg_max_cut)),$S8),N($Z8)<=FLOOR($F8*(1+MIN($N8,cfg_max_raise)),$S8)),N($Z8),IF(AND(N($Y8)<$F8,N($Y8)>=CEILING($F8*(1+MAX($O8,cfg_max_cut)),$S8),N($Y8)<=FLOOR($F8*(1+MIN($N8,cfg_max_raise)),$S8)),N($Y8),MIN(FLOOR($F8*(1+MIN($N8,cfg_max_raise)),$S8),MAX(CEILING($F8*(1+MAX($O8,cfg_max_cut)),$S8),MROUND($R8,$S8))))),IF(ABS(N($Y8)-$F8)<=ABS(N($Z8)-$F8),IF(AND(N($Y8)>=CEILING($F8*(1+MAX($O8,cfg_max_cut)),$S8),N($Y8)<=FLOOR($F8*(1+MIN($N8,cfg_max_raise)),$S8)),N($Y8),MIN(FLOOR($F8*(1+MIN($N8,cfg_max_raise)),$S8),MAX(CEILING($F8*(1+MAX($O8,cfg_max_cut)),$S8),MROUND($R8,$S8)))),IF(AND(N($Z8)>=CEILING($F8*(1+MAX($O8,cfg_max_cut)),$S8),N($Z8)<=FLOOR($F8*(1+MIN($N8,cfg_max_raise)),$S8)),N($Z8),MIN(FLOOR($F8*(1+MIN($N8,cfg_max_raise)),$S8),MAX(CEILING($F8*(1+MAX($O8,cfg_max_cut)),$S8),MROUND($R8,$S8))))))))) -> 9.9 | U8: =IF($B8="","",IFERROR($T8/$F8-1,0)) -> 0.010204082 | V8: =IF($B8="","",$G8*($T8/$F8)^$H8) -> 29.75733 | W8: =IF($B8="","",($T8-$E8)*$V8-($F8-$E8)*$G8) -> 1.6167804 | X8: =IF($B8="","",$W8*30) -> 48.503411 | Y8: =IF($B8="","",IF(AND(cfg_round_to<=0.5,IFERROR(VALUE(cfg_ending),0)>0),CEILING($R8-VALUE(cfg_ending),1)+VALUE(cfg_ending),"")) | Z8: =IF($B8="","",IF(AND(cfg_round_to<=0.5,IFERROR(VALUE(cfg_ending),0)>0),FLOOR($R8-VALUE(cfg_ending),1)+VALUE(cfg_ending),"")) | AA8: =IF($B8="","",IF(AND(cfg_round_to<=0.5,IFERROR(VALUE(cfg_ending),0)>0),VALUE(cfg_ending),0)) -> 0
A9: 4 | B9: =IF(OWNER_INPUTS!B9="","",OWNER_INPUTS!B9) -> Avocado Toast | C9: =IF($B9="","",OWNER_INPUTS!C9) -> Sandwich/Food | D9: =IF($B9="","",OWNER_INPUTS!D9) -> Core | E9: =IF($B9="","",OWNER_INPUTS!E9) -> 4.5 | F9: =IF($B9="","",OWNER_INPUTS!F9) -> 10.5 | G9: =IF($B9="","",OWNER_INPUTS!G9/30) -> 35 | H9: =IF($B9="","",IFERROR( IF(ISNUMBER(INDEX(cal_estimate,MATCH($B9,cal_items,0))), INDEX(cal_estimate,MATCH($B9,cal_items,0)), IFERROR(VLOOKUP($C9,tbl_priors,2,FALSE()), VLOOKUP("Other",tbl_priors,2,FALSE()))), IFERROR(VLOOKUP($C9,tbl_priors,2,FALSE()), VLOOKUP("Other",tbl_priors,2,FALSE())))) -> -0.8 | I9: =IF($B9="","",IF(IFERROR(ISNUMBER(INDEX(cal_estimate,MATCH($B9,cal_items,0))),FALSE()),"Estimated","Prior")) -> Prior | J9: =IF($B9="","",IF($I9="Estimated", IFERROR(INDEX(cal_conf,MATCH($B9,cal_items,0)),"LOW"),"LOW")) -> LOW | K9: =IF($B9="","",IF($H9<-1,$E9*$H9/($H9+1),"test")) -> test | L9: =IF($B9="","",IF($J9="HIGH",cfg_shr_high,IF($J9="MEDIUM",cfg_shr_med,cfg_shr_low))) -> 0.25 | M9: =IF($B9="","",IF($K9="test", $F9*(1+IFERROR(VLOOKUP($D9,tbl_roles,4,FALSE()), VLOOKUP("Other",tbl_roles,4,FALSE()))), $F9+$L9*($K9-$F9))) -> 10.71 | N9: =IF($B9="","",IFERROR(VLOOKUP($D9,tbl_roles,2,FALSE()),VLOOKUP("Other",tbl_roles,2,FALSE()))) -> 0.06 | O9: =IF($B9="","",IFERROR(VLOOKUP($D9,tbl_roles,3,FALSE()),VLOOKUP("Other",tbl_roles,3,FALSE()))) -> -0.05 | P9: =IF($B9="","",MIN($F9*(1+$N9),MAX($F9*(1+$O9),$M9))) -> 10.71 | Q9: =IF($B9="","",MIN($F9*(1+cfg_max_raise),MAX($F9*(1+cfg_max_cut),$P9))) -> 10.71 | R9: =IF($B9="","",IF(cfg_currency="IDR",IF($B9="","",IFERROR(IF(AND($Q9>INDEX(tbl_thr_idr,MATCH($Q9,INDEX(tbl_thr_idr,0,1),1),1),$Q9<=INDEX(tbl_thr_idr,MATCH($Q9,INDEX(tbl_thr_idr,0,1),1),1)+INDEX(tbl_thr_idr,MATCH($Q9,INDEX(tbl_thr_idr,0,1),1),2)),FLOOR(INDEX(tbl_thr_idr,MATCH($Q9,INDEX(tbl_thr_idr,0,1),1),1)-1,cfg_round_to),$Q9),$Q9)),IF($B9="","",IFERROR(IF(AND($Q9>INDEX(tbl_thr_usd,MATCH($Q9,INDEX(tbl_thr_usd,0,1),1),1),$Q9<=INDEX(tbl_thr_usd,MATCH($Q9,INDEX(tbl_thr_usd,0,1),1),1)+INDEX(tbl_thr_usd,MATCH($Q9,INDEX(tbl_thr_usd,0,1),1),2)),FLOOR(INDEX(tbl_thr_usd,MATCH($Q9,INDEX(tbl_thr_usd,0,1),1),1)-0.01,cfg_round_to),$Q9),$Q9)))) -> 10.71 | S9: =IF($B9="","",cfg_round_to) -> 0.1 | T9: =IF($B9="","",IF(N($AA9)=0,MIN(FLOOR($F9*(1+MIN($N9,cfg_max_raise)),$S9),MAX(CEILING($F9*(1+MAX($O9,cfg_max_cut)),$S9),MROUND($R9,$S9))),IF(SIGN(MIN(FLOOR($F9*(1+MIN($N9,cfg_max_raise)),$S9),MAX(CEILING($F9*(1+MAX($O9,cfg_max_cut)),$S9),MROUND($R9,$S9)))-$F9)>0,IF(AND(N($Y9)>=$F9,N($Y9)>=CEILING($F9*(1+MAX($O9,cfg_max_cut)),$S9),N($Y9)<=FLOOR($F9*(1+MIN($N9,cfg_max_raise)),$S9)),N($Y9),IF(AND(N($Z9)>$F9,N($Z9)>=CEILING($F9*(1+MAX($O9,cfg_max_cut)),$S9),N($Z9)<=FLOOR($F9*(1+MIN($N9,cfg_max_raise)),$S9)),N($Z9),MIN(FLOOR($F9*(1+MIN($N9,cfg_max_raise)),$S9),MAX(CEILING($F9*(1+MAX($O9,cfg_max_cut)),$S9),MROUND($R9,$S9))))),IF(SIGN(MIN(FLOOR($F9*(1+MIN($N9,cfg_max_raise)),$S9),MAX(CEILING($F9*(1+MAX($O9,cfg_max_cut)),$S9),MROUND($R9,$S9)))-$F9)<0,IF(AND(N($Z9)<=$F9,N($Z9)>=CEILING($F9*(1+MAX($O9,cfg_max_cut)),$S9),N($Z9)<=FLOOR($F9*(1+MIN($N9,cfg_max_raise)),$S9)),N($Z9),IF(AND(N($Y9)<$F9,N($Y9)>=CEILING($F9*(1+MAX($O9,cfg_max_cut)),$S9),N($Y9)<=FLOOR($F9*(1+MIN($N9,cfg_max_raise)),$S9)),N($Y9),MIN(FLOOR($F9*(1+MIN($N9,cfg_max_raise)),$S9),MAX(CEILING($F9*(1+MAX($O9,cfg_max_cut)),$S9),MROUND($R9,$S9))))),IF(ABS(N($Y9)-$F9)<=ABS(N($Z9)-$F9),IF(AND(N($Y9)>=CEILING($F9*(1+MAX($O9,cfg_max_cut)),$S9),N($Y9)<=FLOOR($F9*(1+MIN($N9,cfg_max_raise)),$S9)),N($Y9),MIN(FLOOR($F9*(1+MIN($N9,cfg_max_raise)),$S9),MAX(CEILING($F9*(1+MAX($O9,cfg_max_cut)),$S9),MROUND($R9,$S9)))),IF(AND(N($Z9)>=CEILING($F9*(1+MAX($O9,cfg_max_cut)),$S9),N($Z9)<=FLOOR($F9*(1+MIN($N9,cfg_max_raise)),$S9)),N($Z9),MIN(FLOOR($F9*(1+MIN($N9,cfg_max_raise)),$S9),MAX(CEILING($F9*(1+MAX($O9,cfg_max_cut)),$S9),MROUND($R9,$S9))))))))) -> 10.7 | U9: =IF($B9="","",IFERROR($T9/$F9-1,0)) -> 0.019047619 | V9: =IF($B9="","",$G9*($T9/$F9)^$H9) -> 34.47565 | W9: =IF($B9="","",($T9-$E9)*$V9-($F9-$E9)*$G9) -> 3.7490292 | X9: =IF($B9="","",$W9*30) -> 112.47088 | Y9: =IF($B9="","",IF(AND(cfg_round_to<=0.5,IFERROR(VALUE(cfg_ending),0)>0),CEILING($R9-VALUE(cfg_ending),1)+VALUE(cfg_ending),"")) | Z9: =IF($B9="","",IF(AND(cfg_round_to<=0.5,IFERROR(VALUE(cfg_ending),0)>0),FLOOR($R9-VALUE(cfg_ending),1)+VALUE(cfg_ending),"")) | AA9: =IF($B9="","",IF(AND(cfg_round_to<=0.5,IFERROR(VALUE(cfg_ending),0)>0),VALUE(cfg_ending),0)) -> 0
A10: 5 | B10: =IF(OWNER_INPUTS!B10="","",OWNER_INPUTS!B10) -> Pancakes | C10: =IF($B10="","",OWNER_INPUTS!C10) -> Pastry | D10: =IF($B10="","",OWNER_INPUTS!D10) -> Premium Anchor | E10: =IF($B10="","",OWNER_INPUTS!E10) -> 3.5 | F10: =IF($B10="","",OWNER_INPUTS!F10) -> 8.8 | G10: =IF($B10="","",OWNER_INPUTS!G10/30) -> 25 | H10: =IF($B10="","",IFERROR( IF(ISNUMBER(INDEX(cal_estimate,MATCH($B10,cal_items,0))), INDEX(cal_estimate,MATCH($B10,cal_items,0)), IFERROR(VLOOKUP($C10,tbl_priors,2,FALSE()), VLOOKUP("Other",tbl_priors,2,FALSE()))), IFERROR(VLOOKUP($C10,tbl_priors,2,FALSE()), VLOOKUP("Other",tbl_priors,2,FALSE())))) -> -0.9 | I10: =IF($B10="","",IF(IFERROR(ISNUMBER(INDEX(cal_estimate,MATCH($B10,cal_items,0))),FALSE()),"Estimated","Prior")) -> Prior | J10: =IF($B10="","",IF($I10="Estimated", IFERROR(INDEX(cal_conf,MATCH($B10,cal_items,0)),"LOW"),"LOW")) -> LOW | K10: =IF($B10="","",IF($H10<-1,$E10*$H10/($H10+1),"test")) -> test | L10: =IF($B10="","",IF($J10="HIGH",cfg_shr_high,IF($J10="MEDIUM",cfg_shr_med,cfg_shr_low))) -> 0.25 | M10: =IF($B10="","",IF($K10="test", $F10*(1+IFERROR(VLOOKUP($D10,tbl_roles,4,FALSE()), VLOOKUP("Other",tbl_roles,4,FALSE()))), $F10+$L10*($K10-$F10))) -> 9.24 | N10: =IF($B10="","",IFERROR(VLOOKUP($D10,tbl_roles,2,FALSE()),VLOOKUP("Other",tbl_roles,2,FALSE()))) -> 0.1 | O10: =IF($B10="","",IFERROR(VLOOKUP($D10,tbl_roles,3,FALSE()),VLOOKUP("Other",tbl_roles,3,FALSE()))) -> -0.05 | P10: =IF($B10="","",MIN($F10*(1+$N10),MAX($F10*(1+$O10),$M10))) -> 9.24 | Q10: =IF($B10="","",MIN($F10*(1+cfg_max_raise),MAX($F10*(1+cfg_max_cut),$P10))) -> 9.24 | R10: =IF($B10="","",IF(cfg_currency="IDR",IF($B10="","",IFERROR(IF(AND($Q10>INDEX(tbl_thr_idr,MATCH($Q10,INDEX(tbl_thr_idr,0,1),1),1),$Q10<=INDEX(tbl_thr_idr,MATCH($Q10,INDEX(tbl_thr_idr,0,1),1),1)+INDEX(tbl_thr_idr,MATCH($Q10,INDEX(tbl_thr_idr,0,1),1),2)),FLOOR(INDEX(tbl_thr_idr,MATCH($Q10,INDEX(tbl_thr_idr,0,1),1),1)-1,cfg_round_to),$Q10),$Q10)),IF($B10="","",IFERROR(IF(AND($Q10>INDEX(tbl_thr_usd,MATCH($Q10,INDEX(tbl_thr_usd,0,1),1),1),$Q10<=INDEX(tbl_thr_usd,MATCH($Q10,INDEX(tbl_thr_usd,0,1),1),1)+INDEX(tbl_thr_usd,MATCH($Q10,INDEX(tbl_thr_usd,0,1),1),2)),FLOOR(INDEX(tbl_thr_usd,MATCH($Q10,INDEX(tbl_thr_usd,0,1),1),1)-0.01,cfg_round_to),$Q10),$Q10)))) -> 9.24 | S10: =IF($B10="","",cfg_round_to) -> 0.1 | T10: =IF($B10="","",IF(N($AA10)=0,MIN(FLOOR($F10*(1+MIN($N10,cfg_max_raise)),$S10),MAX(CEILING($F10*(1+MAX($O10,cfg_max_cut)),$S10),MROUND($R10,$S10))),IF(SIGN(MIN(FLOOR($F10*(1+MIN($N10,cfg_max_raise)),$S10),MAX(CEILING($F10*(1+MAX($O10,cfg_max_cut)),$S10),MROUND($R10,$S10)))-$F10)>0,IF(AND(N($Y10)>=$F10,N($Y10)>=CEILING($F10*(1+MAX($O10,cfg_max_cut)),$S10),N($Y10)<=FLOOR($F10*(1+MIN($N10,cfg_max_raise)),$S10)),N($Y10),IF(AND(N($Z10)>$F10,N($Z10)>=CEILING($F10*(1+MAX($O10,cfg_max_cut)),$S10),N($Z10)<=FLOOR($F10*(1+MIN($N10,cfg_max_raise)),$S10)),N($Z10),MIN(FLOOR($F10*(1+MIN($N10,cfg_max_raise)),$S10),MAX(CEILING($F10*(1+MAX($O10,cfg_max_cut)),$S10),MROUND($R10,$S10))))),IF(SIGN(MIN(FLOOR($F10*(1+MIN($N10,cfg_max_raise)),$S10),MAX(CEILING($F10*(1+MAX($O10,cfg_max_cut)),$S10),MROUND($R10,$S10)))-$F10)<0,IF(AND(N($Z10)<=$F10,N($Z10)>=CEILING($F10*(1+MAX($O10,cfg_max_cut)),$S10),N($Z10)<=FLOOR($F10*(1+MIN($N10,cfg_max_raise)),$S10)),N($Z10),IF(AND(N($Y10)<$F10,N($Y10)>=CEILING($F10*(1+MAX($O10,cfg_max_cut)),$S10),N($Y10)<=FLOOR($F10*(1+MIN($N10,cfg_max_raise)),$S10)),N($Y10),MIN(FLOOR($F10*(1+MIN($N10,cfg_max_raise)),$S10),MAX(CEILING($F10*(1+MAX($O10,cfg_max_cut)),$S10),MROUND($R10,$S10))))),IF(ABS(N($Y10)-$F10)<=ABS(N($Z10)-$F10),IF(AND(N($Y10)>=CEILING($F10*(1+MAX($O10,cfg_max_cut)),$S10),N($Y10)<=FLOOR($F10*(1+MIN($N10,cfg_max_raise)),$S10)),N($Y10),MIN(FLOOR($F10*(1+MIN($N10,cfg_max_raise)),$S10),MAX(CEILING($F10*(1+MAX($O10,cfg_max_cut)),$S10),MROUND($R10,$S10)))),IF(AND(N($Z10)>=CEILING($F10*(1+MAX($O10,cfg_max_cut)),$S10),N($Z10)<=FLOOR($F10*(1+MIN($N10,cfg_max_raise)),$S10)),N($Z10),MIN(FLOOR($F10*(1+MIN($N10,cfg_max_raise)),$S10),MAX(CEILING($F10*(1+MAX($O10,cfg_max_cut)),$S10),MROUND($R10,$S10))))))))) -> 9.2 | U10: =IF($B10="","",IFERROR($T10/$F10-1,0)) -> 0.045454545 | V10: =IF($B10="","",$G10*($T10/$F10)^$H10) -> 24.019578 | W10: =IF($B10="","",($T10-$E10)*$V10-($F10-$E10)*$G10) -> 4.4115933 | X10: =IF($B10="","",$W10*30) -> 132.3478 | Y10: =IF($B10="","",IF(AND(cfg_round_to<=0.5,IFERROR(VALUE(cfg_ending),0)>0),CEILING($R10-VALUE(cfg_ending),1)+VALUE(cfg_ending),"")) | Z10: =IF($B10="","",IF(AND(cfg_round_to<=0.5,IFERROR(VALUE(cfg_ending),0)>0),FLOOR($R10-VALUE(cfg_ending),1)+VALUE(cfg_ending),"")) | AA10: =IF($B10="","",IF(AND(cfg_round_to<=0.5,IFERROR(VALUE(cfg_ending),0)>0),VALUE(cfg_ending),0)) -> 0
A11: 6 | B11: =IF(OWNER_INPUTS!B11="","",OWNER_INPUTS!B11) -> Cheesecake | C11: =IF($B11="","",OWNER_INPUTS!C11) -> Dessert | D11: =IF($B11="","",OWNER_INPUTS!D11) -> Profit Driver | E11: =IF($B11="","",OWNER_INPUTS!E11) -> 2.1 | F11: =IF($B11="","",OWNER_INPUTS!F11) -> 5.8 | G11: =IF($B11="","",OWNER_INPUTS!G11/30) -> 15 | H11: =IF($B11="","",IFERROR( IF(ISNUMBER(INDEX(cal_estimate,MATCH($B11,cal_items,0))), INDEX(cal_estimate,MATCH($B11,cal_items,0)), IFERROR(VLOOKUP($C11,tbl_priors,2,FALSE()), VLOOKUP("Other",tbl_priors,2,FALSE()))), IFERROR(VLOOKUP($C11,tbl_priors,2,FALSE()), VLOOKUP("Other",tbl_priors,2,FALSE())))) -> -1 | I11: =IF($B11="","",IF(IFERROR(ISNUMBER(INDEX(cal_estimate,MATCH($B11,cal_items,0))),FALSE()),"Estimated","Prior")) -> Prior | J11: =IF($B11="","",IF($I11="Estimated", IFERROR(INDEX(cal_conf,MATCH($B11,cal_items,0)),"LOW"),"LOW")) -> LOW | K11: =IF($B11="","",IF($H11<-1,$E11*$H11/($H11+1),"test")) -> test | L11: =IF($B11="","",IF($J11="HIGH",cfg_shr_high,IF($J11="MEDIUM",cfg_shr_med,cfg_shr_low))) -> 0.25 | M11: =IF($B11="","",IF($K11="test", $F11*(1+IFERROR(VLOOKUP($D11,tbl_roles,4,FALSE()), VLOOKUP("Other",tbl_roles,4,FALSE()))), $F11+$L11*($K11-$F11))) -> 6.09 | N11: =IF($B11="","",IFERROR(VLOOKUP($D11,tbl_roles,2,FALSE()),VLOOKUP("Other",tbl_roles,2,FALSE()))) -> 0.1 | O11: =IF($B11="","",IFERROR(VLOOKUP($D11,tbl_roles,3,FALSE()),VLOOKUP("Other",tbl_roles,3,FALSE()))) -> -0.05 | P11: =IF($B11="","",MIN($F11*(1+$N11),MAX($F11*(1+$O11),$M11))) -> 6.09 | Q11: =IF($B11="","",MIN($F11*(1+cfg_max_raise),MAX($F11*(1+cfg_max_cut),$P11))) -> 6.09 | R11: =IF($B11="","",IF(cfg_currency="IDR",IF($B11="","",IFERROR(IF(AND($Q11>INDEX(tbl_thr_idr,MATCH($Q11,INDEX(tbl_thr_idr,0,1),1),1),$Q11<=INDEX(tbl_thr_idr,MATCH($Q11,INDEX(tbl_thr_idr,0,1),1),1)+INDEX(tbl_thr_idr,MATCH($Q11,INDEX(tbl_thr_idr,0,1),1),2)),FLOOR(INDEX(tbl_thr_idr,MATCH($Q11,INDEX(tbl_thr_idr,0,1),1),1)-1,cfg_round_to),$Q11),$Q11)),IF($B11="","",IFERROR(IF(AND($Q11>INDEX(tbl_thr_usd,MATCH($Q11,INDEX(tbl_thr_usd,0,1),1),1),$Q11<=INDEX(tbl_thr_usd,MATCH($Q11,INDEX(tbl_thr_usd,0,1),1),1)+INDEX(tbl_thr_usd,MATCH($Q11,INDEX(tbl_thr_usd,0,1),1),2)),FLOOR(INDEX(tbl_thr_usd,MATCH($Q11,INDEX(tbl_thr_usd,0,1),1),1)-0.01,cfg_round_to),$Q11),$Q11)))) -> 6.09 | S11: =IF($B11="","",cfg_round_to) -> 0.1 | T11: =IF($B11="","",IF(N($AA11)=0,MIN(FLOOR($F11*(1+MIN($N11,cfg_max_raise)),$S11),MAX(CEILING($F11*(1+MAX($O11,cfg_max_cut)),$S11),MROUND($R11,$S11))),IF(SIGN(MIN(FLOOR($F11*(1+MIN($N11,cfg_max_raise)),$S11),MAX(CEILING($F11*(1+MAX($O11,cfg_max_cut)),$S11),MROUND($R11,$S11)))-$F11)>0,IF(AND(N($Y11)>=$F11,N($Y11)>=CEILING($F11*(1+MAX($O11,cfg_max_cut)),$S11),N($Y11)<=FLOOR($F11*(1+MIN($N11,cfg_max_raise)),$S11)),N($Y11),IF(AND(N($Z11)>$F11,N($Z11)>=CEILING($F11*(1+MAX($O11,cfg_max_cut)),$S11),N($Z11)<=FLOOR($F11*(1+MIN($N11,cfg_max_raise)),$S11)),N($Z11),MIN(FLOOR($F11*(1+MIN($N11,cfg_max_raise)),$S11),MAX(CEILING($F11*(1+MAX($O11,cfg_max_cut)),$S11),MROUND($R11,$S11))))),IF(SIGN(MIN(FLOOR($F11*(1+MIN($N11,cfg_max_raise)),$S11),MAX(CEILING($F11*(1+MAX($O11,cfg_max_cut)),$S11),MROUND($R11,$S11)))-$F11)<0,IF(AND(N($Z11)<=$F11,N($Z11)>=CEILING($F11*(1+MAX($O11,cfg_max_cut)),$S11),N($Z11)<=FLOOR($F11*(1+MIN($N11,cfg_max_raise)),$S11)),N($Z11),IF(AND(N($Y11)<$F11,N($Y11)>=CEILING($F11*(1+MAX($O11,cfg_max_cut)),$S11),N($Y11)<=FLOOR($F11*(1+MIN($N11,cfg_max_raise)),$S11)),N($Y11),MIN(FLOOR($F11*(1+MIN($N11,cfg_max_raise)),$S11),MAX(CEILING($F11*(1+MAX($O11,cfg_max_cut)),$S11),MROUND($R11,$S11))))),IF(ABS(N($Y11)-$F11)<=ABS(N($Z11)-$F11),IF(AND(N($Y11)>=CEILING($F11*(1+MAX($O11,cfg_max_cut)),$S11),N($Y11)<=FLOOR($F11*(1+MIN($N11,cfg_max_raise)),$S11)),N($Y11),MIN(FLOOR($F11*(1+MIN($N11,cfg_max_raise)),$S11),MAX(CEILING($F11*(1+MAX($O11,cfg_max_cut)),$S11),MROUND($R11,$S11)))),IF(AND(N($Z11)>=CEILING($F11*(1+MAX($O11,cfg_max_cut)),$S11),N($Z11)<=FLOOR($F11*(1+MIN($N11,cfg_max_raise)),$S11)),N($Z11),MIN(FLOOR($F11*(1+MIN($N11,cfg_max_raise)),$S11),MAX(CEILING($F11*(1+MAX($O11,cfg_max_cut)),$S11),MROUND($R11,$S11))))))))) -> 6.1 | U11: =IF($B11="","",IFERROR($T11/$F11-1,0)) -> 0.051724138 | V11: =IF($B11="","",$G11*($T11/$F11)^$H11) -> 14.262295 | W11: =IF($B11="","",($T11-$E11)*$V11-($F11-$E11)*$G11) -> 1.5491803 | X11: =IF($B11="","",$W11*30) -> 46.47541 | Y11: =IF($B11="","",IF(AND(cfg_round_to<=0.5,IFERROR(VALUE(cfg_ending),0)>0),CEILING($R11-VALUE(cfg_ending),1)+VALUE(cfg_ending),"")) | Z11: =IF($B11="","",IF(AND(cfg_round_to<=0.5,IFERROR(VALUE(cfg_ending),0)>0),FLOOR($R11-VALUE(cfg_ending),1)+VALUE(cfg_ending),"")) | AA11: =IF($B11="","",IF(AND(cfg_round_to<=0.5,IFERROR(VALUE(cfg_ending),0)>0),VALUE(cfg_ending),0)) -> 0
A12: 7 | B12: =IF(OWNER_INPUTS!B12="","",OWNER_INPUTS!B12) | C12: =IF($B12="","",OWNER_INPUTS!C12) | D12: =IF($B12="","",OWNER_INPUTS!D12) | E12: =IF($B12="","",OWNER_INPUTS!E12) | F12: =IF($B12="","",OWNER_INPUTS!F12) | G12: =IF($B12="","",OWNER_INPUTS!G12/30) | H12: =IF($B12="","",IFERROR( IF(ISNUMBER(INDEX(cal_estimate,MATCH($B12,cal_items,0))), INDEX(cal_estimate,MATCH($B12,cal_items,0)), IFERROR(VLOOKUP($C12,tbl_priors,2,FALSE()), VLOOKUP("Other",tbl_priors,2,FALSE()))), IFERROR(VLOOKUP($C12,tbl_priors,2,FALSE()), VLOOKUP("Other",tbl_priors,2,FALSE())))) | I12: =IF($B12="","",IF(IFERROR(ISNUMBER(INDEX(cal_estimate,MATCH($B12,cal_items,0))),FALSE()),"Estimated","Prior")) | J12: =IF($B12="","",IF($I12="Estimated", IFERROR(INDEX(cal_conf,MATCH($B12,cal_items,0)),"LOW"),"LOW")) | K12: =IF($B12="","",IF($H12<-1,$E12*$H12/($H12+1),"test")) | L12: =IF($B12="","",IF($J12="HIGH",cfg_shr_high,IF($J12="MEDIUM",cfg_shr_med,cfg_shr_low))) | M12: =IF($B12="","",IF($K12="test", $F12*(1+IFERROR(VLOOKUP($D12,tbl_roles,4,FALSE()), VLOOKUP("Other",tbl_roles,4,FALSE()))), $F12+$L12*($K12-$F12))) | N12: =IF($B12="","",IFERROR(VLOOKUP($D12,tbl_roles,2,FALSE()),VLOOKUP("Other",tbl_roles,2,FALSE()))) | O12: =IF($B12="","",IFERROR(VLOOKUP($D12,tbl_roles,3,FALSE()),VLOOKUP("Other",tbl_roles,3,FALSE()))) | P12: =IF($B12="","",MIN($F12*(1+$N12),MAX($F12*(1+$O12),$M12))) | Q12: =IF($B12="","",MIN($F12*(1+cfg_max_raise),MAX($F12*(1+cfg_max_cut),$P12))) | R12: =IF($B12="","",IF(cfg_currency="IDR",IF($B12="","",IFERROR(IF(AND($Q12>INDEX(tbl_thr_idr,MATCH($Q12,INDEX(tbl_thr_idr,0,1),1),1),$Q12<=INDEX(tbl_thr_idr,MATCH($Q12,INDEX(tbl_thr_idr,0,1),1),1)+INDEX(tbl_thr_idr,MATCH($Q12,INDEX(tbl_thr_idr,0,1),1),2)),FLOOR(INDEX(tbl_thr_idr,MATCH($Q12,INDEX(tbl_thr_idr,0,1),1),1)-1,cfg_round_to),$Q12),$Q12)),IF($B12="","",IFERROR(IF(AND($Q12>INDEX(tbl_thr_usd,MATCH($Q12,INDEX(tbl_thr_usd,0,1),1),1),$Q12<=INDEX(tbl_thr_usd,MATCH($Q12,INDEX(tbl_thr_usd,0,1),1),1)+INDEX(tbl_thr_usd,MATCH($Q12,INDEX(tbl_thr_usd,0,1),1),2)),FLOOR(INDEX(tbl_thr_usd,MATCH($Q12,INDEX(tbl_thr_usd,0,1),1),1)-0.01,cfg_round_to),$Q12),$Q12)))) | S12: =IF($B12="","",cfg_round_to) | T12: =IF($B12="","",IF(N($AA12)=0,MIN(FLOOR($F12*(1+MIN($N12,cfg_max_raise)),$S12),MAX(CEILING($F12*(1+MAX($O12,cfg_max_cut)),$S12),MROUND($R12,$S12))),IF(SIGN(MIN(FLOOR($F12*(1+MIN($N12,cfg_max_raise)),$S12),MAX(CEILING($F12*(1+MAX($O12,cfg_max_cut)),$S12),MROUND($R12,$S12)))-$F12)>0,IF(AND(N($Y12)>=$F12,N($Y12)>=CEILING($F12*(1+MAX($O12,cfg_max_cut)),$S12),N($Y12)<=FLOOR($F12*(1+MIN($N12,cfg_max_raise)),$S12)),N($Y12),IF(AND(N($Z12)>$F12,N($Z12)>=CEILING($F12*(1+MAX($O12,cfg_max_cut)),$S12),N($Z12)<=FLOOR($F12*(1+MIN($N12,cfg_max_raise)),$S12)),N($Z12),MIN(FLOOR($F12*(1+MIN($N12,cfg_max_raise)),$S12),MAX(CEILING($F12*(1+MAX($O12,cfg_max_cut)),$S12),MROUND($R12,$S12))))),IF(SIGN(MIN(FLOOR($F12*(1+MIN($N12,cfg_max_raise)),$S12),MAX(CEILING($F12*(1+MAX($O12,cfg_max_cut)),$S12),MROUND($R12,$S12)))-$F12)<0,IF(AND(N($Z12)<=$F12,N($Z12)>=CEILING($F12*(1+MAX($O12,cfg_max_cut)),$S12),N($Z12)<=FLOOR($F12*(1+MIN($N12,cfg_max_raise)),$S12)),N($Z12),IF(AND(N($Y12)<$F12,N($Y12)>=CEILING($F12*(1+MAX($O12,cfg_max_cut)),$S12),N($Y12)<=FLOOR($F12*(1+MIN($N12,cfg_max_raise)),$S12)),N($Y12),MIN(FLOOR($F12*(1+MIN($N12,cfg_max_raise)),$S12),MAX(CEILING($F12*(1+MAX($O12,cfg_max_cut)),$S12),MROUND($R12,$S12))))),IF(ABS(N($Y12)-$F12)<=ABS(N($Z12)-$F12),IF(AND(N($Y12)>=CEILING($F12*(1+MAX($O12,cfg_max_cut)),$S12),N($Y12)<=FLOOR($F12*(1+MIN($N12,cfg_max_raise)),$S12)),N($Y12),MIN(FLOOR($F12*(1+MIN($N12,cfg_max_raise)),$S12),MAX(CEILING($F12*(1+MAX($O12,cfg_max_cut)),$S12),MROUND($R12,$S12)))),IF(AND(N($Z12)>=CEILING($F12*(1+MAX($O12,cfg_max_cut)),$S12),N($Z12)<=FLOOR($F12*(1+MIN($N12,cfg_max_raise)),$S12)),N($Z12),MIN(FLOOR($F12*(1+MIN($N12,cfg_max_raise)),$S12),MAX(CEILING($F12*(1+MAX($O12,cfg_max_cut)),$S12),MROUND($R12,$S12))))))))) | U12: =IF($B12="","",IFERROR($T12/$F12-1,0)) | V12: =IF($B12="","",$G12*($T12/$F12)^$H12) | W12: =IF($B12="","",($T12-$E12)*$V12-($F12-$E12)*$G12) | X12: =IF($B12="","",$W12*30) | Y12: =IF($B12="","",IF(AND(cfg_round_to<=0.5,IFERROR(VALUE(cfg_ending),0)>0),CEILING($R12-VALUE(cfg_ending),1)+VALUE(cfg_ending),"")) | Z12: =IF($B12="","",IF(AND(cfg_round_to<=0.5,IFERROR(VALUE(cfg_ending),0)>0),FLOOR($R12-VALUE(cfg_ending),1)+VALUE(cfg_ending),"")) | AA12: =IF($B12="","",IF(AND(cfg_round_to<=0.5,IFERROR(VALUE(cfg_ending),0)>0),VALUE(cfg_ending),0))
A13: 8 | B13: =IF(OWNER_INPUTS!B13="","",OWNER_INPUTS!B13) | C13: =IF($B13="","",OWNER_INPUTS!C13) | D13: =IF($B13="","",OWNER_INPUTS!D13) | E13: =IF($B13="","",OWNER_INPUTS!E13) | F13: =IF($B13="","",OWNER_INPUTS!F13) | G13: =IF($B13="","",OWNER_INPUTS!G13/30) | H13: =IF($B13="","",IFERROR( IF(ISNUMBER(INDEX(cal_estimate,MATCH($B13,cal_items,0))), INDEX(cal_estimate,MATCH($B13,cal_items,0)), IFERROR(VLOOKUP($C13,tbl_priors,2,FALSE()), VLOOKUP("Other",tbl_priors,2,FALSE()))), IFERROR(VLOOKUP($C13,tbl_priors,2,FALSE()), VLOOKUP("Other",tbl_priors,2,FALSE())))) | I13: =IF($B13="","",IF(IFERROR(ISNUMBER(INDEX(cal_estimate,MATCH($B13,cal_items,0))),FALSE()),"Estimated","Prior")) | J13: =IF($B13="","",IF($I13="Estimated", IFERROR(INDEX(cal_conf,MATCH($B13,cal_items,0)),"LOW"),"LOW")) | K13: =IF($B13="","",IF($H13<-1,$E13*$H13/($H13+1),"test")) | L13: =IF($B13="","",IF($J13="HIGH",cfg_shr_high,IF($J13="MEDIUM",cfg_shr_med,cfg_shr_low))) | M13: =IF($B13="","",IF($K13="test", $F13*(1+IFERROR(VLOOKUP($D13,tbl_roles,4,FALSE()), VLOOKUP("Other",tbl_roles,4,FALSE()))), $F13+$L13*($K13-$F13))) | N13: =IF($B13="","",IFERROR(VLOOKUP($D13,tbl_roles,2,FALSE()),VLOOKUP("Other",tbl_roles,2,FALSE()))) | O13: =IF($B13="","",IFERROR(VLOOKUP($D13,tbl_roles,3,FALSE()),VLOOKUP("Other",tbl_roles,3,FALSE()))) | P13: =IF($B13="","",MIN($F13*(1+$N13),MAX($F13*(1+$O13),$M13))) | Q13: =IF($B13="","",MIN($F13*(1+cfg_max_raise),MAX($F13*(1+cfg_max_cut),$P13))) | R13: =IF($B13="","",IF(cfg_currency="IDR",IF($B13="","",IFERROR(IF(AND($Q13>INDEX(tbl_thr_idr,MATCH($Q13,INDEX(tbl_thr_idr,0,1),1),1),$Q13<=INDEX(tbl_thr_idr,MATCH($Q13,INDEX(tbl_thr_idr,0,1),1),1)+INDEX(tbl_thr_idr,MATCH($Q13,INDEX(tbl_thr_idr,0,1),1),2)),FLOOR(INDEX(tbl_thr_idr,MATCH($Q13,INDEX(tbl_thr_idr,0,1),1),1)-1,cfg_round_to),$Q13),$Q13)),IF($B13="","",IFERROR(IF(AND($Q13>INDEX(tbl_thr_usd,MATCH($Q13,INDEX(tbl_thr_usd,0,1),1),1),$Q13<=INDEX(tbl_thr_usd,MATCH($Q13,INDEX(tbl_thr_usd,0,1),1),1)+INDEX(tbl_thr_usd,MATCH($Q13,INDEX(tbl_thr_usd,0,1),1),2)),FLOOR(INDEX(tbl_thr_usd,MATCH($Q13,INDEX(tbl_thr_usd,0,1),1),1)-0.01,cfg_round_to),$Q13),$Q13)))) | S13: =IF($B13="","",cfg_round_to) | T13: =IF($B13="","",IF(N($AA13)=0,MIN(FLOOR($F13*(1+MIN($N13,cfg_max_raise)),$S13),MAX(CEILING($F13*(1+MAX($O13,cfg_max_cut)),$S13),MROUND($R13,$S13))),IF(SIGN(MIN(FLOOR($F13*(1+MIN($N13,cfg_max_raise)),$S13),MAX(CEILING($F13*(1+MAX($O13,cfg_max_cut)),$S13),MROUND($R13,$S13)))-$F13)>0,IF(AND(N($Y13)>=$F13,N($Y13)>=CEILING($F13*(1+MAX($O13,cfg_max_cut)),$S13),N($Y13)<=FLOOR($F13*(1+MIN($N13,cfg_max_raise)),$S13)),N($Y13),IF(AND(N($Z13)>$F13,N($Z13)>=CEILING($F13*(1+MAX($O13,cfg_max_cut)),$S13),N($Z13)<=FLOOR($F13*(1+MIN($N13,cfg_max_raise)),$S13)),N($Z13),MIN(FLOOR($F13*(1+MIN($N13,cfg_max_raise)),$S13),MAX(CEILING($F13*(1+MAX($O13,cfg_max_cut)),$S13),MROUND($R13,$S13))))),IF(SIGN(MIN(FLOOR($F13*(1+MIN($N13,cfg_max_raise)),$S13),MAX(CEILING($F13*(1+MAX($O13,cfg_max_cut)),$S13),MROUND($R13,$S13)))-$F13)<0,IF(AND(N($Z13)<=$F13,N($Z13)>=CEILING($F13*(1+MAX($O13,cfg_max_cut)),$S13),N($Z13)<=FLOOR($F13*(1+MIN($N13,cfg_max_raise)),$S13)),N($Z13),IF(AND(N($Y13)<$F13,N($Y13)>=CEILING($F13*(1+MAX($O13,cfg_max_cut)),$S13),N($Y13)<=FLOOR($F13*(1+MIN($N13,cfg_max_raise)),$S13)),N($Y13),MIN(FLOOR($F13*(1+MIN($N13,cfg_max_raise)),$S13),MAX(CEILING($F13*(1+MAX($O13,cfg_max_cut)),$S13),MROUND($R13,$S13))))),IF(ABS(N($Y13)-$F13)<=ABS(N($Z13)-$F13),IF(AND(N($Y13)>=CEILING($F13*(1+MAX($O13,cfg_max_cut)),$S13),N($Y13)<=FLOOR($F13*(1+MIN($N13,cfg_max_raise)),$S13)),N($Y13),MIN(FLOOR($F13*(1+MIN($N13,cfg_max_raise)),$S13),MAX(CEILING($F13*(1+MAX($O13,cfg_max_cut)),$S13),MROUND($R13,$S13)))),IF(AND(N($Z13)>=CEILING($F13*(1+MAX($O13,cfg_max_cut)),$S13),N($Z13)<=FLOOR($F13*(1+MIN($N13,cfg_max_raise)),$S13)),N($Z13),MIN(FLOOR($F13*(1+MIN($N13,cfg_max_raise)),$S13),MAX(CEILING($F13*(1+MAX($O13,cfg_max_cut)),$S13),MROUND($R13,$S13))))))))) | U13: =IF($B13="","",IFERROR($T13/$F13-1,0)) | V13: =IF($B13="","",$G13*($T13/$F13)^$H13) | W13: =IF($B13="","",($T13-$E13)*$V13-($F13-$E13)*$G13) | X13: =IF($B13="","",$W13*30) | Y13: =IF($B13="","",IF(AND(cfg_round_to<=0.5,IFERROR(VALUE(cfg_ending),0)>0),CEILING($R13-VALUE(cfg_ending),1)+VALUE(cfg_ending),"")) | Z13: =IF($B13="","",IF(AND(cfg_round_to<=0.5,IFERROR(VALUE(cfg_ending),0)>0),FLOOR($R13-VALUE(cfg_ending),1)+VALUE(cfg_ending),"")) | AA13: =IF($B13="","",IF(AND(cfg_round_to<=0.5,IFERROR(VALUE(cfg_ending),0)>0),VALUE(cfg_ending),0))
A14: 9 | B14: =IF(OWNER_INPUTS!B14="","",OWNER_INPUTS!B14) | C14: =IF($B14="","",OWNER_INPUTS!C14) | D14: =IF($B14="","",OWNER_INPUTS!D14) | E14: =IF($B14="","",OWNER_INPUTS!E14) | F14: =IF($B14="","",OWNER_INPUTS!F14) | G14: =IF($B14="","",OWNER_INPUTS!G14/30) | H14: =IF($B14="","",IFERROR( IF(ISNUMBER(INDEX(cal_estimate,MATCH($B14,cal_items,0))), INDEX(cal_estimate,MATCH($B14,cal_items,0)), IFERROR(VLOOKUP($C14,tbl_priors,2,FALSE()), VLOOKUP("Other",tbl_priors,2,FALSE()))), IFERROR(VLOOKUP($C14,tbl_priors,2,FALSE()), VLOOKUP("Other",tbl_priors,2,FALSE())))) | I14: =IF($B14="","",IF(IFERROR(ISNUMBER(INDEX(cal_estimate,MATCH($B14,cal_items,0))),FALSE()),"Estimated","Prior")) | J14: =IF($B14="","",IF($I14="Estimated", IFERROR(INDEX(cal_conf,MATCH($B14,cal_items,0)),"LOW"),"LOW")) | K14: =IF($B14="","",IF($H14<-1,$E14*$H14/($H14+1),"test")) | L14: =IF($B14="","",IF($J14="HIGH",cfg_shr_high,IF($J14="MEDIUM",cfg_shr_med,cfg_shr_low))) | M14: =IF($B14="","",IF($K14="test", $F14*(1+IFERROR(VLOOKUP($D14,tbl_roles,4,FALSE()), VLOOKUP("Other",tbl_roles,4,FALSE()))), $F14+$L14*($K14-$F14))) | N14: =IF($B14="","",IFERROR(VLOOKUP($D14,tbl_roles,2,FALSE()),VLOOKUP("Other",tbl_roles,2,FALSE()))) | O14: =IF($B14="","",IFERROR(VLOOKUP($D14,tbl_roles,3,FALSE()),VLOOKUP("Other",tbl_roles,3,FALSE()))) | P14: =IF($B14="","",MIN($F14*(1+$N14),MAX($F14*(1+$O14),$M14))) | Q14: =IF($B14="","",MIN($F14*(1+cfg_max_raise),MAX($F14*(1+cfg_max_cut),$P14))) | R14: =IF($B14="","",IF(cfg_currency="IDR",IF($B14="","",IFERROR(IF(AND($Q14>INDEX(tbl_thr_idr,MATCH($Q14,INDEX(tbl_thr_idr,0,1),1),1),$Q14<=INDEX(tbl_thr_idr,MATCH($Q14,INDEX(tbl_thr_idr,0,1),1),1)+INDEX(tbl_thr_idr,MATCH($Q14,INDEX(tbl_thr_idr,0,1),1),2)),FLOOR(INDEX(tbl_thr_idr,MATCH($Q14,INDEX(tbl_thr_idr,0,1),1),1)-1,cfg_round_to),$Q14),$Q14)),IF($B14="","",IFERROR(IF(AND($Q14>INDEX(tbl_thr_usd,MATCH($Q14,INDEX(tbl_thr_usd,0,1),1),1),$Q14<=INDEX(tbl_thr_usd,MATCH($Q14,INDEX(tbl_thr_usd,0,1),1),1)+INDEX(tbl_thr_usd,MATCH($Q14,INDEX(tbl_thr_usd,0,1),1),2)),FLOOR(INDEX(tbl_thr_usd,MATCH($Q14,INDEX(tbl_thr_usd,0,1),1),1)-0.01,cfg_round_to),$Q14),$Q14)))) | S14: =IF($B14="","",cfg_round_to) | T14: =IF($B14="","",IF(N($AA14)=0,MIN(FLOOR($F14*(1+MIN($N14,cfg_max_raise)),$S14),MAX(CEILING($F14*(1+MAX($O14,cfg_max_cut)),$S14),MROUND($R14,$S14))),IF(SIGN(MIN(FLOOR($F14*(1+MIN($N14,cfg_max_raise)),$S14),MAX(CEILING($F14*(1+MAX($O14,cfg_max_cut)),$S14),MROUND($R14,$S14)))-$F14)>0,IF(AND(N($Y14)>=$F14,N($Y14)>=CEILING($F14*(1+MAX($O14,cfg_max_cut)),$S14),N($Y14)<=FLOOR($F14*(1+MIN($N14,cfg_max_raise)),$S14)),N($Y14),IF(AND(N($Z14)>$F14,N($Z14)>=CEILING($F14*(1+MAX($O14,cfg_max_cut)),$S14),N($Z14)<=FLOOR($F14*(1+MIN($N14,cfg_max_raise)),$S14)),N($Z14),MIN(FLOOR($F14*(1+MIN($N14,cfg_max_raise)),$S14),MAX(CEILING($F14*(1+MAX($O14,cfg_max_cut)),$S14),MROUND($R14,$S14))))),IF(SIGN(MIN(FLOOR($F14*(1+MIN($N14,cfg_max_raise)),$S14),MAX(CEILING($F14*(1+MAX($O14,cfg_max_cut)),$S14),MROUND($R14,$S14)))-$F14)<0,IF(AND(N($Z14)<=$F14,N($Z14)>=CEILING($F14*(1+MAX($O14,cfg_max_cut)),$S14),N($Z14)<=FLOOR($F14*(1+MIN($N14,cfg_max_raise)),$S14)),N($Z14),IF(AND(N($Y14)<$F14,N($Y14)>=CEILING($F14*(1+MAX($O14,cfg_max_cut)),$S14),N($Y14)<=FLOOR($F14*(1+MIN($N14,cfg_max_raise)),$S14)),N($Y14),MIN(FLOOR($F14*(1+MIN($N14,cfg_max_raise)),$S14),MAX(CEILING($F14*(1+MAX($O14,cfg_max_cut)),$S14),MROUND($R14,$S14))))),IF(ABS(N($Y14)-$F14)<=ABS(N($Z14)-$F14),IF(AND(N($Y14)>=CEILING($F14*(1+MAX($O14,cfg_max_cut)),$S14),N($Y14)<=FLOOR($F14*(1+MIN($N14,cfg_max_raise)),$S14)),N($Y14),MIN(FLOOR($F14*(1+MIN($N14,cfg_max_raise)),$S14),MAX(CEILING($F14*(1+MAX($O14,cfg_max_cut)),$S14),MROUND($R14,$S14)))),IF(AND(N($Z14)>=CEILING($F14*(1+MAX($O14,cfg_max_cut)),$S14),N($Z14)<=FLOOR($F14*(1+MIN($N14,cfg_max_raise)),$S14)),N($Z14),MIN(FLOOR($F14*(1+MIN($N14,cfg_max_raise)),$S14),MAX(CEILING($F14*(1+MAX($O14,cfg_max_cut)),$S14),MROUND($R14,$S14))))))))) | U14: =IF($B14="","",IFERROR($T14/$F14-1,0)) | V14: =IF($B14="","",$G14*($T14/$F14)^$H14) | W14: =IF($B14="","",($T14-$E14)*$V14-($F14-$E14)*$G14) | X14: =IF($B14="","",$W14*30) | Y14: =IF($B14="","",IF(AND(cfg_round_to<=0.5,IFERROR(VALUE(cfg_ending),0)>0),CEILING($R14-VALUE(cfg_ending),1)+VALUE(cfg_ending),"")) | Z14: =IF($B14="","",IF(AND(cfg_round_to<=0.5,IFERROR(VALUE(cfg_ending),0)>0),FLOOR($R14-VALUE(cfg_ending),1)+VALUE(cfg_ending),"")) | AA14: =IF($B14="","",IF(AND(cfg_round_to<=0.5,IFERROR(VALUE(cfg_ending),0)>0),VALUE(cfg_ending),0))
A15: 10 | B15: =IF(OWNER_INPUTS!B15="","",OWNER_INPUTS!B15) | C15: =IF($B15="","",OWNER_INPUTS!C15) | D15: =IF($B15="","",OWNER_INPUTS!D15) | E15: =IF($B15="","",OWNER_INPUTS!E15) | F15: =IF($B15="","",OWNER_INPUTS!F15) | G15: =IF($B15="","",OWNER_INPUTS!G15/30) | H15: =IF($B15="","",IFERROR( IF(ISNUMBER(INDEX(cal_estimate,MATCH($B15,cal_items,0))), INDEX(cal_estimate,MATCH($B15,cal_items,0)), IFERROR(VLOOKUP($C15,tbl_priors,2,FALSE()), VLOOKUP("Other",tbl_priors,2,FALSE()))), IFERROR(VLOOKUP($C15,tbl_priors,2,FALSE()), VLOOKUP("Other",tbl_priors,2,FALSE())))) | I15: =IF($B15="","",IF(IFERROR(ISNUMBER(INDEX(cal_estimate,MATCH($B15,cal_items,0))),FALSE()),"Estimated","Prior")) | J15: =IF($B15="","",IF($I15="Estimated", IFERROR(INDEX(cal_conf,MATCH($B15,cal_items,0)),"LOW"),"LOW")) | K15: =IF($B15="","",IF($H15<-1,$E15*$H15/($H15+1),"test")) | L15: =IF($B15="","",IF($J15="HIGH",cfg_shr_high,IF($J15="MEDIUM",cfg_shr_med,cfg_shr_low))) | M15: =IF($B15="","",IF($K15="test", $F15*(1+IFERROR(VLOOKUP($D15,tbl_roles,4,FALSE()), VLOOKUP("Other",tbl_roles,4,FALSE()))), $F15+$L15*($K15-$F15))) | N15: =IF($B15="","",IFERROR(VLOOKUP($D15,tbl_roles,2,FALSE()),VLOOKUP("Other",tbl_roles,2,FALSE()))) | O15: =IF($B15="","",IFERROR(VLOOKUP($D15,tbl_roles,3,FALSE()),VLOOKUP("Other",tbl_roles,3,FALSE()))) | P15: =IF($B15="","",MIN($F15*(1+$N15),MAX($F15*(1+$O15),$M15))) | Q15: =IF($B15="","",MIN($F15*(1+cfg_max_raise),MAX($F15*(1+cfg_max_cut),$P15))) | R15: =IF($B15="","",IF(cfg_currency="IDR",IF($B15="","",IFERROR(IF(AND($Q15>INDEX(tbl_thr_idr,MATCH($Q15,INDEX(tbl_thr_idr,0,1),1),1),$Q15<=INDEX(tbl_thr_idr,MATCH($Q15,INDEX(tbl_thr_idr,0,1),1),1)+INDEX(tbl_thr_idr,MATCH($Q15,INDEX(tbl_thr_idr,0,1),1),2)),FLOOR(INDEX(tbl_thr_idr,MATCH($Q15,INDEX(tbl_thr_idr,0,1),1),1)-1,cfg_round_to),$Q15),$Q15)),IF($B15="","",IFERROR(IF(AND($Q15>INDEX(tbl_thr_usd,MATCH($Q15,INDEX(tbl_thr_usd,0,1),1),1),$Q15<=INDEX(tbl_thr_usd,MATCH($Q15,INDEX(tbl_thr_usd,0,1),1),1)+INDEX(tbl_thr_usd,MATCH($Q15,INDEX(tbl_thr_usd,0,1),1),2)),FLOOR(INDEX(tbl_thr_usd,MATCH($Q15,INDEX(tbl_thr_usd,0,1),1),1)-0.01,cfg_round_to),$Q15),$Q15)))) | S15: =IF($B15="","",cfg_round_to) | T15: =IF($B15="","",IF(N($AA15)=0,MIN(FLOOR($F15*(1+MIN($N15,cfg_max_raise)),$S15),MAX(CEILING($F15*(1+MAX($O15,cfg_max_cut)),$S15),MROUND($R15,$S15))),IF(SIGN(MIN(FLOOR($F15*(1+MIN($N15,cfg_max_raise)),$S15),MAX(CEILING($F15*(1+MAX($O15,cfg_max_cut)),$S15),MROUND($R15,$S15)))-$F15)>0,IF(AND(N($Y15)>=$F15,N($Y15)>=CEILING($F15*(1+MAX($O15,cfg_max_cut)),$S15),N($Y15)<=FLOOR($F15*(1+MIN($N15,cfg_max_raise)),$S15)),N($Y15),IF(AND(N($Z15)>$F15,N($Z15)>=CEILING($F15*(1+MAX($O15,cfg_max_cut)),$S15),N($Z15)<=FLOOR($F15*(1+MIN($N15,cfg_max_raise)),$S15)),N($Z15),MIN(FLOOR($F15*(1+MIN($N15,cfg_max_raise)),$S15),MAX(CEILING($F15*(1+MAX($O15,cfg_max_cut)),$S15),MROUND($R15,$S15))))),IF(SIGN(MIN(FLOOR($F15*(1+MIN($N15,cfg_max_raise)),$S15),MAX(CEILING($F15*(1+MAX($O15,cfg_max_cut)),$S15),MROUND($R15,$S15)))-$F15)<0,IF(AND(N($Z15)<=$F15,N($Z15)>=CEILING($F15*(1+MAX($O15,cfg_max_cut)),$S15),N($Z15)<=FLOOR($F15*(1+MIN($N15,cfg_max_raise)),$S15)),N($Z15),IF(AND(N($Y15)<$F15,N($Y15)>=CEILING($F15*(1+MAX($O15,cfg_max_cut)),$S15),N($Y15)<=FLOOR($F15*(1+MIN($N15,cfg_max_raise)),$S15)),N($Y15),MIN(FLOOR($F15*(1+MIN($N15,cfg_max_raise)),$S15),MAX(CEILING($F15*(1+MAX($O15,cfg_max_cut)),$S15),MROUND($R15,$S15))))),IF(ABS(N($Y15)-$F15)<=ABS(N($Z15)-$F15),IF(AND(N($Y15)>=CEILING($F15*(1+MAX($O15,cfg_max_cut)),$S15),N($Y15)<=FLOOR($F15*(1+MIN($N15,cfg_max_raise)),$S15)),N($Y15),MIN(FLOOR($F15*(1+MIN($N15,cfg_max_raise)),$S15),MAX(CEILING($F15*(1+MAX($O15,cfg_max_cut)),$S15),MROUND($R15,$S15)))),IF(AND(N($Z15)>=CEILING($F15*(1+MAX($O15,cfg_max_cut)),$S15),N($Z15)<=FLOOR($F15*(1+MIN($N15,cfg_max_raise)),$S15)),N($Z15),MIN(FLOOR($F15*(1+MIN($N15,cfg_max_raise)),$S15),MAX(CEILING($F15*(1+MAX($O15,cfg_max_cut)),$S15),MROUND($R15,$S15))))))))) | U15: =IF($B15="","",IFERROR($T15/$F15-1,0)) | V15: =IF($B15="","",$G15*($T15/$F15)^$H15) | W15: =IF($B15="","",($T15-$E15)*$V15-($F15-$E15)*$G15) | X15: =IF($B15="","",$W15*30) | Y15: =IF($B15="","",IF(AND(cfg_round_to<=0.5,IFERROR(VALUE(cfg_ending),0)>0),CEILING($R15-VALUE(cfg_ending),1)+VALUE(cfg_ending),"")) | Z15: =IF($B15="","",IF(AND(cfg_round_to<=0.5,IFERROR(VALUE(cfg_ending),0)>0),FLOOR($R15-VALUE(cfg_ending),1)+VALUE(cfg_ending),"")) | AA15: =IF($B15="","",IF(AND(cfg_round_to<=0.5,IFERROR(VALUE(cfg_ending),0)>0),VALUE(cfg_ending),0))
A16: 11 | B16: =IF(OWNER_INPUTS!B16="","",OWNER_INPUTS!B16) | C16: =IF($B16="","",OWNER_INPUTS!C16) | D16: =IF($B16="","",OWNER_INPUTS!D16) | E16: =IF($B16="","",OWNER_INPUTS!E16) | F16: =IF($B16="","",OWNER_INPUTS!F16) | G16: =IF($B16="","",OWNER_INPUTS!G16/30) | H16: =IF($B16="","",IFERROR( IF(ISNUMBER(INDEX(cal_estimate,MATCH($B16,cal_items,0))), INDEX(cal_estimate,MATCH($B16,cal_items,0)), IFERROR(VLOOKUP($C16,tbl_priors,2,FALSE()), VLOOKUP("Other",tbl_priors,2,FALSE()))), IFERROR(VLOOKUP($C16,tbl_priors,2,FALSE()), VLOOKUP("Other",tbl_priors,2,FALSE())))) | I16: =IF($B16="","",IF(IFERROR(ISNUMBER(INDEX(cal_estimate,MATCH($B16,cal_items,0))),FALSE()),"Estimated","Prior")) | J16: =IF($B16="","",IF($I16="Estimated", IFERROR(INDEX(cal_conf,MATCH($B16,cal_items,0)),"LOW"),"LOW")) | K16: =IF($B16="","",IF($H16<-1,$E16*$H16/($H16+1),"test")) | L16: =IF($B16="","",IF($J16="HIGH",cfg_shr_high,IF($J16="MEDIUM",cfg_shr_med,cfg_shr_low))) | M16: =IF($B16="","",IF($K16="test", $F16*(1+IFERROR(VLOOKUP($D16,tbl_roles,4,FALSE()), VLOOKUP("Other",tbl_roles,4,FALSE()))), $F16+$L16*($K16-$F16))) | N16: =IF($B16="","",IFERROR(VLOOKUP($D16,tbl_roles,2,FALSE()),VLOOKUP("Other",tbl_roles,2,FALSE()))) | O16: =IF($B16="","",IFERROR(VLOOKUP($D16,tbl_roles,3,FALSE()),VLOOKUP("Other",tbl_roles,3,FALSE()))) | P16: =IF($B16="","",MIN($F16*(1+$N16),MAX($F16*(1+$O16),$M16))) | Q16: =IF($B16="","",MIN($F16*(1+cfg_max_raise),MAX($F16*(1+cfg_max_cut),$P16))) | R16: =IF($B16="","",IF(cfg_currency="IDR",IF($B16="","",IFERROR(IF(AND($Q16>INDEX(tbl_thr_idr,MATCH($Q16,INDEX(tbl_thr_idr,0,1),1),1),$Q16<=INDEX(tbl_thr_idr,MATCH($Q16,INDEX(tbl_thr_idr,0,1),1),1)+INDEX(tbl_thr_idr,MATCH($Q16,INDEX(tbl_thr_idr,0,1),1),2)),FLOOR(INDEX(tbl_thr_idr,MATCH($Q16,INDEX(tbl_thr_idr,0,1),1),1)-1,cfg_round_to),$Q16),$Q16)),IF($B16="","",IFERROR(IF(AND($Q16>INDEX(tbl_thr_usd,MATCH($Q16,INDEX(tbl_thr_usd,0,1),1),1),$Q16<=INDEX(tbl_thr_usd,MATCH($Q16,INDEX(tbl_thr_usd,0,1),1),1)+INDEX(tbl_thr_usd,MATCH($Q16,INDEX(tbl_thr_usd,0,1),1),2)),FLOOR(INDEX(tbl_thr_usd,MATCH($Q16,INDEX(tbl_thr_usd,0,1),1),1)-0.01,cfg_round_to),$Q16),$Q16)))) | S16: =IF($B16="","",cfg_round_to) | T16: =IF($B16="","",IF(N($AA16)=0,MIN(FLOOR($F16*(1+MIN($N16,cfg_max_raise)),$S16),MAX(CEILING($F16*(1+MAX($O16,cfg_max_cut)),$S16),MROUND($R16,$S16))),IF(SIGN(MIN(FLOOR($F16*(1+MIN($N16,cfg_max_raise)),$S16),MAX(CEILING($F16*(1+MAX($O16,cfg_max_cut)),$S16),MROUND($R16,$S16)))-$F16)>0,IF(AND(N($Y16)>=$F16,N($Y16)>=CEILING($F16*(1+MAX($O16,cfg_max_cut)),$S16),N($Y16)<=FLOOR($F16*(1+MIN($N16,cfg_max_raise)),$S16)),N($Y16),IF(AND(N($Z16)>$F16,N($Z16)>=CEILING($F16*(1+MAX($O16,cfg_max_cut)),$S16),N($Z16)<=FLOOR($F16*(1+MIN($N16,cfg_max_raise)),$S16)),N($Z16),MIN(FLOOR($F16*(1+MIN($N16,cfg_max_raise)),$S16),MAX(CEILING($F16*(1+MAX($O16,cfg_max_cut)),$S16),MROUND($R16,$S16))))),IF(SIGN(MIN(FLOOR($F16*(1+MIN($N16,cfg_max_raise)),$S16),MAX(CEILING($F16*(1+MAX($O16,cfg_max_cut)),$S16),MROUND($R16,$S16)))-$F16)<0,IF(AND(N($Z16)<=$F16,N($Z16)>=CEILING($F16*(1+MAX($O16,cfg_max_cut)),$S16),N($Z16)<=FLOOR($F16*(1+MIN($N16,cfg_max_raise)),$S16)),N($Z16),IF(AND(N($Y16)<$F16,N($Y16)>=CEILING($F16*(1+MAX($O16,cfg_max_cut)),$S16),N($Y16)<=FLOOR($F16*(1+MIN($N16,cfg_max_raise)),$S16)),N($Y16),MIN(FLOOR($F16*(1+MIN($N16,cfg_max_raise)),$S16),MAX(CEILING($F16*(1+MAX($O16,cfg_max_cut)),$S16),MROUND($R16,$S16))))),IF(ABS(N($Y16)-$F16)<=ABS(N($Z16)-$F16),IF(AND(N($Y16)>=CEILING($F16*(1+MAX($O16,cfg_max_cut)),$S16),N($Y16)<=FLOOR($F16*(1+MIN($N16,cfg_max_raise)),$S16)),N($Y16),MIN(FLOOR($F16*(1+MIN($N16,cfg_max_raise)),$S16),MAX(CEILING($F16*(1+MAX($O16,cfg_max_cut)),$S16),MROUND($R16,$S16)))),IF(AND(N($Z16)>=CEILING($F16*(1+MAX($O16,cfg_max_cut)),$S16),N($Z16)<=FLOOR($F16*(1+MIN($N16,cfg_max_raise)),$S16)),N($Z16),MIN(FLOOR($F16*(1+MIN($N16,cfg_max_raise)),$S16),MAX(CEILING($F16*(1+MAX($O16,cfg_max_cut)),$S16),MROUND($R16,$S16))))))))) | U16: =IF($B16="","",IFERROR($T16/$F16-1,0)) | V16: =IF($B16="","",$G16*($T16/$F16)^$H16) | W16: =IF($B16="","",($T16-$E16)*$V16-($F16-$E16)*$G16) | X16: =IF($B16="","",$W16*30) | Y16: =IF($B16="","",IF(AND(cfg_round_to<=0.5,IFERROR(VALUE(cfg_ending),0)>0),CEILING($R16-VALUE(cfg_ending),1)+VALUE(cfg_ending),"")) | Z16: =IF($B16="","",IF(AND(cfg_round_to<=0.5,IFERROR(VALUE(cfg_ending),0)>0),FLOOR($R16-VALUE(cfg_ending),1)+VALUE(cfg_ending),"")) | AA16: =IF($B16="","",IF(AND(cfg_round_to<=0.5,IFERROR(VALUE(cfg_ending),0)>0),VALUE(cfg_ending),0))
A17: 12 | B17: =IF(OWNER_INPUTS!B17="","",OWNER_INPUTS!B17) | C17: =IF($B17="","",OWNER_INPUTS!C17) | D17: =IF($B17="","",OWNER_INPUTS!D17) | E17: =IF($B17="","",OWNER_INPUTS!E17) | F17: =IF($B17="","",OWNER_INPUTS!F17) | G17: =IF($B17="","",OWNER_INPUTS!G17/30) | H17: =IF($B17="","",IFERROR( IF(ISNUMBER(INDEX(cal_estimate,MATCH($B17,cal_items,0))), INDEX(cal_estimate,MATCH($B17,cal_items,0)), IFERROR(VLOOKUP($C17,tbl_priors,2,FALSE()), VLOOKUP("Other",tbl_priors,2,FALSE()))), IFERROR(VLOOKUP($C17,tbl_priors,2,FALSE()), VLOOKUP("Other",tbl_priors,2,FALSE())))) | I17: =IF($B17="","",IF(IFERROR(ISNUMBER(INDEX(cal_estimate,MATCH($B17,cal_items,0))),FALSE()),"Estimated","Prior")) | J17: =IF($B17="","",IF($I17="Estimated", IFERROR(INDEX(cal_conf,MATCH($B17,cal_items,0)),"LOW"),"LOW")) | K17: =IF($B17="","",IF($H17<-1,$E17*$H17/($H17+1),"test")) | L17: =IF($B17="","",IF($J17="HIGH",cfg_shr_high,IF($J17="MEDIUM",cfg_shr_med,cfg_shr_low))) | M17: =IF($B17="","",IF($K17="test", $F17*(1+IFERROR(VLOOKUP($D17,tbl_roles,4,FALSE()), VLOOKUP("Other",tbl_roles,4,FALSE()))), $F17+$L17*($K17-$F17))) | N17: =IF($B17="","",IFERROR(VLOOKUP($D17,tbl_roles,2,FALSE()),VLOOKUP("Other",tbl_roles,2,FALSE()))) | O17: =IF($B17="","",IFERROR(VLOOKUP($D17,tbl_roles,3,FALSE()),VLOOKUP("Other",tbl_roles,3,FALSE()))) | P17: =IF($B17="","",MIN($F17*(1+$N17),MAX($F17*(1+$O17),$M17))) | Q17: =IF($B17="","",MIN($F17*(1+cfg_max_raise),MAX($F17*(1+cfg_max_cut),$P17))) | R17: =IF($B17="","",IF(cfg_currency="IDR",IF($B17="","",IFERROR(IF(AND($Q17>INDEX(tbl_thr_idr,MATCH($Q17,INDEX(tbl_thr_idr,0,1),1),1),$Q17<=INDEX(tbl_thr_idr,MATCH($Q17,INDEX(tbl_thr_idr,0,1),1),1)+INDEX(tbl_thr_idr,MATCH($Q17,INDEX(tbl_thr_idr,0,1),1),2)),FLOOR(INDEX(tbl_thr_idr,MATCH($Q17,INDEX(tbl_thr_idr,0,1),1),1)-1,cfg_round_to),$Q17),$Q17)),IF($B17="","",IFERROR(IF(AND($Q17>INDEX(tbl_thr_usd,MATCH($Q17,INDEX(tbl_thr_usd,0,1),1),1),$Q17<=INDEX(tbl_thr_usd,MATCH($Q17,INDEX(tbl_thr_usd,0,1),1),1)+INDEX(tbl_thr_usd,MATCH($Q17,INDEX(tbl_thr_usd,0,1),1),2)),FLOOR(INDEX(tbl_thr_usd,MATCH($Q17,INDEX(tbl_thr_usd,0,1),1),1)-0.01,cfg_round_to),$Q17),$Q17)))) | S17: =IF($B17="","",cfg_round_to) | T17: =IF($B17="","",IF(N($AA17)=0,MIN(FLOOR($F17*(1+MIN($N17,cfg_max_raise)),$S17),MAX(CEILING($F17*(1+MAX($O17,cfg_max_cut)),$S17),MROUND($R17,$S17))),IF(SIGN(MIN(FLOOR($F17*(1+MIN($N17,cfg_max_raise)),$S17),MAX(CEILING($F17*(1+MAX($O17,cfg_max_cut)),$S17),MROUND($R17,$S17)))-$F17)>0,IF(AND(N($Y17)>=$F17,N($Y17)>=CEILING($F17*(1+MAX($O17,cfg_max_cut)),$S17),N($Y17)<=FLOOR($F17*(1+MIN($N17,cfg_max_raise)),$S17)),N($Y17),IF(AND(N($Z17)>$F17,N($Z17)>=CEILING($F17*(1+MAX($O17,cfg_max_cut)),$S17),N($Z17)<=FLOOR($F17*(1+MIN($N17,cfg_max_raise)),$S17)),N($Z17),MIN(FLOOR($F17*(1+MIN($N17,cfg_max_raise)),$S17),MAX(CEILING($F17*(1+MAX($O17,cfg_max_cut)),$S17),MROUND($R17,$S17))))),IF(SIGN(MIN(FLOOR($F17*(1+MIN($N17,cfg_max_raise)),$S17),MAX(CEILING($F17*(1+MAX($O17,cfg_max_cut)),$S17),MROUND($R17,$S17)))-$F17)<0,IF(AND(N($Z17)<=$F17,N($Z17)>=CEILING($F17*(1+MAX($O17,cfg_max_cut)),$S17),N($Z17)<=FLOOR($F17*(1+MIN($N17,cfg_max_raise)),$S17)),N($Z17),IF(AND(N($Y17)<$F17,N($Y17)>=CEILING($F17*(1+MAX($O17,cfg_max_cut)),$S17),N($Y17)<=FLOOR($F17*(1+MIN($N17,cfg_max_raise)),$S17)),N($Y17),MIN(FLOOR($F17*(1+MIN($N17,cfg_max_raise)),$S17),MAX(CEILING($F17*(1+MAX($O17,cfg_max_cut)),$S17),MROUND($R17,$S17))))),IF(ABS(N($Y17)-$F17)<=ABS(N($Z17)-$F17),IF(AND(N($Y17)>=CEILING($F17*(1+MAX($O17,cfg_max_cut)),$S17),N($Y17)<=FLOOR($F17*(1+MIN($N17,cfg_max_raise)),$S17)),N($Y17),MIN(FLOOR($F17*(1+MIN($N17,cfg_max_raise)),$S17),MAX(CEILING($F17*(1+MAX($O17,cfg_max_cut)),$S17),MROUND($R17,$S17)))),IF(AND(N($Z17)>=CEILING($F17*(1+MAX($O17,cfg_max_cut)),$S17),N($Z17)<=FLOOR($F17*(1+MIN($N17,cfg_max_raise)),$S17)),N($Z17),MIN(FLOOR($F17*(1+MIN($N17,cfg_max_raise)),$S17),MAX(CEILING($F17*(1+MAX($O17,cfg_max_cut)),$S17),MROUND($R17,$S17))))))))) | U17: =IF($B17="","",IFERROR($T17/$F17-1,0)) | V17: =IF($B17="","",$G17*($T17/$F17)^$H17) | W17: =IF($B17="","",($T17-$E17)*$V17-($F17-$E17)*$G17) | X17: =IF($B17="","",$W17*30) | Y17: =IF($B17="","",IF(AND(cfg_round_to<=0.5,IFERROR(VALUE(cfg_ending),0)>0),CEILING($R17-VALUE(cfg_ending),1)+VALUE(cfg_ending),"")) | Z17: =IF($B17="","",IF(AND(cfg_round_to<=0.5,IFERROR(VALUE(cfg_ending),0)>0),FLOOR($R17-VALUE(cfg_ending),1)+VALUE(cfg_ending),"")) | AA17: =IF($B17="","",IF(AND(cfg_round_to<=0.5,IFERROR(VALUE(cfg_ending),0)>0),VALUE(cfg_ending),0))
... A35: 30 | B35: =IF(OWNER_INPUTS!B35="","",OWNER_INPUTS!B35) | C35: =IF($B35="","",OWNER_INPUTS!C35) | D35: =IF($B35="","",OWNER_INPUTS!D35) | E35: =IF($B35="","",OWNER_INPUTS!E35) | F35: =IF($B35="","",OWNER_INPUTS!F35) | G35: =IF($B35="","",OWNER_INPUTS!G35/30) | H35: =IF($B35="","",IFERROR( IF(ISNUMBER(INDEX(cal_estimate,MATCH($B35,cal_items,0))), INDEX(cal_estimate,MATCH($B35,cal_items,0)), IFERROR(VLOOKUP($C35,tbl_priors,2,FALSE()), VLOOKUP("Other",tbl_priors,2,FALSE()))), IFERROR(VLOOKUP($C35,tbl_priors,2,FALSE()), VLOOKUP("Other",tbl_priors,2,FALSE())))) | I35: =IF($B35="","",IF(IFERROR(ISNUMBER(INDEX(cal_estimate,MATCH($B35,cal_items,0))),FALSE()),"Estimated","Prior")) | J35: =IF($B35="","",IF($I35="Estimated", IFERROR(INDEX(cal_conf,MATCH($B35,cal_items,0)),"LOW"),"LOW")) | K35: =IF($B35="","",IF($H35<-1,$E35*$H35/($H35+1),"test")) | L35: =IF($B35="","",IF($J35="HIGH",cfg_shr_high,IF($J35="MEDIUM",cfg_shr_med,cfg_shr_low))) | M35: =IF($B35="","",IF($K35="test", $F35*(1+IFERROR(VLOOKUP($D35,tbl_roles,4,FALSE()), VLOOKUP("Other",tbl_roles,4,FALSE()))), $F35+$L35*($K35-$F35))) | N35: =IF($B35="","",IFERROR(VLOOKUP($D35,tbl_roles,2,FALSE()),VLOOKUP("Other",tbl_roles,2,FALSE()))) | O35: =IF($B35="","",IFERROR(VLOOKUP($D35,tbl_roles,3,FALSE()),VLOOKUP("Other",tbl_roles,3,FALSE()))) | P35: =IF($B35="","",MIN($F35*(1+$N35),MAX($F35*(1+$O35),$M35))) | Q35: =IF($B35="","",MIN($F35*(1+cfg_max_raise),MAX($F35*(1+cfg_max_cut),$P35))) | R35: =IF($B35="","",IF(cfg_currency="IDR",IF($B35="","",IFERROR(IF(AND($Q35>INDEX(tbl_thr_idr,MATCH($Q35,INDEX(tbl_thr_idr,0,1),1),1),$Q35<=INDEX(tbl_thr_idr,MATCH($Q35,INDEX(tbl_thr_idr,0,1),1),1)+INDEX(tbl_thr_idr,MATCH($Q35,INDEX(tbl_thr_idr,0,1),1),2)),FLOOR(INDEX(tbl_thr_idr,MATCH($Q35,INDEX(tbl_thr_idr,0,1),1),1)-1,cfg_round_to),$Q35),$Q35)),IF($B35="","",IFERROR(IF(AND($Q35>INDEX(tbl_thr_usd,MATCH($Q35,INDEX(tbl_thr_usd,0,1),1),1),$Q35<=INDEX(tbl_thr_usd,MATCH($Q35,INDEX(tbl_thr_usd,0,1),1),1)+INDEX(tbl_thr_usd,MATCH($Q35,INDEX(tbl_thr_usd,0,1),1),2)),FLOOR(INDEX(tbl_thr_usd,MATCH($Q35,INDEX(tbl_thr_usd,0,1),1),1)-0.01,cfg_round_to),$Q35),$Q35)))) | S35: =IF($B35="","",cfg_round_to) | T35: =IF($B35="","",IF(N($AA35)=0,MIN(FLOOR($F35*(1+MIN($N35,cfg_max_raise)),$S35),MAX(CEILING($F35*(1+MAX($O35,cfg_max_cut)),$S35),MROUND($R35,$S35))),IF(SIGN(MIN(FLOOR($F35*(1+MIN($N35,cfg_max_raise)),$S35),MAX(CEILING($F35*(1+MAX($O35,cfg_max_cut)),$S35),MROUND($R35,$S35)))-$F35)>0,IF(AND(N($Y35)>=$F35,N($Y35)>=CEILING($F35*(1+MAX($O35,cfg_max_cut)),$S35),N($Y35)<=FLOOR($F35*(1+MIN($N35,cfg_max_raise)),$S35)),N($Y35),IF(AND(N($Z35)>$F35,N($Z35)>=CEILING($F35*(1+MAX($O35,cfg_max_cut)),$S35),N($Z35)<=FLOOR($F35*(1+MIN($N35,cfg_max_raise)),$S35)),N($Z35),MIN(FLOOR($F35*(1+MIN($N35,cfg_max_raise)),$S35),MAX(CEILING($F35*(1+MAX($O35,cfg_max_cut)),$S35),MROUND($R35,$S35))))),IF(SIGN(MIN(FLOOR($F35*(1+MIN($N35,cfg_max_raise)),$S35),MAX(CEILING($F35*(1+MAX($O35,cfg_max_cut)),$S35),MROUND($R35,$S35)))-$F35)<0,IF(AND(N($Z35)<=$F35,N($Z35)>=CEILING($F35*(1+MAX($O35,cfg_max_cut)),$S35),N($Z35)<=FLOOR($F35*(1+MIN($N35,cfg_max_raise)),$S35)),N($Z35),IF(AND(N($Y35)<$F35,N($Y35)>=CEILING($F35*(1+MAX($O35,cfg_max_cut)),$S35),N($Y35)<=FLOOR($F35*(1+MIN($N35,cfg_max_raise)),$S35)),N($Y35),MIN(FLOOR($F35*(1+MIN($N35,cfg_max_raise)),$S35),MAX(CEILING($F35*(1+MAX($O35,cfg_max_cut)),$S35),MROUND($R35,$S35))))),IF(ABS(N($Y35)-$F35)<=ABS(N($Z35)-$F35),IF(AND(N($Y35)>=CEILING($F35*(1+MAX($O35,cfg_max_cut)),$S35),N($Y35)<=FLOOR($F35*(1+MIN($N35,cfg_max_raise)),$S35)),N($Y35),MIN(FLOOR($F35*(1+MIN($N35,cfg_max_raise)),$S35),MAX(CEILING($F35*(1+MAX($O35,cfg_max_cut)),$S35),MROUND($R35,$S35)))),IF(AND(N($Z35)>=CEILING($F35*(1+MAX($O35,cfg_max_cut)),$S35),N($Z35)<=FLOOR($F35*(1+MIN($N35,cfg_max_raise)),$S35)),N($Z35),MIN(FLOOR($F35*(1+MIN($N35,cfg_max_raise)),$S35),MAX(CEILING($F35*(1+MAX($O35,cfg_max_cut)),$S35),MROUND($R35,$S35))))))))) | U35: =IF($B35="","",IFERROR($T35/$F35-1,0)) | V35: =IF($B35="","",$G35*($T35/$F35)^$H35) | W35: =IF($B35="","",($T35-$E35)*$V35-($F35-$E35)*$G35) | X35: =IF($B35="","",$W35*30) | Y35: =IF($B35="","",IF(AND(cfg_round_to<=0.5,IFERROR(VALUE(cfg_ending),0)>0),CEILING($R35-VALUE(cfg_ending),1)+VALUE(cfg_ending),"")) | Z35: =IF($B35="","",IF(AND(cfg_round_to<=0.5,IFERROR(VALUE(cfg_ending),0)>0),FLOOR($R35-VALUE(cfg_ending),1)+VALUE(cfg_ending),"")) | AA35: =IF($B35="","",IF(AND(cfg_round_to<=0.5,IFERROR(VALUE(cfg_ending),0)>0),VALUE(cfg_ending),0))
B36: TOTAL | W36: =SUM(W6:W35) -> 12.407735 | X36: =SUM(X6:X35) -> 372.23205
B37: Baseline monthly profit | X37: =SUMPRODUCT((N($F$6:$F$35)-N($E$6:$E$35))*N($G$6:$G$35))*30 -> 25860
B38: Lift % of monthly profit | X38: =IFERROR(X36/X37,0) -> 0.014394124

Sheet SENSITIVITY
A1: Sensitivity Analysis — Profit Lift Under Elasticity Scenarios
A3: Holds the recommended price (T) fixed and varies the elasticity by a multiplier. Conservative scenario assumes customers are MORE sensitive (e × 1.2), Optimistic assumes LESS sensitive (e × 0.8). If profit lift is positive across all three scenarios, the recommendation is robust.
A5: Conservative multiplier | B5: 1.2 | C5: Demand reacts MORE to price changes (e.g. -1.1 → -1.32). Lower projected lift.
A6: Baseline multiplier | B6: 1 | C6: Use the elasticity estimate as-is from OPTIMIZER.
A7: Optimistic multiplier | B7: 0.8 | C7: Demand reacts LESS to price changes (e.g. -1.1 → -0.88). Higher projected lift.
A9: # | B9: Item | C9: Current price | D9: Rec price | E9: Cost | F9: Daily qty | G9: Baseline e | H9: =CONCATENATE("ΔProfit Conservative (e×",TEXT($B$5,"0.0"),")") -> ΔProfit Conservative (e×1.2) | I9: =CONCATENATE("ΔProfit Baseline (e×",TEXT($B$6,"0.0"),")") -> ΔProfit Baseline (e×1.0) | J9: =CONCATENATE("ΔProfit Optimistic (e×",TEXT($B$7,"0.0"),")") -> ΔProfit Optimistic (e×0.8) | K9: Robust?
A10: 1 | B10: =IF(OPTIMIZER!B6="","",OPTIMIZER!B6) -> Flat White | C10: =IF($B10="","",OPTIMIZER!F6) -> 4.2 | D10: =IF($B10="","",OPTIMIZER!T6) -> 4.3 | E10: =IF($B10="","",OPTIMIZER!E6) -> 1 | F10: =IF($B10="","",OPTIMIZER!G6) -> 50 | G10: =IF($B10="","",OPTIMIZER!H6) -> -1.1 | H10: =IF($B10="","",IFERROR(((($D10-$E10)*$F10*($D10/$C10)^($G10*$B$5))-(($C10-$E10)*$F10))*30,0)) -> -1.3850701 | I10: =IF($B10="","",IFERROR(((($D10-$E10)*$F10*($D10/$C10)^($G10*$B$6))-(($C10-$E10)*$F10))*30,0)) -> 23.520374 | J10: =IF($B10="","",IFERROR(((($D10-$E10)*$F10*($D10/$C10)^($G10*$B$7))-(($C10-$E10)*$F10))*30,0)) -> 48.55508 | K10: =IF($B10="","",IF(AND(N($H10)>=0,N($I10)>=0,N($J10)>=0),"Yes","No")) -> No
A11: 2 | B11: =IF(OPTIMIZER!B7="","",OPTIMIZER!B7) -> Matcha Latte | C11: =IF($B11="","",OPTIMIZER!F7) -> 4.8 | D11: =IF($B11="","",OPTIMIZER!T7) -> 4.9 | E11: =IF($B11="","",OPTIMIZER!E7) -> 1.4 | F11: =IF($B11="","",OPTIMIZER!G7) -> 40 | G11: =IF($B11="","",OPTIMIZER!H7) -> -1.3 | H11: =IF($B11="","",IFERROR(((($D11-$E11)*$F11*($D11/$C11)^($G11*$B$5))-(($C11-$E11)*$F11))*30,0)) -> -12.9479 | I11: =IF($B11="","",IFERROR(((($D11-$E11)*$F11*($D11/$C11)^($G11*$B$6))-(($C11-$E11)*$F11))*30,0)) -> 8.914175 | J11: =IF($B11="","",IFERROR(((($D11-$E11)*$F11*($D11/$C11)^($G11*$B$7))-(($C11-$E11)*$F11))*30,0)) -> 30.893768 | K11: =IF($B11="","",IF(AND(N($H11)>=0,N($I11)>=0,N($J11)>=0),"Yes","No")) -> No
A12: 3 | B12: =IF(OPTIMIZER!B8="","",OPTIMIZER!B8) -> Eggs Benedict | C12: =IF($B12="","",OPTIMIZER!F8) -> 9.8 | D12: =IF($B12="","",OPTIMIZER!T8) -> 9.9 | E12: =IF($B12="","",OPTIMIZER!E8) -> 4.2 | F12: =IF($B12="","",OPTIMIZER!G8) -> 30 | G12: =IF($B12="","",OPTIMIZER!H8) -> -0.8 | H12: =IF($B12="","",IFERROR(((($D12-$E12)*$F12*($D12/$C12)^($G12*$B$5))-(($C12-$E12)*$F12))*30,0)) -> 40.24446 | I12: =IF($B12="","",IFERROR(((($D12-$E12)*$F12*($D12/$C12)^($G12*$B$6))-(($C12-$E12)*$F12))*30,0)) -> 48.503411 | J12: =IF($B12="","",IFERROR(((($D12-$E12)*$F12*($D12/$C12)^($G12*$B$7))-(($C12-$E12)*$F12))*30,0)) -> 56.775788 | K12: =IF($B12="","",IF(AND(N($H12)>=0,N($I12)>=0,N($J12)>=0),"Yes","No")) -> Yes
A13: 4 | B13: =IF(OPTIMIZER!B9="","",OPTIMIZER!B9) -> Avocado Toast | C13: =IF($B13="","",OPTIMIZER!F9) -> 10.5 | D13: =IF($B13="","",OPTIMIZER!T9) -> 10.7 | E13: =IF($B13="","",OPTIMIZER!E9) -> 4.5 | F13: =IF($B13="","",OPTIMIZER!G9) -> 35 | G13: =IF($B13="","",OPTIMIZER!H9) -> -0.8 | H13: =IF($B13="","",IFERROR(((($D13-$E13)*$F13*($D13/$C13)^($G13*$B$5))-(($C13-$E13)*$F13))*30,0)) -> 93.141092 | I13: =IF($B13="","",IFERROR(((($D13-$E13)*$F13*($D13/$C13)^($G13*$B$6))-(($C13-$E13)*$F13))*30,0)) -> 112.47088 | J13: =IF($B13="","",IFERROR(((($D13-$E13)*$F13*($D13/$C13)^($G13*$B$7))-(($C13-$E13)*$F13))*30,0)) -> 131.8591 | K13: =IF($B13="","",IF(AND(N($H13)>=0,N($I13)>=0,N($J13)>=0),"Yes","No")) -> Yes
A14: 5 | B14: =IF(OPTIMIZER!B10="","",OPTIMIZER!B10) -> Pancakes | C14: =IF($B14="","",OPTIMIZER!F10) -> 8.8 | D14: =IF($B14="","",OPTIMIZER!T10) -> 9.2 | E14: =IF($B14="","",OPTIMIZER!E10) -> 3.5 | F14: =IF($B14="","",OPTIMIZER!G10) -> 25 | G14: =IF($B14="","",OPTIMIZER!H10) -> -0.9 | H14: =IF($B14="","",IFERROR(((($D14-$E14)*$F14*($D14/$C14)^($G14*$B$5))-(($C14-$E14)*$F14))*30,0)) -> 99.614736 | I14: =IF($B14="","",IFERROR(((($D14-$E14)*$F14*($D14/$C14)^($G14*$B$6))-(($C14-$E14)*$F14))*30,0)) -> 132.3478 | J14: =IF($B14="","",IFERROR(((($D14-$E14)*$F14*($D14/$C14)^($G14*$B$7))-(($C14-$E14)*$F14))*30,0)) -> 165.34382 | K14: =IF($B14="","",IF(AND(N($H14)>=0,N($I14)>=0,N($J14)>=0),"Yes","No")) -> Yes
A15: 6 | B15: =IF(OPTIMIZER!B11="","",OPTIMIZER!B11) -> Cheesecake | C15: =IF($B15="","",OPTIMIZER!F11) -> 5.8 | D15: =IF($B15="","",OPTIMIZER!T11) -> 6.1 | E15: =IF($B15="","",OPTIMIZER!E11) -> 2.1 | F15: =IF($B15="","",OPTIMIZER!G11) -> 15 | G15: =IF($B15="","",OPTIMIZER!H11) -> -1 | H15: =IF($B15="","",IFERROR(((($D15-$E15)*$F15*($D15/$C15)^($G15*$B$5))-(($C15-$E15)*$F15))*30,0)) -> 29.29994 | I15: =IF($B15="","",IFERROR(((($D15-$E15)*$F15*($D15/$C15)^($G15*$B$6))-(($C15-$E15)*$F15))*30,0)) -> 46.47541 | J15: =IF($B15="","",IFERROR(((($D15-$E15)*$F15*($D15/$C15)^($G15*$B$7))-(($C15-$E15)*$F15))*30,0)) -> 63.824991 | K15: =IF($B15="","",IF(AND(N($H15)>=0,N($I15)>=0,N($J15)>=0),"Yes","No")) -> Yes
A16: 7 | B16: =IF(OPTIMIZER!B12="","",OPTIMIZER!B12) | C16: =IF($B16="","",OPTIMIZER!F12) | D16: =IF($B16="","",OPTIMIZER!T12) | E16: =IF($B16="","",OPTIMIZER!E12) | F16: =IF($B16="","",OPTIMIZER!G12) | G16: =IF($B16="","",OPTIMIZER!H12) | H16: =IF($B16="","",IFERROR(((($D16-$E16)*$F16*($D16/$C16)^($G16*$B$5))-(($C16-$E16)*$F16))*30,0)) | I16: =IF($B16="","",IFERROR(((($D16-$E16)*$F16*($D16/$C16)^($G16*$B$6))-(($C16-$E16)*$F16))*30,0)) | J16: =IF($B16="","",IFERROR(((($D16-$E16)*$F16*($D16/$C16)^($G16*$B$7))-(($C16-$E16)*$F16))*30,0)) | K16: =IF($B16="","",IF(AND(N($H16)>=0,N($I16)>=0,N($J16)>=0),"Yes","No"))
A17: 8 | B17: =IF(OPTIMIZER!B13="","",OPTIMIZER!B13) | C17: =IF($B17="","",OPTIMIZER!F13) | D17: =IF($B17="","",OPTIMIZER!T13) | E17: =IF($B17="","",OPTIMIZER!E13) | F17: =IF($B17="","",OPTIMIZER!G13) | G17: =IF($B17="","",OPTIMIZER!H13) | H17: =IF($B17="","",IFERROR(((($D17-$E17)*$F17*($D17/$C17)^($G17*$B$5))-(($C17-$E17)*$F17))*30,0)) | I17: =IF($B17="","",IFERROR(((($D17-$E17)*$F17*($D17/$C17)^($G17*$B$6))-(($C17-$E17)*$F17))*30,0)) | J17: =IF($B17="","",IFERROR(((($D17-$E17)*$F17*($D17/$C17)^($G17*$B$7))-(($C17-$E17)*$F17))*30,0)) | K17: =IF($B17="","",IF(AND(N($H17)>=0,N($I17)>=0,N($J17)>=0),"Yes","No"))
A18: 9 | B18: =IF(OPTIMIZER!B14="","",OPTIMIZER!B14) | C18: =IF($B18="","",OPTIMIZER!F14) | D18: =IF($B18="","",OPTIMIZER!T14) | E18: =IF($B18="","",OPTIMIZER!E14) | F18: =IF($B18="","",OPTIMIZER!G14) | G18: =IF($B18="","",OPTIMIZER!H14) | H18: =IF($B18="","",IFERROR(((($D18-$E18)*$F18*($D18/$C18)^($G18*$B$5))-(($C18-$E18)*$F18))*30,0)) | I18: =IF($B18="","",IFERROR(((($D18-$E18)*$F18*($D18/$C18)^($G18*$B$6))-(($C18-$E18)*$F18))*30,0)) | J18: =IF($B18="","",IFERROR(((($D18-$E18)*$F18*($D18/$C18)^($G18*$B$7))-(($C18-$E18)*$F18))*30,0)) | K18: =IF($B18="","",IF(AND(N($H18)>=0,N($I18)>=0,N($J18)>=0),"Yes","No"))
A19: 10 | B19: =IF(OPTIMIZER!B15="","",OPTIMIZER!B15) | C19: =IF($B19="","",OPTIMIZER!F15) | D19: =IF($B19="","",OPTIMIZER!T15) | E19: =IF($B19="","",OPTIMIZER!E15) | F19: =IF($B19="","",OPTIMIZER!G15) | G19: =IF($B19="","",OPTIMIZER!H15) | H19: =IF($B19="","",IFERROR(((($D19-$E19)*$F19*($D19/$C19)^($G19*$B$5))-(($C19-$E19)*$F19))*30,0)) | I19: =IF($B19="","",IFERROR(((($D19-$E19)*$F19*($D19/$C19)^($G19*$B$6))-(($C19-$E19)*$F19))*30,0)) | J19: =IF($B19="","",IFERROR(((($D19-$E19)*$F19*($D19/$C19)^($G19*$B$7))-(($C19-$E19)*$F19))*30,0)) | K19: =IF($B19="","",IF(AND(N($H19)>=0,N($I19)>=0,N($J19)>=0),"Yes","No"))
A20: 11 | B20: =IF(OPTIMIZER!B16="","",OPTIMIZER!B16) | C20: =IF($B20="","",OPTIMIZER!F16) | D20: =IF($B20="","",OPTIMIZER!T16) | E20: =IF($B20="","",OPTIMIZER!E16) | F20: =IF($B20="","",OPTIMIZER!G16) | G20: =IF($B20="","",OPTIMIZER!H16) | H20: =IF($B20="","",IFERROR(((($D20-$E20)*$F20*($D20/$C20)^($G20*$B$5))-(($C20-$E20)*$F20))*30,0)) | I20: =IF($B20="","",IFERROR(((($D20-$E20)*$F20*($D20/$C20)^($G20*$B$6))-(($C20-$E20)*$F20))*30,0)) | J20: =IF($B20="","",IFERROR(((($D20-$E20)*$F20*($D20/$C20)^($G20*$B$7))-(($C20-$E20)*$F20))*30,0)) | K20: =IF($B20="","",IF(AND(N($H20)>=0,N($I20)>=0,N($J20)>=0),"Yes","No"))
A21: 12 | B21: =IF(OPTIMIZER!B17="","",OPTIMIZER!B17) | C21: =IF($B21="","",OPTIMIZER!F17) | D21: =IF($B21="","",OPTIMIZER!T17) | E21: =IF($B21="","",OPTIMIZER!E17) | F21: =IF($B21="","",OPTIMIZER!G17) | G21: =IF($B21="","",OPTIMIZER!H17) | H21: =IF($B21="","",IFERROR(((($D21-$E21)*$F21*($D21/$C21)^($G21*$B$5))-(($C21-$E21)*$F21))*30,0)) | I21: =IF($B21="","",IFERROR(((($D21-$E21)*$F21*($D21/$C21)^($G21*$B$6))-(($C21-$E21)*$F21))*30,0)) | J21: =IF($B21="","",IFERROR(((($D21-$E21)*$F21*($D21/$C21)^($G21*$B$7))-(($C21-$E21)*$F21))*30,0)) | K21: =IF($B21="","",IF(AND(N($H21)>=0,N($I21)>=0,N($J21)>=0),"Yes","No"))
... A39: 30 | B39: =IF(OPTIMIZER!B35="","",OPTIMIZER!B35) | C39: =IF($B39="","",OPTIMIZER!F35) | D39: =IF($B39="","",OPTIMIZER!T35) | E39: =IF($B39="","",OPTIMIZER!E35) | F39: =IF($B39="","",OPTIMIZER!G35) | G39: =IF($B39="","",OPTIMIZER!H35) | H39: =IF($B39="","",IFERROR(((($D39-$E39)*$F39*($D39/$C39)^($G39*$B$5))-(($C39-$E39)*$F39))*30,0)) | I39: =IF($B39="","",IFERROR(((($D39-$E39)*$F39*($D39/$C39)^($G39*$B$6))-(($C39-$E39)*$F39))*30,0)) | J39: =IF($B39="","",IFERROR(((($D39-$E39)*$F39*($D39/$C39)^($G39*$B$7))-(($C39-$E39)*$F39))*30,0)) | K39: =IF($B39="","",IF(AND(N($H39)>=0,N($I39)>=0,N($J39)>=0),"Yes","No"))
B40: TOTAL | H40: =SUM(H10:H39) -> 247.96726 | I40: =SUM(I10:I39) -> 372.23205 | J40: =SUM(J10:J39) -> 497.25255
B41: Baseline check (vs OPTIMIZER) | I41: =opt_total_lift -> 372.23205 | K41: =IF(ABS(I40-I41)<0.01,"Match","MISMATCH") -> Match
B43: All scenarios positive? | H43: =IF(H40>=0,"Yes","No") -> Yes | I43: =IF(I40>=0,"Yes","No") -> Yes | J43: =IF(J40>=0,"Yes","No") -> Yes
B44: Recommendation robust? | H44: =IF(AND(H40>=0,I40>=0,J40>=0),"YES — all positive","NO — at least one negative scenario") -> YES — all positive

Sheet QA_CHECKS
A1: Pre-Delivery QA Checklist
A3: Internal validation. Before sending the report to a client, every row in the lower table must read "OK". Each row checks a different failure mode. The summary box at the top tells you whether the workbook is ready.
A5: Workbook status
A6: Items configured | B6: =COUNTA(OWNER_INPUTS!B6:B35) -> 6 | C6: Number of items with a name on OWNER_INPUTS.
A7: Items with HIGH confidence | B7: =COUNTIF(OPTIMIZER!J6:J35,"HIGH") -> 0 | C7: These items have CI cleanly excluding -1 — can be shipped "Now".
A8: Items with MEDIUM confidence | B8: =COUNTIF(OPTIMIZER!J6:J35,"MEDIUM") -> 0 | C8: Enough data but CI is wide — recommend pilot.
A9: Items with LOW confidence | B9: =COUNTIF(OPTIMIZER!J6:J35,"LOW") -> 6 | C9: No client data — using category priors. Test small.
A10: Demo mode active? | B10: =IF(cfg_use_sample="Yes","YES — DEMO","No — production") -> No — production | C10: Must be "No" before client delivery.
A12: Per-item validation
A13: Check | B13: Items with this issue | C13: Status | D13: Severity | E13: Action if fail
A14: Items missing a Category | B14: =SUMPRODUCT((OWNER_INPUTS!B6:B35<>"")*(OWNER_INPUTS!C6:C35="")) -> 0 | C14: =IF(B14=0,"OK","FLAG") -> OK | D14: Hard | E14: Set Category dropdown on OWNER_INPUTS for every named item. Without category, the prior fallback uses "Other".
A15: Items missing a Role | B15: =SUMPRODUCT((OWNER_INPUTS!B6:B35<>"")*(OWNER_INPUTS!D6:D35="")) -> 0 | C15: =IF(B15=0,"OK","FLAG") -> OK | D15: Hard | E15: Set Role dropdown. Role caps and test increments depend on it; missing role drops to "Other" with conservative caps.
A16: Items where Cost ≥ Current price | B16: =SUMPRODUCT((OWNER_INPUTS!B6:B35<>"")*(N(OWNER_INPUTS!E6:E35)>=N(OWNER_INPUTS!F6:F35))*(N(OWNER_INPUTS!F6:F35)>0)) -> 0 | C16: =IF(B16=0,"OK","FLAG") -> OK | D16: Hard | E16: A cost above the price means no margin. Verify cost figure with owner — sometimes the wrong number is entered.
A17: Items with zero or missing monthly units | B17: =SUMPRODUCT((OWNER_INPUTS!B6:B35<>"")*(N(OWNER_INPUTS!G6:G35)=0)) -> 0 | C17: =IF(B17=0,"OK","FLAG") -> OK | D17: Hard | E17: Profit lift cannot be computed without volume. Ask owner for approximate monthly units even ±20%.
A18: Items where role cap was the binding constraint (upward) | B18: =SUMPRODUCT((OPTIMIZER!B6:B35<>"")*(N(OPTIMIZER!M6:M35)>N(OPTIMIZER!F6:F35)*(1+N(OPTIMIZER!N6:N35)))) -> 1 | C18: =IF(B18=0,"OK","FLAG") -> FLAG | D18: Soft | E18: Shrunk target wanted more raise than role cap allows. Model is leaving margin on the table. Consider promoting role (Traffic Driver → Core, etc.) or running a pilot before next cycle.
A19: Items where role floor was the binding constraint (downward) | B19: =SUMPRODUCT((OPTIMIZER!B6:B35<>"")*(N(OPTIMIZER!M6:M35)<N(OPTIMIZER!F6:F35)*(1+N(OPTIMIZER!O6:O35)))) -> 0 | C19: =IF(B19=0,"OK","FLAG") -> OK | D19: Soft | E19: Cost-vs-price signal says cut more than the role allows. Sanity-check the cost number first.
A20: Items where elasticity CI crosses zero | B20: =SUMPRODUCT((OPTIMIZER!B6:B35<>"")*(OPTIMIZER!I6:I35="Estimated")*(N(CALIBRATION!I6:I35)>0)) -> 0 | C20: =IF(B20=0,"OK","FLAG") -> OK | D20: Soft | E20: CI upper bound > 0 means data cannot rule out an UPWARD-sloping demand curve. Treat as LOW-confidence regardless of N.
A21: Items recommended to move > 5% | B21: =SUMPRODUCT((OPTIMIZER!B6:B35<>"")*(ABS(N(OPTIMIZER!U6:U35))>0.05)) -> 1 | C21: =IF(B21=0,"OK","FLAG") -> FLAG | D21: Info | E21: Any single move above 5% deserves a written rationale in the client memo. Check the role label and confidence tier.
A22: Items with negative projected Δ profit | B22: =SUMPRODUCT((OPTIMIZER!B6:B35<>"")*(N(OPTIMIZER!X6:X35)<-0.001)) -> 0 | C22: =IF(B22=0,"OK","FLAG") -> OK | D22: Soft | E22: The model wants to cut and accept a profit loss now to defend volume. Worth challenging — usually a sign of bad cost data.
A23: Items where threshold pullback fired | B23: =SUMPRODUCT((OPTIMIZER!B6:B35<>"")*(ABS(N(OPTIMIZER!R6:R35)-N(OPTIMIZER!Q6:Q35))>0.001)) -> 2 | C23: =IF(B23=0,"OK","FLAG") -> FLAG | D23: Info | E23: These prices were pulled below a major price threshold (e.g. $10) — that is the psychology layer working as intended.
A24: Items below cost AND recommended to raise | B24: =SUMPRODUCT((OPTIMIZER!B6:B35<>"")*(N(OPTIMIZER!E6:E35)>=N(OPTIMIZER!F6:F35))*(N(OPTIMIZER!U6:U35)>0)) -> 0 | C24: =IF(B24=0,"OK","FLAG") -> OK | D24: Hard | E24: Item already sells below cost but model recommends raising further. Owner should fix the cost figure first OR consider removing the item entirely — repricing a loss-maker does not fix the loss.
A25: Model sanity
A26: Check | B26: Value | C26: Status | D26: Severity | E26: Notes
A27: All elasticities are negative | B27: =IF(SUMPRODUCT((OPTIMIZER!B6:B35<>"")*(N(OPTIMIZER!H6:H35)>=0))=0,"OK","FAIL") -> OK | C27: =B27 -> OK | D27: Hard | E27: Economic theory: an own-price elasticity must be negative.
A28: All recommended prices are positive | B28: =IF(SUMPRODUCT((OPTIMIZER!B6:B35<>"")*(N(OPTIMIZER!T6:T35)<=0))=0,"OK","FAIL") -> OK | C28: =B28 -> OK | D28: Hard | E28: Prices must be positive.
A29: All Δ% within global guardrails | B29: =IF(SUMPRODUCT((OPTIMIZER!B6:B35<>"")*((N(OPTIMIZER!U6:U35)>cfg_max_raise+0.0001)+(N(OPTIMIZER!U6:U35)<cfg_max_cut-0.0001)))=0,"OK","FAIL") -> OK | C29: =B29 -> OK | D29: Hard | E29: Output must respect SETTINGS guardrails.
A30: Baseline profit is positive | B30: =IF(opt_baseline>0,"OK","FAIL") -> OK | C30: =B30 -> OK | D30: Hard | E30: Cannot compute lift % if baseline is zero or negative. Check cost vs price.
A31: Lift % within sanity range (±20%) | B31: =IF(ABS(opt_lift_pct)<0.2,"OK","FAIL") -> OK | C31: =B31 -> OK | D31: Hard | E31: A single-pass model rarely improves profit > +20% honestly, AND rarely indicates a > -20% drop without bad inputs. If outside ±20%, the inputs are probably wrong.
A32: Overall confidence (weighted by ΔProfit) | B32: =IFERROR(IF(SUMPRODUCT(ABS(N(OPTIMIZER!X6:X35))*(OPTIMIZER!B6:B35<>""))>0,SUMPRODUCT(ABS(N(OPTIMIZER!X6:X35))*((OPTIMIZER!J6:J35="HIGH")*1+(OPTIMIZER!J6:J35="MEDIUM")*0.5+(OPTIMIZER!J6:J35="LOW")*0.25))/SUMPRODUCT(ABS(N(OPTIMIZER!X6:X35))*(OPTIMIZER!B6:B35<>"")),IF(COUNTIF(OPTIMIZER!B6:B35,"?*")>0,(COUNTIF(OPTIMIZER!J6:J35,"HIGH")*1+COUNTIF(OPTIMIZER!J6:J35,"MEDIUM")*0.5+COUNTIF(OPTIMIZER!J6:J35,"LOW")*0.25)/COUNTIF(OPTIMIZER!B6:B35,"?*"),0)),0) -> 0.25 | C32: =IF(B32>=0.85,"HIGH",IF(B32>=0.5,"MEDIUM","LOW")) -> LOW | D32: Info | E32: Weighted average of per-item confidence tiers (HIGH=1, MEDIUM=0.5, LOW=0.25), weighted by absolute ΔProfit. When all items are Holds (zero ΔProfit), falls back to an equal-weighted average. The OWNER_RESULTS headline uses this value. HIGH ≥ 0.85, MEDIUM ≥ 0.50, LOW < 0.50.
A33: Items recommended above local market range | B33: =COUNTIF(COMPETITOR_BENCHMARK!K9:K38,"Above market") -> 0 | C33: =IF(B33=0,"OK","FLAG") -> OK | D33: Info | E33: Recommendation exceeds local market max by more than the configured tolerance. Defensible if the item is a Star or Signature with strong product differentiation; flag if the item is a Traffic Driver.
A34: Items classified as Dog (low volume + low margin) | B34: =COUNTIF(MENU_ENGINEERING!K10:K39,"Dog") -> 2 | C34: =IF(B34=0,"OK","FLAG") -> FLAG | D34: Info | E34: Low-volume, low-margin items. Consider removal or repositioning. Repricing a Dog rarely moves total profit.
A35: Items losing money under Conservative elasticity scenario | B35: =COUNTIF(SENSITIVITY!H10:H39,"<0") -> 2 | C35: =IF(B35=0,"OK","FLAG") -> FLAG | D35: Soft | E35: These items show negative ΔProfit when elasticity is assumed 1.2× more sensitive. Their recommended raise is not robust to a more cautious demand assumption — consider pilot-testing first.
A36: Status summary
A37: Hard checks failing | B37: =SUMPRODUCT(($D14:$D24="Hard")*(($C14:$C24="FLAG")+($C14:$C24="FAIL")))+SUMPRODUCT(($D27:$D35="Hard")*(($C27:$C35="FLAG")+($C27:$C35="FAIL"))) -> 0 | C37: =IF(B37=0,"✓ Ready to deliver","✗ Fix before delivery") -> ✓ Ready to deliver
A38: Soft warnings | B38: =SUMPRODUCT(($D14:$D24="Soft")*(($C14:$C24="FLAG")+($C14:$C24="FAIL")))+SUMPRODUCT(($D27:$D35="Soft")*(($C27:$C35="FLAG")+($C27:$C35="FAIL"))) -> 2 | C38: =IF(B38=0,"All clear","Review before delivery") -> Review before delivery
A39: Info observations | B39: =SUMPRODUCT(($D14:$D24="Info")*(($C14:$C24="FLAG")+($C14:$C24="FAIL")))+SUMPRODUCT(($D27:$D35="Info")*(($C27:$C35="FLAG")+($C27:$C35="FAIL"))) -> 3 | C39: =IF(B39=0,"No notes","Worth mentioning") -> Worth mentioning
